Workbook

Sheet Spotswood College
A2: 1
A3: 1
A4: 1
A5: 1
A6: 1
A7: 1
A8: 1 | B8: Project: | C8: Spotswood College | K8: DK Roofing BOQ
A9: 1 | B9: Location:
C10: Building | D10: Timber | I10: 1
A11: 1 | B11: SN | C11: Description | D11: Type | E11: Girth | F11: Degree | G11: Location | H11: BMT | I11: Coating | J11: Specs | K11: Unit | L11: BOQ | M11: TAKEOFF | Q11: Qty | R11: MATERIAL | V11: LABOUR | AD11: TOTAL COST | AE11: For Markup | AF11: factor | AG11: Prelims | AH11: Margin | AJ11: Rate | AK11: Amount | AM11: Qty | AN11: Quantity Formula | AO11: Discrepancy | AP11: Remarks
A12: 1 | L12: QTY | M12: Qty | N12: Pitch F | O12: 0 | P12: Unit | R12: Rate | S12: Amount | T12: Total Material Cost | U12: Rate | V12: Amount | W12: Total Labour | AF12: =SUM(AF13) -> 0
A13: 1
A14: 1 | C14: ROOFING WORKS
A15: 1 | C15: Roof Sheeting
A16: 1 | C16: Supply and install 4311: DW Dimond advanced roofing system - 0.55mm BMT AM150 Zincalume Dimond BB900 TBC with Thermakraft 407 Covertek Roof Underlay, Dimond Ashgrid AG40 rail and AB40 post located above all purlins complete with EPDM thermal breaks., Dimond R1.8 75mm thermal BIB insulation over R2.4 95mm BIB insulation, Lap seal tape, and 0.55mm BMT Dimond BB900 TBC Zincalume Base Sheet, as per general notes (A002) | L16: =Q16 -> #REF! | Q16: =Q17 -> #REF! | S16: =T16/Q16 -> #REF! | T16: =SUM(S17:S35) -> #REF! | U16: =iferror(if(B16="",,VLOOKUP(B16,Data!$B$2:$F905,5,0)),"") | V16: =W16/Q16 -> #REF! | W16: =SUM(W17:W35) -> #REF! | X16: =W16/$AC$176/$W$183/$X$173 -> #REF! | Y16: =(T16+W16)=(SUM(AB17:AB34)) -> #REF! | Z16: =(T16+W16)-(SUM(AB17:AB34)) -> #REF! | AD16: =W16+T16 -> #REF! | AE16: =AD16 -> #REF! | AF16: =AE16/$AE$151 -> #REF! | AG16: =AF16*$AG$158 -> #REF! | AH16: =AF16*$AG$161 -> #REF! | AJ16: =ROUND(AK16/L16,2) -> #REF! | AK16: =ROUND(AH16+AG16+AD16,2) -> #REF!
B17: DRBB900Zinc055 | C17: 4311:01 - 0.55mm BMT AM150 Zincalume Dimond BB900 TBC @ 9 deg | D17: R-Sheeting | E17: =IFERROR(__xludf.DUMMYFUNCTION("IF($B$17:$B379="""","""", VLOOKUP( $B$17:$B379, QUERY( IMPORTRANGE(""1Ag27m9YF5mMfJh2E6NipJDFvPLlDI1p-s_1XEnzMHcc"",""Merge!F2:R""), ""select Col1, Col11"", 0 ), 2, FALSE ) ) "),"#REF!") -> #REF! | F17: =IFERROR(__xludf.DUMMYFUNCTION("IFERROR(REGEXEXTRACT(C17,""@\s*(\d+)\s*deg"")&""°"","""") "),"9°") -> 9° | H17: =IFERROR(__xludf.DUMMYFUNCTION("IFERROR(REGEXEXTRACT(C17, ""(\d*\.\d+)mm""), """")"),"0.55") -> 0.55 | J17: Specs | K17: m2 | L17: 602.91 | M17: =L17*E17 -> #REF! | N17: =IFERROR(__xludf.DUMMYFUNCTION("ARRAYFORMULA(IF( (B17:B148<>"""") * (F17:F148=""""), 1, IF( F17:F148="""", """", IFERROR(1/COS(RADIANS(REGEXEXTRACT(F17:F148,""(\d+)"")))) ) ))"),1.0124651257880029) -> 1.0124651 | O17: 1 | P17: 1 | Q17: =M17*N17*O17*P17 -> #REF! | R17: {=iferror(if(B17:B148="",,VLOOKUP(B17:B148,Data!$B$2:$K905,9,0)),"")} | S17: =R17*Q17 -> #REF! | U17: {=iferror(if(B17:B148="",,VLOOKUP(B17:B148,Data!$B$2:$K905,10,0)),"")} | W17: =U17*Q17 -> #REF! | X17: =W17/$AC$176/$W$183/Y17 -> #REF! | Y17: 10 | Z17: =Q17/X17 -> #REF! | AA17: =27*15/60/8 -> 0.84375 | AB17: =W17+S17 -> #REF! | AM17: {=IFERROR( IF(B17:B148="","", IF(D17:D148="Rain Head",L17:L148, IF(D17:D148="R-Accessories",L17:L148, IF(D17:D148="R-AdvFixing",L17:L148, IF(D17:D148="R-Angle Bar",L17:L148, IF(D17:D148="R-Butyl",L17:L148/12, IF(D17:D148="R-Comb Filler",L17:L148, IF(D17:D148="R-Dektite",L17:L148, IF(D17:D148="R-Dektite Fix",L17:L148*(ROUNDUP(E17:E148/0.05,0)+1), IF(D17:D148="R-Dektite Seal",L17:L148*(E17:E148/8), IF(D17:D148="R-DP",L17:L148, IF(D17:D148="R-DPC",L17:L148, IF(D17:D148="R-DPBracket",L17:L148, IF(D17:D148="R-EavesGut",L17:L148, IF(D17:D148="R-EGBracket",ROUNDUP(L17:L148/E17:E148,0)+1, IF(D17:D148="R-EGBracketFixing",ROUNDUP(L17:L148*E17:E148,0)+1, IF(D17:D148="R-ExpFoam",L17:L148, IF(D17:D148="R-Fascia",L17:L148, IF(D17:D148="R-FasciaBracket",ROUNDUP(L17:L148/E17:E148,0)+1, IF(D17:D148="R-FasciaBracketFixing",ROUNDUP(L17:L148/0.6,0)+1, IF(D17:D148="R-FFBottom",L17:L148, IF(D17:D148="R-FFSide",L17:L148, IF(D17:D148="R-FFTop",L17:L148, IF(D17:D148="R-Fixings",ROUNDUP(L17:L148*6,0)+1, IF(D17:D148="R-Flashing",L17:L148, IF(D17:D148="R-GenFix",ROUNDUP(L17:L148/0.6,0)+1, IF(D17:D148="R-Insulation",L17:L148, IF(D17:D148="R-KS",VLOOKUP(B17:B148,Data!B2:H905,6,0)*L17:L148, IF(D17:D148="R-KSFixing",ROUNDUP(L17:L148*6,0)+1, IF(D17:D148="R-LM",L17:L148, IF(D17:D148="R-m2",L17:L148*E17:E148, IF(D17:D148="R-OF",L17:L148, IF(D17:D148="R-OP",L17:L148, IF(D17:D148="R-OPFixing",L17:L148*10, IF(D17:D148="R-OPSeal",(L17:L148*3.14*E17:E148)/8, IF(D17:D148="R-PanFlashing",L17:L148, IF(D17:D148="R-PanFlash Fix",ROUNDUP((L17:L148*E17:E148)*8,0)+1, IF(D17:D148="R-Post",L17:L148/E17:E148, IF(D17:D148="R-PostFix",L17:L148, IF(D17:D148="R-Perforated ",ROUNDUP(L17:L148/E17:E148,0), IF(D17:D148="R-PerforatedFix",ROUNDUP(L17:L148*8,0)+1, IF(D17:D148="R-Rail",L17:L148, IF(D17:D148="R-Rainhead",L17:L148, IF(D17:D148="R-Ridge Vent",(L17:L148/(VLOOKUP(B17:B148,Data!B2:H905,6,0))), IF(D17:D148="R-Rivets",ROUNDUP(((L17:L148/5.7)+1)*(E17:E148/0.05),0), IF(D17:D148="R-RivetsEa",L17:L148, IF(D17:D148="R-RoofClips",ROUNDUP(L17:L148/E17:E148,0)+1, IF(D17:D148="R-Safety Mesh",L17:L148, IF(D17:D148="R-Scupper",L17:L148, IF(D17:D148="R-Sheeting",VLOOKUP(B17:B148,Data!B2:H905,6,0)*L17:L148, IF(D17:D148="R-Silicone",(ROUNDDOWN((L17:L148/5.7)+2,0)*E17:E148)/8, IF(D17:D148="R-Silicone LM",L17:L148/8, IF(D17:D148="R-SumpFixing",ROUNDUP((L17:L148*E17:E148)/0.05,0)+1, IF(D17:D148="R-SumpSeal",(L17:L148*E17:E148)/8, IF(D17:D148="R-Sump",L17:L148, IF(D17:D148="R-Takeoff ea",L17:L148, IF(D17:D148="R-Takeoff LM",L17:L148, IF(D17:D148="R-Takeoff m2",L17:L148*E17:E148, IF(D17:D148="R-Takeoff m3",L17:L148*E17:E148*H17:H148, IF(D17:D148="R-Timber ea",ROUNDUP(L17:L148/E17:E148,0)+1, IF(D17:D148="R-Timber LM",L17:L148, IF(D17:D148="R-Timber m2",L17:L148*E17:E148, IF(D17:D148="R-Timber eaFix",L17:L148*E17:E148, IF(D17:D148="R-TimberLMFix",ROUNDUP(L17:L148/1,0)+1, IF(D17:D148="R-Timberm2Fix",ROUNDUP(L17:L148*5,0)+1, IF(D17:D148="R-TopHatFixings",ROUNDUP(L17:L148/0.6,0)*2, IF(D17:D148="R-Trimmer/Packer",L17:L148, IF(D17:D148="R-TS",VLOOKUP(B17:B148,Data!B2:H905,6,0)*L17:L148, IF(D17:D148="R-TSFixing",(ROUNDUP(L17:L148/0.6,0)+1)*2, IF(D17:D148="R-TSLapSeal",L17:L148, IF(D17:D148="R-TSPurlinStrip",L17:L148/E17:E148, IF(D17:D148="R-TSStitching",L17:L148*2, IF(D17:D148="R-TPO",L17:L148, IF(D17:D148="R-TPO Gutter",L17:L148, IF(D17:D148="R-TU/TD",L17:L148, IF(D17:D148="R-UBracket",ROUNDUP(L17:L148/E17:E148,0)+1, IF(D17:D148="R-UBracketFix",ROUNDUP(L17:L148*E17:E148,0)+1, IF(D17:D148="R-Underlay",(L17:L148/(VLOOKUP(B17:B148,Data!B2:H905,6,0)-0.15))*0.15+L17:L148, IF(D17:D148="R-UTape",L17:L148/E17:E148/H17:H148, IF(D17:D148="R-Vent",(L17:L148/(VLOOKUP(B17:B148,Data!B2:H905,6,0))), IF(D17:D148="R-Valley Gutter",L17:L148, IF(D17:D148="R-VapBarrier",(L17:L148/(E17:E148-0.15))*0.15+L17:L148, IF(D17:D148="R-Washer",L17:L148, IF(D17:D148="R-ZFlashingFix",(L17:L148/E17:E148)*2, IF(D17:D148="W-Comb Filler",L17:L148, IF(D17:D148="W-DPC",L17:L148, IF(D17:D148="W-Fixings",ROUNDUP(L17:L148*6,0)+1, IF(D17:D148="W-Flashing",L17:L148, IF(D17:D148="W-GenFix",ROUNDUP(L17:L148/0.6,0)+1, IF(D17:D148="W-KS",VLOOKUP(B17:B148,Data!B2:H905,6,0)*L17:L148, IF(D17:D148="W-KSFixing",ROUNDUP(L17:L148*6,0)+1, IF(D17:D148="W-RAB",L17:L148, IF(D17:D148="W-RABFix",ROUNDUP(L17:L148*E17:E148,0)+1, IF(D17:D148="W-Rivets",ROUNDUP(((L17:L148/5.7)+1)*(E17:E148/0.05),0), IF(D17:D148="W-Silicone",(ROUNDDOWN((L17:L148/5.7)+2,0)*E17:E148)/8, IF(D17:D148="W-Silicone LM",L17:L148/8, IF(D17:D148="W-Sheeting",VLOOKUP(B17:B148,Data!B2:H905,6,0)*L17:L148, IF(D17:D148="W-Silicone",(ROUNDDOWN((L17:L148/5.7)+2,0)*E17:E148)/8, IF(D17:D148="W-Silicone LM",L17:L148/8, IF(D17:D148="W-Takeoff ea",L17:L148, IF(D17:D148="W-Takeoff LM",L17:L148, IF(D17:D148="W-Takeoff m2",L17:L148*E17:E148, IF(D17:D148="W-Timber LM",L17:L148, IF(D17:D148="W-Timber m2",L17:L148*E17:E148, IF(D17:D148="W-TimberLMFix",ROUNDUP(L17:L148/1,0)+1, IF(D17:D148="W-Timberm2Fix",ROUNDUP(L17:L148*5,0)+1, IF(D17:D148="W-TopHatFixings",ROUNDUP(L17:L148/0.6,0)*2, IF(D17:D148="W-Trimmer/Packer",L17:L148, IF(D17:D148="W-TimberLMFix",ROUNDUP(L17:L148/0.6,0)+1, IF(D17:D148="W-Timberm2Fix",ROUNDUP(L17:L148*8,0)+1, IF(D17:D148="W-Underlay",(L17:L148/(VLOOKUP(B17:B148,Data!B2:H905,6,0)-0.15))*0.15+L17:L148, IF(D17:D148="W-UTape",L17:L148/E17:E148/H17:H148, IF(D17:D148="W-Vent",(L17:L148/(VLOOKUP(B17:B148,Data!B2:H905,6,0))), 0 ))))))))))))))))))))))))))))))))))))))))))))))))))))))))))))))))))))))))))))))))))))))))))))))))))))))))))))))))), "" )} | AN17: {=if(B17:B148="",,if(M17:M148=AM17:AM148,"Matched","Mismatched"))} -> #REF! | AO17: {=if(AM17:AM148="","",AM17:AM148-M17:M148)}
N18: =IFERROR(__xludf.DUMMYFUNCTION("""COMPUTED_VALUE"""),"") | AB18: =W18+S18 -> 0
B19: DR75mmInsul | C19: Dimond R1.8 75mm thermal BIB insulation | D19: R-Insulation | F19: =F59 -> 9° | J19: Specs | K19: m2 | L19: 539.5 | M19: =L19 -> 539.5 | N19: =IFERROR(__xludf.DUMMYFUNCTION("""COMPUTED_VALUE"""),1.0124651257880029) -> 1.0124651 | O19: 1 | P19: 1 | Q19: =M19*N19*O19*P19 -> 546.22494 | S19: =R19*Q19 -> 0 | W19: =U19*Q19 -> 0 | AB19: =W19+S19 -> 0 | AM19: 539.5 | AN19: Matched | AO19: 0
B20: DR95mmInsul | C20: Dimond R2.4 95mm BIB insulation | D20: R-Insulation | F20: =F19 -> 9° | J20: Specs | K20: m2 | L20: =M19 -> 539.5 | M20: =L20 -> 539.5 | N20: =IFERROR(__xludf.DUMMYFUNCTION("""COMPUTED_VALUE"""),1.0124651257880029) -> 1.0124651 | O20: 1 | P20: 1 | Q20: =M20*N20*O20*P20 -> 546.22494 | S20: =R20*Q20 -> 0 | W20: =U20*Q20 -> 0 | AB20: =W20+S20 -> 0 | AM20: 539.5 | AN20: Matched | AO20: 0
N21: =IFERROR(__xludf.DUMMYFUNCTION("""COMPUTED_VALUE"""),"") | AB21: =W21+S21 -> 0
B22: DARSFixSt12x75 | C22: Top Sheet Fixing - STEEL 12X75 COLOUR X100 | D22: R-AdvFixing | F22: =F17 -> 9° | H22: =IFERROR(__xludf.DUMMYFUNCTION("IFERROR(REGEXEXTRACT(C22, ""(\d*\.\d+)mm""), """")"),"") | J22: Specs | K22: ea | L22: =M28 -> 676.68 | M22: 676.68 | N22: =IFERROR(__xludf.DUMMYFUNCTION("""COMPUTED_VALUE"""),1.0124651257880029) -> 1.0124651 | O22: 1 | P22: 1 | Q22: =M22*N22*O22*P22 -> 685.1149 | S22: =R22*Q22 -> 0 | W22: =U22*Q22 -> 0 | AB22: =W22+S22 -> 0 | AM22: 676.68 | AN22: Matched | AO22: 0
B23: DARSepdmWsh | C23: Top Sheet EPDM - EPDM SEALING WASH X100 | D23: R-AdvFixing | F23: =F22 -> 9° | J23: Specs | K23: LM | L23: =M28 -> 676.68 | M23: 676.68 | N23: =IFERROR(__xludf.DUMMYFUNCTION("""COMPUTED_VALUE"""),1.0124651257880029) -> 1.0124651 | AB23: =W23+S23 -> 0 | AM23: 676.68 | AN23: Matched | AO23: 0
B24: DARSPrWshrBB900 | C24: Top Sheet Profile Washer - ROOF WASHER BB900 x100 | D24: R-AdvFixing | F24: =F23 -> 9° | J24: Specs | K24: ea | L24: =M28 -> 676.68 | M24: 676.68 | N24: =IFERROR(__xludf.DUMMYFUNCTION("""COMPUTED_VALUE"""),1.0124651257880029) -> 1.0124651 | AB24: =W24+S24 -> 0 | AM24: 676.68 | AN24: Matched | AO24: 0
N25: =IFERROR(__xludf.DUMMYFUNCTION("""COMPUTED_VALUE"""),"") | AB25: =W25+S25 -> 0
B26: AG40rail | C26: 4311:03 - Ashgrid AG40 rail | D26: R-Rail | J26: Specs | K26: LM | L26: 676.68 | M26: 676.68 | N26: =IFERROR(__xludf.DUMMYFUNCTION("""COMPUTED_VALUE"""),1.0) -> 1 | O26: 1 | P26: 1 | Q26: =M26*N26*O26*P26 -> 676.68 | S26: =R26*Q26 -> 0 | W26: =U26*Q26 -> 0 | AB26: =W26+S26 -> 0 | AM26: 676.68 | AN26: Matched | AO26: 0
N27: =IFERROR(__xludf.DUMMYFUNCTION("""COMPUTED_VALUE"""),"") | AB27: =W27+S27 -> 0
B28: AB40post | C28: 4311:03 - AB40 post | D28: R-Post | E28: 1 | J28: Specs | K28: ea | L28: =M26 -> 676.68 | M28: =L28/E28 -> 676.68 | N28: =IFERROR(__xludf.DUMMYFUNCTION("""COMPUTED_VALUE"""),1.0) -> 1 | O28: 1 | P28: 1 | Q28: =M28*N28*O28*P28 -> 676.68 | S28: =R28*Q28 -> 0 | W28: =U28*Q28 -> 0 | AB28: =W28+S28 -> 0 | AM28: 676.68 | AN28: Matched | AO28: 0
B29: PostFixSt12x30 | C29: 4311:11 - Fixings 12g x 20mm tek (for steel purlins) to secure the post to purlins. STEEL 12X30 NO NEO X100 | D29: R-PostFix | J29: Specs | K29: ea | L29: =M28 -> 676.68 | M29: 676.68 | N29: =IFERROR(__xludf.DUMMYFUNCTION("""COMPUTED_VALUE"""),1.0) -> 1 | O29: 1 | P29: 2 | Q29: =M29*N29*O29*P29 -> 1353.36 | S29: =R29*Q29 -> 0 | W29: =U29*Q29 -> 0 | AB29: =W29+S29 -> 0 | AM29: 676.68 | AN29: Matched | AO29: 0
N30: =IFERROR(__xludf.DUMMYFUNCTION("""COMPUTED_VALUE"""),"") | AB30: =W30+S30 -> 0
B31: EPDMThrmBrks | C31: 4311:03 - EPDM thermal breaks | D31: R-Takeoff LM | J31: Specs | K31: LM | L31: =M26 -> 676.68 | M31: =L31 -> 676.68 | N31: =IFERROR(__xludf.DUMMYFUNCTION("""COMPUTED_VALUE"""),1.0) -> 1 | O31: 1 | P31: 1 | Q31: =M31*N31*O31*P31 -> 676.68 | S31: =R31*Q31 -> 0 | W31: =U31*Q31 -> 0 | AB31: =W31+S31 -> 0 | AM31: 676.68 | AN31: Matched | AO31: 0
N32: =IFERROR(__xludf.DUMMYFUNCTION("""COMPUTED_VALUE"""),"") | AB32: =W32+S32 -> 0
B33: DRBB900Maxam055 | C33: 4311:01 - 0.55bmt BB900 Maxam | D33: R-Sheeting | E33: =IFERROR(__xludf.DUMMYFUNCTION("IF($B$17:$B379="""","""", VLOOKUP( $B$17:$B379, QUERY( IMPORTRANGE(""1Ag27m9YF5mMfJh2E6NipJDFvPLlDI1p-s_1XEnzMHcc"",""Merge!F2:R""), ""select Col1, Col11"", 0 ), 2, FALSE ) ) "),"#REF!") -> #REF! | F33: 9° | H33: 0.55 | J33: Specs | K33: m2 | L33: =L17 -> 602.91 | M33: =L33*E33 -> #REF! | N33: =IFERROR(__xludf.DUMMYFUNCTION("""COMPUTED_VALUE"""),1.0124651257880029) -> 1.0124651 | O33: 1 | P33: 1 | Q33: =M33*N33*O33*P33 -> #REF! | S33: =R33*Q33 -> #REF! | W33: =U33*Q33 -> #REF! | AB33: =W33+S33 -> #REF! | AN33: #REF!
B34: LinerFixSt12x20 | C34: Liner Fixing - STEEL 12X20 PER X100 | J34: Specs | K34: ea | L34: 676.68 | M34: 676.68 | N34: =IFERROR(__xludf.DUMMYFUNCTION("""COMPUTED_VALUE"""),1.0) -> 1 | O34: 1 | P34: 1 | Q34: =M34*N34*O34*P34 -> 676.68 | S34: =R34*Q34 -> 0 | W34: =U34*Q34 -> 0 | AB34: =W34+S34 -> 0 | AM34: 0 | AN34: Mismatched | AO34: -676.68
N35: =IFERROR(__xludf.DUMMYFUNCTION("""COMPUTED_VALUE"""),"")
A36: 1 | C36: Supply and install 4311: DW Dimond advanced roofing system - 0.55mm BMT AM150 Zincalume Dimond BB900 TBC with Thermakraft 407 Covertek Roof Underlay, Dimond Ashgrid AG40 rail and AB40 post located above all purlins complete with EPDM thermal breaks., Dimond R1.8 75mm thermal BIB insulation over R2.4 95mm BIB insulation, Lap seal tape, and 0.55mm BMT Dimond BB900 TBC Zincalume Base Sheet, as per general notes (A002) | L36: =Q36 -> #REF! | N36: =IFERROR(__xludf.DUMMYFUNCTION("""COMPUTED_VALUE"""),"") | Q36: =Q37 -> #REF! | S36: =T36/Q36 -> #REF! | T36: =SUM(S37:S55) -> #REF! | V36: =W36/Q36 -> #REF! | W36: =SUM(W37:W55) -> #REF! | X36: =W36/$AC$176/$W$183/$X$173 -> #REF! | Y36: =(T36+W36)=(SUM(AB37:AB55)) -> #REF! | Z36: =(T36+W36)-(SUM(AB37:AB55)) -> #REF! | AD36: =W36+T36 -> #REF! | AE36: =AD36 -> #REF! | AF36: =AE36/$AE$151 -> #REF! | AG36: =AF36*$AG$158 -> #REF! | AH36: =AF36*$AG$161 -> #REF! | AJ36: =ROUND(AK36/L36,2) -> #REF! | AK36: =ROUND(AH36+AG36+AD36,2) -> #REF!
B37: DRBB900Zinc055 | C37: 4311:01 - 0.55mm BMT AM150 Zincalume Dimond BB900 TBC @ 5 deg | D37: R-Sheeting | E37: =IFERROR(__xludf.DUMMYFUNCTION("IF($B$17:$B379="""","""", VLOOKUP( $B$17:$B379, QUERY( IMPORTRANGE(""1Ag27m9YF5mMfJh2E6NipJDFvPLlDI1p-s_1XEnzMHcc"",""Merge!F2:R""), ""select Col1, Col11"", 0 ), 2, FALSE ) ) "),"#REF!") -> #REF! | F37: =IFERROR(__xludf.DUMMYFUNCTION("IFERROR(REGEXEXTRACT(C37,""@\s*(\d+)\s*deg"")&""°"","""") "),"5°") -> 5° | H37: =IFERROR(__xludf.DUMMYFUNCTION("IFERROR(REGEXEXTRACT(C37, ""(\d*\.\d+)mm""), """")"),"0.55") -> 0.55 | J37: Specs | K37: m2 | L37: 1029.42 | M37: =L37*E37 -> #REF! | N37: =IFERROR(__xludf.DUMMYFUNCTION("""COMPUTED_VALUE"""),1.0038198375433474) -> 1.0038198 | O37: 1 | P37: 1 | Q37: =M37*N37*O37*P37 -> #REF! | S37: =R37*Q37 -> #REF! | W37: =U37*Q37 -> #REF! | X37: =W37/$AC$176/$W$183/Y37 -> #REF! | Y37: 10 | Z37: =Q37/X37 -> #REF! | AA37: =27*15/60/8 -> 0.84375 | AB37: =W37+S37 -> #REF! | AN37: #REF!
N38: =IFERROR(__xludf.DUMMYFUNCTION("""COMPUTED_VALUE"""),"") | AB38: =W38+S38 -> 0
B39: DR75mmInsul | C39: Dimond R1.8 75mm thermal BIB insulation | D39: R-Insulation | F39: =F61 -> 5° | J39: Specs | K39: m2 | L39: 921.66 | M39: 921.66 | N39: =IFERROR(__xludf.DUMMYFUNCTION("""COMPUTED_VALUE"""),1.0038198375433474) -> 1.0038198 | O39: 1 | P39: 1 | Q39: =M39*N39*O39*P39 -> 925.18059 | S39: =R39*Q39 -> 0 | W39: =U39*Q39 -> 0 | AB39: =W39+S39 -> 0 | AM39: 921.66 | AN39: Matched | AO39: 0
B40: DR95mmInsul | C40: Dimond R2.4 95mm BIB insulation | D40: R-Insulation | F40: =F39 -> 5° | J40: Specs | K40: m2 | L40: =M39 -> 921.66 | M40: 921.66 | N40: =IFERROR(__xludf.DUMMYFUNCTION("""COMPUTED_VALUE"""),1.0038198375433474) -> 1.0038198 | O40: 1 | P40: 1 | Q40: =M40*N40*O40*P40 -> 925.18059 | S40: =R40*Q40 -> 0 | W40: =U40*Q40 -> 0 | AB40: =W40+S40 -> 0 | AM40: 921.66 | AN40: Matched | AO40: 0
N41: =IFERROR(__xludf.DUMMYFUNCTION("""COMPUTED_VALUE"""),"") | AB41: =W41+S41 -> 0
B42: DARSFixSt12x75 | C42: Top Sheet Fixing - STEEL 12X75 COLOUR X100 | D42: R-AdvFixing | F42: =F40 -> 5° | J42: Specs | K42: ea | L42: 1071.41 | M42: 1071.41 | N42: =IFERROR(__xludf.DUMMYFUNCTION("""COMPUTED_VALUE"""),1.0038198375433474) -> 1.0038198 | AB42: =W42+S42 -> 0 | AM42: 1071.41 | AN42: Matched | AO42: 0
B43: DARSepdmWsh | C43: Top Sheet EPDM - EPDM SEALING WASH X100 | D43: R-AdvFixing | F43: =F42 -> 5° | H43: =IFERROR(__xludf.DUMMYFUNCTION("IFERROR(REGEXEXTRACT(C43, ""(\d*\.\d+)mm""), """")"),"") | J43: Specs | K43: LM | L43: =M48 -> 1071.41 | M43: =M48 -> 1071.41 | N43: =IFERROR(__xludf.DUMMYFUNCTION("""COMPUTED_VALUE"""),1.0038198375433474) -> 1.0038198 | O43: 1 | P43: 1 | Q43: =M43*N43*O43*P43 -> 1075.5026 | S43: =R43*Q43 -> 0 | W43: =U43*Q43 -> 0 | AB43: =W43+S43 -> 0 | AM43: 1071.41 | AN43: Matched | AO43: 0
B44: DARSPrWshrBB900 | C44: Top Sheet Profile Washer - ROOF WASHER BB900 x100 | D44: R-AdvFixing | F44: =F43 -> 5° | J44: Specs | K44: ea | L44: 1071.41 | M44: 1071.41 | N44: =IFERROR(__xludf.DUMMYFUNCTION("""COMPUTED_VALUE"""),1.0038198375433474) -> 1.0038198 | AB44: =W44+S44 -> 0 | AM44: 1071.41 | AN44: Matched | AO44: 0
N45: =IFERROR(__xludf.DUMMYFUNCTION("""COMPUTED_VALUE"""),"") | AB45: =W45+S45 -> 0
B46: AG40rail | C46: 4311:03 - Ashgrid AG40 rail | D46: R-Rail | J46: Specs | K46: LM | L46: 1071.41 | M46: 1071.41 | N46: =IFERROR(__xludf.DUMMYFUNCTION("""COMPUTED_VALUE"""),1.0) -> 1 | O46: 1 | P46: 1 | Q46: =M46*N46*O46*P46 -> 1071.41 | S46: =R46*Q46 -> 0 | W46: =U46*Q46 -> 0 | AB46: =W46+S46 -> 0 | AM46: 1071.41 | AN46: Matched | AO46: 0
N47: =IFERROR(__xludf.DUMMYFUNCTION("""COMPUTED_VALUE"""),"") | AB47: =W47+S47 -> 0
B48: AB40post | C48: 4311:03 - AB40 post | D48: R-Post | E48: 1 | J48: Specs | K48: ea | L48: =M46 -> 1071.41 | M48: =L48/E48 -> 1071.41 | N48: =IFERROR(__xludf.DUMMYFUNCTION("""COMPUTED_VALUE"""),1.0) -> 1 | O48: 1 | P48: 1 | Q48: =M48*N48*O48*P48 -> 1071.41 | S48: =R48*Q48 -> 0 | W48: =U48*Q48 -> 0 | AB48: =W48+S48 -> 0 | AM48: 1071.41 | AN48: Matched | AO48: 0
B49: =IFERROR(__xludf.DUMMYFUNCTION("IFERROR( IF(C49="""","""", IF(OR(REGEXMATCH(D49,""(?i)-Flashing""), REGEXMATCH(D49,""(?i)-EavesGut""), REGEXMATCH(D49,""(?i)Valley"")), ""DR"" & TEXT( ROUNDUP( MIN( VALUE(MID(C49, FIND("&"""("",C49)+1, FIND(""/"",C49)-FIND(""("",C49)-1)), 1200 ) / 50, 0 ) * 50, ""0"" ) & MID(C49, FIND(""/"",C49)+1, FIND("")"",C49)-FIND(""/"",C49)-1) & TEXT(H49*100,""0"") & I49,"&" IF(AND(D49=""Roof Sheet"", REGEXMATCH(C49,""(?i)KS\d{4}[A-Z]{2}"")), REGEXEXTRACT(C49,""(?i)KS\d{4}[A-Z]{2}""), IF(AND(REGEXMATCH(D49,""(?i)-DP""), REGEXMATCH(C49,""(?i)Downpipe"")), ""dp"" & REGEXEXTRACT(C49,""(\d+)"") & ""mm"", "&" IF(AND(REGEXMATCH(D49,""(?i)Bracket""), REGEXMATCH(C49,""(?i)Bracket"")), ""Brkt"" & REGEXEXTRACT(C49,""(\d+)"") & ""mm"", IF(AND(REGEXMATCH(D49,""(?i)-OP""), REGEXMATCH(C49,""(?i)pops"")), ""op"" & REGEXEXTRACT(C49,""(\d+)"") & ""mm"""&", IF(OR(D49=""R-FFTop"", D49=""R-FFBottom"", D49=""R-FFSide""), IF(REGEXMATCH(C49,""(?i)Profiled.*Top|Top.*Profiled""),""pfft"", IF(REGEXMATCH(C49,""(?i)Profiled.*Bottom|Bottom.*Profiled""),""pffb"", IF(REGEXMATCH(C49,""(?i)Squ"&"are""),""sff"",""""))), IF(REGEXMATCH(D49,""(?i)-Rivets""),""Rvt"", IF(REGEXMATCH(D49,""(?i)Silicone""),""300ml"", IF(REGEXMATCH(D49,""(?i)R-Butyl""),""300ml"", IF(REGEXMATCH(D49,""(?i)Fix""),""GenFix"", IF(AND(REGEXMATCH(C49,""(?i)Tim"&"ber""), REGEXMATCH(D49,""(?i)Timber"")),""tp"", IF(AND(REGEXMATCH(C49,""(?i)Vent G1275""), REGEXMATCH(D49,""(?i)Comb FIller"")),""CFV1275"", IF(REGEXMATCH(C49,""(?i)DPC""),""dpc"", IF(REGEXMATCH(C49,""(?i)Concealed Clips""),""ConClips"", I"&"F(REGEXMATCH(D49,""(?i)-Takeoff ea""),""Takeoff ea"", IF(REGEXMATCH(D49,""(?i)-Takeoff LM""),""Takeoff LM"", IF(REGEXMATCH(D49,""(?i)-Takeoff m2""),""Takeoff m2"", IF(D49=""R-TU/TD"",""TU/TD"",""""))))))))))))))))) )))"),"GenFix") -> GenFix | C49: 4311:11 - Fixings 12g x 20mm tek (for steel purlins) to secure the post to purlins | D49: R-PostFix | J49: Specs | K49: ea | L49: =M48 -> 1071.41 | M49: =M48 -> 1071.41 | N49: =IFERROR(__xludf.DUMMYFUNCTION("""COMPUTED_VALUE"""),1.0) -> 1 | O49: 1 | P49: 2 | Q49: =M49*N49*O49*P49 -> 2142.82 | S49: =R49*Q49 -> 0 | W49: =U49*Q49 -> 0 | AB49: =W49+S49 -> 0 | AM49: 1071.41 | AN49: Matched | AO49: 0
N50: =IFERROR(__xludf.DUMMYFUNCTION("""COMPUTED_VALUE"""),"") | AB50: =W50+S50 -> 0
B51: EPDMThrmBrks | C51: 4311:03 - EPDM thermal breaks | D51: R-Takeoff LM | J51: Specs | K51: LM | L51: =M46 -> 1071.41 | M51: =M46 -> 1071.41 | N51: =IFERROR(__xludf.DUMMYFUNCTION("""COMPUTED_VALUE"""),1.0) -> 1 | O51: 1 | P51: 1 | Q51: =M51*N51*O51*P51 -> 1071.41 | S51: =R51*Q51 -> 0 | W51: =U51*Q51 -> 0 | AB51: =W51+S51 -> 0 | AM51: 1071.41 | AN51: Matched | AO51: 0
N52: =IFERROR(__xludf.DUMMYFUNCTION("""COMPUTED_VALUE"""),"") | AB52: =W52+S52 -> 0
B53: DRBB900Maxam055 | C53: 4311:01 - 0.55bmt BB900 Maxam | D53: R-Sheeting | E53: =IFERROR(__xludf.DUMMYFUNCTION("IF($B$17:$B379="""","""", VLOOKUP( $B$17:$B379, QUERY( IMPORTRANGE(""1Ag27m9YF5mMfJh2E6NipJDFvPLlDI1p-s_1XEnzMHcc"",""Merge!F2:R""), ""select Col1, Col11"", 0 ), 2, FALSE ) ) "),"#REF!") -> #REF! | F53: =F37 -> 5° | H53: 0.55 | J53: Specs | K53: m2 | L53: =L37 -> 1029.42 | M53: =L53*E53 -> #REF! | N53: =IFERROR(__xludf.DUMMYFUNCTION("""COMPUTED_VALUE"""),1.0038198375433474) -> 1.0038198 | O53: 1 | P53: 1 | Q53: =M53*N53*O53*P53 -> #REF! | S53: =R53*Q53 -> #REF! | W53: =U53*Q53 -> #REF! | AB53: =W53+S53 -> #REF! | AN53: #REF!
B54: LinerFixSt12x20 | C54: Liner Fixing - STEEL 12X20 PER X100 | J54: Specs | K54: ea | L54: 1071.41 | M54: 1071.41 | N54: =IFERROR(__xludf.DUMMYFUNCTION("""COMPUTED_VALUE"""),1.0) -> 1 | O54: 1 | P54: 1 | Q54: =M54*N54*O54*P54 -> 1071.41 | S54: =R54*Q54 -> 0 | W54: =U54*Q54 -> 0 | AB54: =W54+S54 -> 0 | AM54: 0 | AN54: Mismatched | AO54: -1071.41
N55: =IFERROR(__xludf.DUMMYFUNCTION("""COMPUTED_VALUE"""),"")
A56: 1 | C56: Underlay | N56: =IFERROR(__xludf.DUMMYFUNCTION("""COMPUTED_VALUE"""),"")
A57: 1 | C57: Supply and install underlay | L57: =Q57 -> #REF! | N57: =IFERROR(__xludf.DUMMYFUNCTION("""COMPUTED_VALUE"""),"") | Q57: =Q58 -> #REF! | S57: =T57/Q57 -> #REF! | T57: =SUM(S58:S62) -> #REF! | V57: =W57/Q57 -> #REF! | W57: =SUM(W58:W62) -> #REF! | X57: =W57/$AC$176/$W$183/$X$173 -> #REF! | Y57: =(T57+W57)=(SUM(AB58:AB62)) -> #REF! | Z57: =(T57+W57)-(SUM(AB58:AB62)) -> #REF! | AD57: =W57+T57 -> #REF! | AE57: =AD57 -> #REF! | AF57: =AE57/$AE$151 -> #REF! | AG57: =AF57*$AG$158 -> #REF! | AH57: =AF57*$AG$161 -> #REF! | AJ57: =ROUND(AK57/L57,2) -> #REF! | AK57: =ROUND(AH57+AG57+AD57,2) -> #REF!
B58: TKUF407 | C58: 4311:02 - Thermakraft 407 Covertek Roof Underlay | D58: R-Underlay | E58: =IFERROR(__xludf.DUMMYFUNCTION("IF($B$17:$B379="""","""", VLOOKUP( $B$17:$B379, QUERY( IMPORTRANGE(""1Ag27m9YF5mMfJh2E6NipJDFvPLlDI1p-s_1XEnzMHcc"",""Merge!F2:R""), ""select Col1, Col11"", 0 ), 2, FALSE ) ) "),"#REF!") -> #REF! | F58: =F17 -> 9° | H58: =IFERROR(__xludf.DUMMYFUNCTION("IFERROR(REGEXEXTRACT(C58, ""(\d*\.\d+)mm""), """")"),"") | J58: Specs | K58: m2 | L58: =M17 -> #REF! | M58: =(M17/(E58-0.15))*0.15+M17 -> #REF! | N58: =IFERROR(__xludf.DUMMYFUNCTION("""COMPUTED_VALUE"""),1.0124651257880029) -> 1.0124651 | O58: 1 | P58: 1 | Q58: =M58*N58*O58*P58 -> #REF! | S58: =R58*Q58 -> #REF! | W58: =U58*Q58 -> #REF! | AB58: =W58+S58 -> #REF! | AN58: #REF!
B59: TKGenTape | C59: Thermakraft White General Purpose Tape (60 mm × 66 m) | D59: R-UTape | E59: =E58 -> #REF! | F59: =F58 -> 9° | H59: =IFERROR(__xludf.DUMMYFUNCTION("IF($B$17:$B379="""","""", VLOOKUP( $B$17:$B379, QUERY( IMPORTRANGE(""1Ag27m9YF5mMfJh2E6NipJDFvPLlDI1p-s_1XEnzMHcc"",""Merge!F2:R""), ""select Col1, Col11"", 0 ), 2, FALSE ) ) "),"#REF!") -> #REF! | J59: No Specs | K59: ea | L59: =M58 -> #REF! | M59: =M58/E59/H59 -> #REF! | N59: =IFERROR(__xludf.DUMMYFUNCTION("""COMPUTED_VALUE"""),1.0124651257880029) -> 1.0124651 | O59: 1 | P59: 1 | Q59: =M59*N59*O59*P59 -> #REF! | S59: =R59*Q59 -> #REF! | W59: =U59*Q59 -> #REF! | AB59: =W59+S59 -> #REF! | AN59: #REF!
B60: TKUF407 | C60: 4311:02 - Thermakraft 407 Covertek Roof Underlay | D60: R-Underlay | E60: =IFERROR(__xludf.DUMMYFUNCTION("IF($B$17:$B379="""","""", VLOOKUP( $B$17:$B379, QUERY( IMPORTRANGE(""1Ag27m9YF5mMfJh2E6NipJDFvPLlDI1p-s_1XEnzMHcc"",""Merge!F2:R""), ""select Col1, Col11"", 0 ), 2, FALSE ) ) "),"#REF!") -> #REF! | F60: 5° | H60: =IFERROR(__xludf.DUMMYFUNCTION("IFERROR(REGEXEXTRACT(C60, ""(\d*\.\d+)mm""), """")"),"") | J60: Specs | K60: m2 | L60: =M43 -> 1071.41 | M60: 1352.7904 | N60: =IFERROR(__xludf.DUMMYFUNCTION("""COMPUTED_VALUE"""),1.0038198375433474) -> 1.0038198 | O60: 1 | P60: 1 | Q60: =M60*N60*O60*P60 -> 1357.9578 | S60: =R60*Q60 -> 0 | W60: =U60*Q60 -> 0 | AB60: =W60+S60 -> 0 | AN60: Mismatched
B61: TKGenTape | C61: Thermakraft White General Purpose Tape (60 mm × 66 m) | D61: R-UTape | E61: =E60 -> #REF! | F61: =F60 -> 5° | H61: =IFERROR(__xludf.DUMMYFUNCTION("IF($B$17:$B379="""","""", VLOOKUP( $B$17:$B379, QUERY( IMPORTRANGE(""1Ag27m9YF5mMfJh2E6NipJDFvPLlDI1p-s_1XEnzMHcc"",""Merge!F2:R""), ""select Col1, Col11"", 0 ), 2, FALSE ) ) "),"#REF!") -> #REF! | J61: No Specs | K61: ea | L61: =M60 -> 1352.7904 | M61: =M60/E61/H61 -> #REF! | N61: =IFERROR(__xludf.DUMMYFUNCTION("""COMPUTED_VALUE"""),1.0038198375433474) -> 1.0038198 | O61: 1 | P61: 1 | Q61: =M61*N61*O61*P61 -> #REF! | S61: =R61*Q61 -> #REF! | W61: =U61*Q61 -> #REF! | AB61: =W61+S61 -> #REF! | AN61: #REF!
N62: =IFERROR(__xludf.DUMMYFUNCTION("""COMPUTED_VALUE"""),"") | AB62: =W62+S62 -> 0
A63: 1 | C63: Safety mesh | N63: =IFERROR(__xludf.DUMMYFUNCTION("""COMPUTED_VALUE"""),"")
A64: 1 | C64: Supply and install safety mesh | L64: =Q64 -> #REF! | N64: =IFERROR(__xludf.DUMMYFUNCTION("""COMPUTED_VALUE"""),"") | Q64: =Q65 -> #REF! | S64: =T64/Q64 -> #REF! | T64: =SUM(S65:S67) -> #REF! | V64: =W64/Q64 -> #REF! | W64: =SUM(W65:W67) -> #REF! | X64: =W64/$AC$176/$W$183/$X$173 -> #REF! | Y64: =(T64+W64)=(SUM(AB65:AB67)) -> #REF! | Z64: =(T64+W64)-(SUM(AB65:AB67)) -> #REF! | AD64: =W64+T64 -> #REF! | AE64: =AD64 -> #REF! | AF64: =AE64/$AE$151 -> #REF! | AG64: =AF64*$AG$158 -> #REF! | AH64: =AF64*$AG$161 -> #REF! | AJ64: =ROUND(AK64/L64,2) -> #REF! | AK64: =ROUND(AH64+AG64+AD64,2) -> #REF!
B65: Safetymesh | C65: Safety mesh | D65: R-Safety Mesh | F65: =F59 -> 9° | H65: =IFERROR(__xludf.DUMMYFUNCTION("IFERROR(REGEXEXTRACT(C65, ""(\d*\.\d+)mm""), """")"),"") | J65: No Specs | K65: m2 | L65: =M58 -> #REF! | M65: =M58 -> #REF! | N65: =IFERROR(__xludf.DUMMYFUNCTION("""COMPUTED_VALUE"""),1.0124651257880029) -> 1.0124651 | O65: 1 | P65: 1 | Q65: =M65*N65*O65*P65 -> #REF! | S65: =R65*Q65 -> #REF! | W65: =U65*Q65 -> #REF! | X65: =W65/$AC$176/$W$183/Y65 -> #REF! | Y65: 4 | Z65: =Q65/X65 -> #REF! | AB65: =W65+S65 -> #REF! | AN65: #REF!
B66: Safetymesh | C66: Safety mesh | D66: R-Safety Mesh | F66: =F61 -> 5° | H66: =IFERROR(__xludf.DUMMYFUNCTION("IFERROR(REGEXEXTRACT(C66, ""(\d*\.\d+)mm""), """")"),"") | J66: No Specs | K66: m2 | L66: =M60 -> 1352.7904 | M66: 1352.7904 | N66: =IFERROR(__xludf.DUMMYFUNCTION("""COMPUTED_VALUE"""),1.0038198375433474) -> 1.0038198 | O66: 1 | P66: 1 | Q66: =M66*N66*O66*P66 -> 1357.9578 | S66: =R66*Q66 -> 0 | W66: =U66*Q66 -> 0 | X66: =W66/$AC$176/$W$183/Y66 -> #REF! | Y66: 4 | Z66: =Q66/X66 -> #REF! | AB66: =W66+S66 -> 0 | AM66: 1352.7904 | AN66: Matched | AO66: 0
N67: =IFERROR(__xludf.DUMMYFUNCTION("""COMPUTED_VALUE"""),"") | AB67: =W67+S67 -> 0
A68: 1 | C68: Flashing/Capping | N68: =IFERROR(__xludf.DUMMYFUNCTION("""COMPUTED_VALUE"""),"")
A69: 1 | C69: Supply and install 0.55mm BMT Coloursteel Maxam ridge cap flashing, as per detail 5 (A502) | L69: =Q69 -> 56.39 | N69: =IFERROR(__xludf.DUMMYFUNCTION("""COMPUTED_VALUE"""),"") | Q69: =Q70 -> 56.39 | S69: =T69/Q69 -> 0 | T69: =SUM(S70:S76) -> 0 | V69: =W69/Q69 -> 0 | W69: =SUM(W70:W76) -> 0 | X69: =W69/$AC$176/$W$183/$X$173 -> #REF! | Y69: =(T69+W69)=(SUM(AB70:AB76)) -> TRUE | Z69: =(T69+W69)-(SUM(AB70:AB76)) -> 0 | AD69: =W69+T69 -> 0 | AE69: =AD69 -> 0 | AF69: =AE69/$AE$151 -> #REF! | AG69: =AF69*$AG$158 -> #REF! | AH69: =AF69*$AG$161 -> #REF! | AJ69: =ROUND(AK69/L69,2) -> #REF! | AK69: =ROUND(AH69+AG69+AD69,2) -> #REF!
B70: =IFERROR(__xludf.DUMMYFUNCTION("IFERROR( IF(C70="""","""", IF(OR(REGEXMATCH(D70,""(?i)-Flashing""), REGEXMATCH(D70,""(?i)-EavesGut""), REGEXMATCH(D70,""(?i)Valley"")), ""DR"" & TEXT( ROUNDUP( MIN( VALUE(MID(C70, FIND("&"""("",C70)+1, FIND(""/"",C70)-FIND(""("",C70)-1)), 1200 ) / 50, 0 ) * 50, ""0"" ) & MID(C70, FIND(""/"",C70)+1, FIND("")"",C70)-FIND(""/"",C70)-1) & TEXT(H70*100,""0"") & I70,"&" IF(AND(D70=""Roof Sheet"", REGEXMATCH(C70,""(?i)KS\d{4}[A-Z]{2}"")), REGEXEXTRACT(C70,""(?i)KS\d{4}[A-Z]{2}""), IF(AND(REGEXMATCH(D70,""(?i)-DP""), REGEXMATCH(C70,""(?i)Downpipe"")), ""dp"" & REGEXEXTRACT(C70,""(\d+)"") & ""mm"", "&" IF(AND(REGEXMATCH(D70,""(?i)Bracket""), REGEXMATCH(C70,""(?i)Bracket"")), ""Brkt"" & REGEXEXTRACT(C70,""(\d+)"") & ""mm"", IF(AND(REGEXMATCH(D70,""(?i)-OP""), REGEXMATCH(C70,""(?i)pops"")), ""op"" & REGEXEXTRACT(C70,""(\d+)"") & ""mm"""&", IF(OR(D70=""R-FFTop"", D70=""R-FFBottom"", D70=""R-FFSide""), IF(REGEXMATCH(C70,""(?i)Profiled.*Top|Top.*Profiled""),""pfft"", IF(REGEXMATCH(C70,""(?i)Profiled.*Bottom|Bottom.*Profiled""),""pffb"", IF(REGEXMATCH(C70,""(?i)Squ"&"are""),""sff"",""""))), IF(REGEXMATCH(D70,""(?i)-Rivets""),""Rvt"", IF(REGEXMATCH(D70,""(?i)Silicone""),""300ml"", IF(REGEXMATCH(D70,""(?i)R-Butyl""),""300ml"", IF(REGEXMATCH(D70,""(?i)Fix""),""GenFix"", IF(AND(REGEXMATCH(C70,""(?i)Tim"&"ber""), REGEXMATCH(D70,""(?i)Timber"")),""tp"", IF(AND(REGEXMATCH(C70,""(?i)Vent G1275""), REGEXMATCH(D70,""(?i)Comb FIller"")),""CFV1275"", IF(REGEXMATCH(C70,""(?i)DPC""),""dpc"", IF(REGEXMATCH(C70,""(?i)Concealed Clips""),""ConClips"", I"&"F(REGEXMATCH(D70,""(?i)-Takeoff ea""),""Takeoff ea"", IF(REGEXMATCH(D70,""(?i)-Takeoff LM""),""Takeoff LM"", IF(REGEXMATCH(D70,""(?i)-Takeoff m2""),""Takeoff m2"", IF(D70=""R-TU/TD"",""TU/TD"",""""))))))))))))))))) )))"),"DR7006B55Mag") -> DR7006B55Mag | C70: 0.55mm BMT Coloursteel Maxam ridge cap flashing (690/6B) | D70: R-Flashing | E70: =VALUE(MID(C70, FIND("(", C70)+1, FIND("/", C70)-FIND("(", C70)-1)) / 1000 -> 0.69 | F70: =IFERROR(__xludf.DUMMYFUNCTION("IFERROR(REGEXEXTRACT(C70,""@\s*(\d+)\s*deg"")&""°"","""") "),"") | H70: =IFERROR(__xludf.DUMMYFUNCTION("IFERROR(REGEXEXTRACT(C70, ""(\d*\.\d+)mm""), """")"),"0.55") -> 0.55 | I70: Mag | J70: Specs | K70: LM | L70: 56.39 | M70: =L70 -> 56.39 | N70: =IFERROR(__xludf.DUMMYFUNCTION("""COMPUTED_VALUE"""),1.0) -> 1 | O70: 1 | P70: 1 | Q70: =M70*N70*O70*P70 -> 56.39 | S70: =R70*Q70 -> 0 | W70: =U70*Q70 -> 0 | X70: =W70/$AC$176/$W$183/Y70 -> #REF! | Y70: 2 | Z70: =Q70/X70 -> #REF! | AB70: =W70+S70 -> 0 | AM70: 56.39 | AN70: Matched | AO70: 0
B71: =IFERROR(__xludf.DUMMYFUNCTION("IFERROR( IF(C71="""","""", IF(OR(REGEXMATCH(D71,""(?i)-Flashing""), REGEXMATCH(D71,""(?i)-EavesGut""), REGEXMATCH(D71,""(?i)Valley"")), ""DR"" & TEXT( ROUNDUP( MIN( VALUE(MID(C71, FIND("&"""("",C71)+1, FIND(""/"",C71)-FIND(""("",C71)-1)), 1200 ) / 50, 0 ) * 50, ""0"" ) & MID(C71, FIND(""/"",C71)+1, FIND("")"",C71)-FIND(""/"",C71)-1) & TEXT(H71*100,""0"") & I71,"&" IF(AND(D71=""Roof Sheet"", REGEXMATCH(C71,""(?i)KS\d{4}[A-Z]{2}"")), REGEXEXTRACT(C71,""(?i)KS\d{4}[A-Z]{2}""), IF(AND(REGEXMATCH(D71,""(?i)-DP""), REGEXMATCH(C71,""(?i)Downpipe"")), ""dp"" & REGEXEXTRACT(C71,""(\d+)"") & ""mm"", "&" IF(AND(REGEXMATCH(D71,""(?i)Bracket""), REGEXMATCH(C71,""(?i)Bracket"")), ""Brkt"" & REGEXEXTRACT(C71,""(\d+)"") & ""mm"", IF(AND(REGEXMATCH(D71,""(?i)-OP""), REGEXMATCH(C71,""(?i)pops"")), ""op"" & REGEXEXTRACT(C71,""(\d+)"") & ""mm"""&", IF(OR(D71=""R-FFTop"", D71=""R-FFBottom"", D71=""R-FFSide""), IF(REGEXMATCH(C71,""(?i)Profiled.*Top|Top.*Profiled""),""pfft"", IF(REGEXMATCH(C71,""(?i)Profiled.*Bottom|Bottom.*Profiled""),""pffb"", IF(REGEXMATCH(C71,""(?i)Squ"&"are""),""sff"",""""))), IF(REGEXMATCH(D71,""(?i)-Rivets""),""Rvt"", IF(REGEXMATCH(D71,""(?i)Silicone""),""300ml"", IF(REGEXMATCH(D71,""(?i)R-Butyl""),""300ml"", IF(REGEXMATCH(D71,""(?i)Fix""),""GenFix"", IF(AND(REGEXMATCH(C71,""(?i)Tim"&"ber""), REGEXMATCH(D71,""(?i)Timber"")),""tp"", IF(AND(REGEXMATCH(C71,""(?i)Vent G1275""), REGEXMATCH(D71,""(?i)Comb FIller"")),""CFV1275"", IF(REGEXMATCH(C71,""(?i)DPC""),""dpc"", IF(REGEXMATCH(C71,""(?i)Concealed Clips""),""ConClips"", I"&"F(REGEXMATCH(D71,""(?i)-Takeoff ea""),""Takeoff ea"", IF(REGEXMATCH(D71,""(?i)-Takeoff LM""),""Takeoff LM"", IF(REGEXMATCH(D71,""(?i)-Takeoff m2""),""Takeoff m2"", IF(D71=""R-TU/TD"",""TU/TD"",""""))))))))))))))))) )))"),"300ml") -> 300ml | C71: Silicone 300ml | D71: R-Silicone | E71: =E70 -> 0.69 | H71: =IFERROR(__xludf.DUMMYFUNCTION("IFERROR(REGEXEXTRACT(C71, ""(\d*\.\d+)mm""), """")"),"") | J71: No Specs | K71: ea | L71: =M70 -> 56.39 | M71: =(ROUNDDOWN((M70/5.7)+2,0)*E71)/8 -> 0.94875 | N71: =IFERROR(__xludf.DUMMYFUNCTION("""COMPUTED_VALUE"""),1.0) -> 1 | O71: 1 | P71: 1 | Q71: =M71*N71*O71*P71 -> 0.94875 | S71: =R71*Q71 -> 0 | W71: =U71*Q71 -> 0 | AB71: =W71+S71 -> 0 | AM71: 0.94875 | AN71: Matched | AO71: 0
B72: =IFERROR(__xludf.DUMMYFUNCTION("IFERROR( IF(C72="""","""", IF(OR(REGEXMATCH(D72,""(?i)-Flashing""), REGEXMATCH(D72,""(?i)-EavesGut""), REGEXMATCH(D72,""(?i)Valley"")), ""DR"" & TEXT( ROUNDUP( MIN( VALUE(MID(C72, FIND("&"""("",C72)+1, FIND(""/"",C72)-FIND(""("",C72)-1)), 1200 ) / 50, 0 ) * 50, ""0"" ) & MID(C72, FIND(""/"",C72)+1, FIND("")"",C72)-FIND(""/"",C72)-1) & TEXT(H72*100,""0"") & I72,"&" IF(AND(D72=""Roof Sheet"", REGEXMATCH(C72,""(?i)KS\d{4}[A-Z]{2}"")), REGEXEXTRACT(C72,""(?i)KS\d{4}[A-Z]{2}""), IF(AND(REGEXMATCH(D72,""(?i)-DP""), REGEXMATCH(C72,""(?i)Downpipe"")), ""dp"" & REGEXEXTRACT(C72,""(\d+)"") & ""mm"", "&" IF(AND(REGEXMATCH(D72,""(?i)Bracket""), REGEXMATCH(C72,""(?i)Bracket"")), ""Brkt"" & REGEXEXTRACT(C72,""(\d+)"") & ""mm"", IF(AND(REGEXMATCH(D72,""(?i)-OP""), REGEXMATCH(C72,""(?i)pops"")), ""op"" & REGEXEXTRACT(C72,""(\d+)"") & ""mm"""&", IF(OR(D72=""R-FFTop"", D72=""R-FFBottom"", D72=""R-FFSide""), IF(REGEXMATCH(C72,""(?i)Profiled.*Top|Top.*Profiled""),""pfft"", IF(REGEXMATCH(C72,""(?i)Profiled.*Bottom|Bottom.*Profiled""),""pffb"", IF(REGEXMATCH(C72,""(?i)Squ"&"are""),""sff"",""""))), IF(REGEXMATCH(D72,""(?i)-Rivets""),""Rvt"", IF(REGEXMATCH(D72,""(?i)Silicone""),""300ml"", IF(REGEXMATCH(D72,""(?i)R-Butyl""),""300ml"", IF(REGEXMATCH(D72,""(?i)Fix""),""GenFix"", IF(AND(REGEXMATCH(C72,""(?i)Tim"&"ber""), REGEXMATCH(D72,""(?i)Timber"")),""tp"", IF(AND(REGEXMATCH(C72,""(?i)Vent G1275""), REGEXMATCH(D72,""(?i)Comb FIller"")),""CFV1275"", IF(REGEXMATCH(C72,""(?i)DPC""),""dpc"", IF(REGEXMATCH(C72,""(?i)Concealed Clips""),""ConClips"", I"&"F(REGEXMATCH(D72,""(?i)-Takeoff ea""),""Takeoff ea"", IF(REGEXMATCH(D72,""(?i)-Takeoff LM""),""Takeoff LM"", IF(REGEXMATCH(D72,""(?i)-Takeoff m2""),""Takeoff m2"", IF(D72=""R-TU/TD"",""TU/TD"",""""))))))))))))))))) )))"),"Rvt") -> Rvt | C72: Rivets | D72: R-Rivets | E72: =E70 -> 0.69 | H72: =IFERROR(__xludf.DUMMYFUNCTION("IFERROR(REGEXEXTRACT(C72, ""(\d*\.\d+)mm""), """")"),"") | J72: No Specs | K72: ea | L72: =M70 -> 56.39 | M72: =ROUNDUP(((M70/5.7)+1)*(E72/0.05),0) -> 151 | N72: =IFERROR(__xludf.DUMMYFUNCTION("""COMPUTED_VALUE"""),1.0) -> 1 | O72: 1 | P72: 1 | Q72: =M72*N72*O72*P72 -> 151 | S72: =R72*Q72 -> 0 | W72: =U72*Q72 -> 0 | AB72: =W72+S72 -> 0 | AM72: 151 | AN72: Matched | AO72: 0
B73: =IFERROR(__xludf.DUMMYFUNCTION("IFERROR( IF(C73="""","""", IF(OR(REGEXMATCH(D73,""(?i)-Flashing""), REGEXMATCH(D73,""(?i)-EavesGut""), REGEXMATCH(D73,""(?i)Valley"")), ""DR"" & TEXT( ROUNDUP( MIN( VALUE(MID(C73, FIND("&"""("",C73)+1, FIND(""/"",C73)-FIND(""("",C73)-1)), 1200 ) / 50, 0 ) * 50, ""0"" ) & MID(C73, FIND(""/"",C73)+1, FIND("")"",C73)-FIND(""/"",C73)-1) & TEXT(H73*100,""0"") & I73,"&" IF(AND(D73=""Roof Sheet"", REGEXMATCH(C73,""(?i)KS\d{4}[A-Z]{2}"")), REGEXEXTRACT(C73,""(?i)KS\d{4}[A-Z]{2}""), IF(AND(REGEXMATCH(D73,""(?i)-DP""), REGEXMATCH(C73,""(?i)Downpipe"")), ""dp"" & REGEXEXTRACT(C73,""(\d+)"") & ""mm"", "&" IF(AND(REGEXMATCH(D73,""(?i)Bracket""), REGEXMATCH(C73,""(?i)Bracket"")), ""Brkt"" & REGEXEXTRACT(C73,""(\d+)"") & ""mm"", IF(AND(REGEXMATCH(D73,""(?i)-OP""), REGEXMATCH(C73,""(?i)pops"")), ""op"" & REGEXEXTRACT(C73,""(\d+)"") & ""mm"""&", IF(OR(D73=""R-FFTop"", D73=""R-FFBottom"", D73=""R-FFSide""), IF(REGEXMATCH(C73,""(?i)Profiled.*Top|Top.*Profiled""),""pfft"", IF(REGEXMATCH(C73,""(?i)Profiled.*Bottom|Bottom.*Profiled""),""pffb"", IF(REGEXMATCH(C73,""(?i)Squ"&"are""),""sff"",""""))), IF(REGEXMATCH(D73,""(?i)-Rivets""),""Rvt"", IF(REGEXMATCH(D73,""(?i)Silicone""),""300ml"", IF(REGEXMATCH(D73,""(?i)R-Butyl""),""300ml"", IF(REGEXMATCH(D73,""(?i)Fix""),""GenFix"", IF(AND(REGEXMATCH(C73,""(?i)Tim"&"ber""), REGEXMATCH(D73,""(?i)Timber"")),""tp"", IF(AND(REGEXMATCH(C73,""(?i)Vent G1275""), REGEXMATCH(D73,""(?i)Comb FIller"")),""CFV1275"", IF(REGEXMATCH(C73,""(?i)DPC""),""dpc"", IF(REGEXMATCH(C73,""(?i)Concealed Clips""),""ConClips"", I"&"F(REGEXMATCH(D73,""(?i)-Takeoff ea""),""Takeoff ea"", IF(REGEXMATCH(D73,""(?i)-Takeoff LM""),""Takeoff LM"", IF(REGEXMATCH(D73,""(?i)-Takeoff m2""),""Takeoff m2"", IF(D73=""R-TU/TD"",""TU/TD"",""""))))))))))))))))) )))"),"GenFix") -> GenFix | C73: Fixings | D73: R-GenFix | F73: =F72 | J73: No Specs | K73: ea | L73: =M70 -> 56.39 | M73: =ROUNDUP(M70/0.6,0)+1 -> 95 | N73: =IFERROR(__xludf.DUMMYFUNCTION("""COMPUTED_VALUE"""),1.0) -> 1 | O73: 1 | P73: 1 | Q73: =M73*N73*O73*P73 -> 95 | S73: =R73*Q73 -> 0 | W73: =U73*Q73 -> 0 | AB73: =W73+S73 -> 0 | AM73: 95 | AN73: Matched | AO73: 0
B74: =IFERROR(__xludf.DUMMYFUNCTION("IFERROR( IF(C74="""","""", IF(OR(REGEXMATCH(D74,""(?i)-Flashing""), REGEXMATCH(D74,""(?i)-EavesGut""), REGEXMATCH(D74,""(?i)Valley"")), ""DR"" & TEXT( ROUNDUP( MIN( VALUE(MID(C74, FIND("&"""("",C74)+1, FIND(""/"",C74)-FIND(""("",C74)-1)), 1200 ) / 50, 0 ) * 50, ""0"" ) & MID(C74, FIND(""/"",C74)+1, FIND("")"",C74)-FIND(""/"",C74)-1) & TEXT(H74*100,""0"") & I74,"&" IF(AND(D74=""Roof Sheet"", REGEXMATCH(C74,""(?i)KS\d{4}[A-Z]{2}"")), REGEXEXTRACT(C74,""(?i)KS\d{4}[A-Z]{2}""), IF(AND(REGEXMATCH(D74,""(?i)-DP""), REGEXMATCH(C74,""(?i)Downpipe"")), ""dp"" & REGEXEXTRACT(C74,""(\d+)"") & ""mm"", "&" IF(AND(REGEXMATCH(D74,""(?i)Bracket""), REGEXMATCH(C74,""(?i)Bracket"")), ""Brkt"" & REGEXEXTRACT(C74,""(\d+)"") & ""mm"", IF(AND(REGEXMATCH(D74,""(?i)-OP""), REGEXMATCH(C74,""(?i)pops"")), ""op"" & REGEXEXTRACT(C74,""(\d+)"") & ""mm"""&", IF(OR(D74=""R-FFTop"", D74=""R-FFBottom"", D74=""R-FFSide""), IF(REGEXMATCH(C74,""(?i)Profiled.*Top|Top.*Profiled""),""pfft"", IF(REGEXMATCH(C74,""(?i)Profiled.*Bottom|Bottom.*Profiled""),""pffb"", IF(REGEXMATCH(C74,""(?i)Squ"&"are""),""sff"",""""))), IF(REGEXMATCH(D74,""(?i)-Rivets""),""Rvt"", IF(REGEXMATCH(D74,""(?i)Silicone""),""300ml"", IF(REGEXMATCH(D74,""(?i)R-Butyl""),""300ml"", IF(REGEXMATCH(D74,""(?i)Fix""),""GenFix"", IF(AND(REGEXMATCH(C74,""(?i)Tim"&"ber""), REGEXMATCH(D74,""(?i)Timber"")),""tp"", IF(AND(REGEXMATCH(C74,""(?i)Vent G1275""), REGEXMATCH(D74,""(?i)Comb FIller"")),""CFV1275"", IF(REGEXMATCH(C74,""(?i)DPC""),""dpc"", IF(REGEXMATCH(C74,""(?i)Concealed Clips""),""ConClips"", I"&"F(REGEXMATCH(D74,""(?i)-Takeoff ea""),""Takeoff ea"", IF(REGEXMATCH(D74,""(?i)-Takeoff LM""),""Takeoff LM"", IF(REGEXMATCH(D74,""(?i)-Takeoff m2""),""Takeoff m2"", IF(D74=""R-TU/TD"",""TU/TD"",""""))))))))))))))))) )))"),"pfft") -> pfft | C74: Profiled Foam Filler Top | D74: R-FFTop | J74: No Specs | K74: LM | L74: =M70 -> 56.39 | M74: =M70 -> 56.39 | N74: =IFERROR(__xludf.DUMMYFUNCTION("""COMPUTED_VALUE"""),1.0) -> 1 | O74: 1 | P74: 2 | Q74: =M74*N74*O74*P74 -> 112.78 | S74: =R74*Q74 -> 0 | W74: =U74*Q74 -> 0 | AB74: =W74+S74 -> 0 | AM74: 56.39 | AN74: Matched | AO74: 0
B75: =IFERROR(__xludf.DUMMYFUNCTION("IFERROR( IF(C75="""","""", IF(OR(REGEXMATCH(D75,""(?i)-Flashing""), REGEXMATCH(D75,""(?i)-EavesGut""), REGEXMATCH(D75,""(?i)Valley"")), ""DR"" & TEXT( ROUNDUP( MIN( VALUE(MID(C75, FIND("&"""("",C75)+1, FIND(""/"",C75)-FIND(""("",C75)-1)), 1200 ) / 50, 0 ) * 50, ""0"" ) & MID(C75, FIND(""/"",C75)+1, FIND("")"",C75)-FIND(""/"",C75)-1) & TEXT(H75*100,""0"") & I75,"&" IF(AND(D75=""Roof Sheet"", REGEXMATCH(C75,""(?i)KS\d{4}[A-Z]{2}"")), REGEXEXTRACT(C75,""(?i)KS\d{4}[A-Z]{2}""), IF(AND(REGEXMATCH(D75,""(?i)-DP""), REGEXMATCH(C75,""(?i)Downpipe"")), ""dp"" & REGEXEXTRACT(C75,""(\d+)"") & ""mm"", "&" IF(AND(REGEXMATCH(D75,""(?i)Bracket""), REGEXMATCH(C75,""(?i)Bracket"")), ""Brkt"" & REGEXEXTRACT(C75,""(\d+)"") & ""mm"", IF(AND(REGEXMATCH(D75,""(?i)-OP""), REGEXMATCH(C75,""(?i)pops"")), ""op"" & REGEXEXTRACT(C75,""(\d+)"") & ""mm"""&", IF(OR(D75=""R-FFTop"", D75=""R-FFBottom"", D75=""R-FFSide""), IF(REGEXMATCH(C75,""(?i)Profiled.*Top|Top.*Profiled""),""pfft"", IF(REGEXMATCH(C75,""(?i)Profiled.*Bottom|Bottom.*Profiled""),""pffb"", IF(REGEXMATCH(C75,""(?i)Squ"&"are""),""sff"",""""))), IF(REGEXMATCH(D75,""(?i)-Rivets""),""Rvt"", IF(REGEXMATCH(D75,""(?i)Silicone""),""300ml"", IF(REGEXMATCH(D75,""(?i)R-Butyl""),""300ml"", IF(REGEXMATCH(D75,""(?i)Fix""),""GenFix"", IF(AND(REGEXMATCH(C75,""(?i)Tim"&"ber""), REGEXMATCH(D75,""(?i)Timber"")),""tp"", IF(AND(REGEXMATCH(C75,""(?i)Vent G1275""), REGEXMATCH(D75,""(?i)Comb FIller"")),""CFV1275"", IF(REGEXMATCH(C75,""(?i)DPC""),""dpc"", IF(REGEXMATCH(C75,""(?i)Concealed Clips""),""ConClips"", I"&"F(REGEXMATCH(D75,""(?i)-Takeoff ea""),""Takeoff ea"", IF(REGEXMATCH(D75,""(?i)-Takeoff LM""),""Takeoff LM"", IF(REGEXMATCH(D75,""(?i)-Takeoff m2""),""Takeoff m2"", IF(D75=""R-TU/TD"",""TU/TD"",""""))))))))))))))))) )))"),"TU/TD") -> TU/TD | C75: Turn Up Roof End | D75: R-TU/TD | J75: No Specs | K75: LM | L75: =M70 -> 56.39 | M75: =M70 -> 56.39 | N75: =IFERROR(__xludf.DUMMYFUNCTION("""COMPUTED_VALUE"""),1.0) -> 1 | O75: 1 | P75: 2 | Q75: =M75*N75*O75*P75 -> 112.78 | S75: =R75*Q75 -> 0 | W75: =U75*Q75 -> 0 | AB75: =W75+S75 -> 0 | AM75: 56.39 | AN75: Matched | AO75: 0
N76: =IFERROR(__xludf.DUMMYFUNCTION("""COMPUTED_VALUE"""),"")
A77: 1 | C77: Supply and install 0.55mm BMT Coloursteel Maxam side barge flashing, as per detail 6 (A502) | L77: =Q77 -> 19.378583 | N77: =IFERROR(__xludf.DUMMYFUNCTION("""COMPUTED_VALUE"""),"") | Q77: =Q78 -> 19.378583 | S77: =T77/Q77 -> 0 | T77: =SUM(S78:S82) -> 0 | V77: =W77/Q77 -> 0 | W77: =SUM(W78:W82) -> 0 | X77: =W77/$AC$176/$W$183/$X$173 -> #REF! | Y77: =(T77+W77)=(SUM(AB78:AB82)) -> TRUE | Z77: =(T77+W77)-(SUM(AB78:AB82)) -> 0 | AD77: =W77+T77 -> 0 | AE77: =AD77 -> 0 | AF77: =AE77/$AE$151 -> #REF! | AG77: =AF77*$AG$158 -> #REF! | AH77: =AF77*$AG$161 -> #REF! | AJ77: =ROUND(AK77/L77,2) -> #REF! | AK77: =ROUND(AH77+AG77+AD77,2) -> #REF!
B78: =IFERROR(__xludf.DUMMYFUNCTION("IFERROR( IF(C78="""","""", IF(OR(REGEXMATCH(D78,""(?i)-Flashing""), REGEXMATCH(D78,""(?i)-EavesGut""), REGEXMATCH(D78,""(?i)Valley"")), ""DR"" & TEXT( ROUNDUP( MIN( VALUE(MID(C78, FIND("&"""("",C78)+1, FIND(""/"",C78)-FIND(""("",C78)-1)), 1200 ) / 50, 0 ) * 50, ""0"" ) & MID(C78, FIND(""/"",C78)+1, FIND("")"",C78)-FIND(""/"",C78)-1) & TEXT(H78*100,""0"") & I78,"&" IF(AND(D78=""Roof Sheet"", REGEXMATCH(C78,""(?i)KS\d{4}[A-Z]{2}"")), REGEXEXTRACT(C78,""(?i)KS\d{4}[A-Z]{2}""), IF(AND(REGEXMATCH(D78,""(?i)-DP""), REGEXMATCH(C78,""(?i)Downpipe"")), ""dp"" & REGEXEXTRACT(C78,""(\d+)"") & ""mm"", "&" IF(AND(REGEXMATCH(D78,""(?i)Bracket""), REGEXMATCH(C78,""(?i)Bracket"")), ""Brkt"" & REGEXEXTRACT(C78,""(\d+)"") & ""mm"", IF(AND(REGEXMATCH(D78,""(?i)-OP""), REGEXMATCH(C78,""(?i)pops"")), ""op"" & REGEXEXTRACT(C78,""(\d+)"") & ""mm"""&", IF(OR(D78=""R-FFTop"", D78=""R-FFBottom"", D78=""R-FFSide""), IF(REGEXMATCH(C78,""(?i)Profiled.*Top|Top.*Profiled""),""pfft"", IF(REGEXMATCH(C78,""(?i)Profiled.*Bottom|Bottom.*Profiled""),""pffb"", IF(REGEXMATCH(C78,""(?i)Squ"&"are""),""sff"",""""))), IF(REGEXMATCH(D78,""(?i)-Rivets""),""Rvt"", IF(REGEXMATCH(D78,""(?i)Silicone""),""300ml"", IF(REGEXMATCH(D78,""(?i)R-Butyl""),""300ml"", IF(REGEXMATCH(D78,""(?i)Fix""),""GenFix"", IF(AND(REGEXMATCH(C78,""(?i)Tim"&"ber""), REGEXMATCH(D78,""(?i)Timber"")),""tp"", IF(AND(REGEXMATCH(C78,""(?i)Vent G1275""), REGEXMATCH(D78,""(?i)Comb FIller"")),""CFV1275"", IF(REGEXMATCH(C78,""(?i)DPC""),""dpc"", IF(REGEXMATCH(C78,""(?i)Concealed Clips""),""ConClips"", I"&"F(REGEXMATCH(D78,""(?i)-Takeoff ea""),""Takeoff ea"", IF(REGEXMATCH(D78,""(?i)-Takeoff LM""),""Takeoff LM"", IF(REGEXMATCH(D78,""(?i)-Takeoff m2""),""Takeoff m2"", IF(D78=""R-TU/TD"",""TU/TD"",""""))))))))))))))))) )))"),"DR6003B55Mag") -> DR6003B55Mag | C78: 0.55mm BMT Coloursteel Maxam side barge flashing (570/3B) @ 9 deg | D78: R-Flashing | E78: =VALUE(MID(C78, FIND("(", C78)+1, FIND("/", C78)-FIND("(", C78)-1)) / 1000 -> 0.57 | F78: =IFERROR(__xludf.DUMMYFUNCTION("IFERROR(REGEXEXTRACT(C78,""@\s*(\d+)\s*deg"")&""°"","""") "),"9°") -> 9° | H78: =IFERROR(__xludf.DUMMYFUNCTION("IFERROR(REGEXEXTRACT(C78, ""(\d*\.\d+)mm""), """")"),"0.55") -> 0.55 | I78: Mag | J78: Specs | K78: LM | L78: 19.14 | M78: =L78 -> 19.14 | N78: =IFERROR(__xludf.DUMMYFUNCTION("""COMPUTED_VALUE"""),1.0124651257880029) -> 1.0124651 | O78: 1 | P78: 1 | Q78: =M78*N78*O78*P78 -> 19.378583 | S78: =R78*Q78 -> 0 | W78: =U78*Q78 -> 0 | AB78: =W78+S78 -> 0 | AM78: 19.14 | AN78: Matched | AO78: 0
B79: =IFERROR(__xludf.DUMMYFUNCTION("IFERROR( IF(C79="""","""", IF(OR(REGEXMATCH(D79,""(?i)-Flashing""), REGEXMATCH(D79,""(?i)-EavesGut""), REGEXMATCH(D79,""(?i)Valley"")), ""DR"" & TEXT( ROUNDUP( MIN( VALUE(MID(C79, FIND("&"""("",C79)+1, FIND(""/"",C79)-FIND(""("",C79)-1)), 1200 ) / 50, 0 ) * 50, ""0"" ) & MID(C79, FIND(""/"",C79)+1, FIND("")"",C79)-FIND(""/"",C79)-1) & TEXT(H79*100,""0"") & I79,"&" IF(AND(D79=""Roof Sheet"", REGEXMATCH(C79,""(?i)KS\d{4}[A-Z]{2}"")), REGEXEXTRACT(C79,""(?i)KS\d{4}[A-Z]{2}""), IF(AND(REGEXMATCH(D79,""(?i)-DP""), REGEXMATCH(C79,""(?i)Downpipe"")), ""dp"" & REGEXEXTRACT(C79,""(\d+)"") & ""mm"", "&" IF(AND(REGEXMATCH(D79,""(?i)Bracket""), REGEXMATCH(C79,""(?i)Bracket"")), ""Brkt"" & REGEXEXTRACT(C79,""(\d+)"") & ""mm"", IF(AND(REGEXMATCH(D79,""(?i)-OP""), REGEXMATCH(C79,""(?i)pops"")), ""op"" & REGEXEXTRACT(C79,""(\d+)"") & ""mm"""&", IF(OR(D79=""R-FFTop"", D79=""R-FFBottom"", D79=""R-FFSide""), IF(REGEXMATCH(C79,""(?i)Profiled.*Top|Top.*Profiled""),""pfft"", IF(REGEXMATCH(C79,""(?i)Profiled.*Bottom|Bottom.*Profiled""),""pffb"", IF(REGEXMATCH(C79,""(?i)Squ"&"are""),""sff"",""""))), IF(REGEXMATCH(D79,""(?i)-Rivets""),""Rvt"", IF(REGEXMATCH(D79,""(?i)Silicone""),""300ml"", IF(REGEXMATCH(D79,""(?i)R-Butyl""),""300ml"", IF(REGEXMATCH(D79,""(?i)Fix""),""GenFix"", IF(AND(REGEXMATCH(C79,""(?i)Tim"&"ber""), REGEXMATCH(D79,""(?i)Timber"")),""tp"", IF(AND(REGEXMATCH(C79,""(?i)Vent G1275""), REGEXMATCH(D79,""(?i)Comb FIller"")),""CFV1275"", IF(REGEXMATCH(C79,""(?i)DPC""),""dpc"", IF(REGEXMATCH(C79,""(?i)Concealed Clips""),""ConClips"", I"&"F(REGEXMATCH(D79,""(?i)-Takeoff ea""),""Takeoff ea"", IF(REGEXMATCH(D79,""(?i)-Takeoff LM""),""Takeoff LM"", IF(REGEXMATCH(D79,""(?i)-Takeoff m2""),""Takeoff m2"", IF(D79=""R-TU/TD"",""TU/TD"",""""))))))))))))))))) )))"),"300ml") -> 300ml | C79: Silicone 300ml | D79: R-Silicone | E79: =E78 -> 0.57 | F79: =F78 -> 9° | J79: No Specs | K79: ea | L79: =M78 -> 19.14 | M79: =(ROUNDDOWN((M78/5.7)+2,0)*E79)/8 -> 0.35625 | N79: =IFERROR(__xludf.DUMMYFUNCTION("""COMPUTED_VALUE"""),1.0124651257880029) -> 1.0124651 | O79: 1 | P79: 1 | Q79: =M79*N79*O79*P79 -> 0.3606907 | S79: =R79*Q79 -> 0 | W79: =U79*Q79 -> 0 | AB79: =W79+S79 -> 0 | AM79: 0.35625 | AN79: Matched | AO79: 0
B80: =IFERROR(__xludf.DUMMYFUNCTION("IFERROR( IF(C80="""","""", IF(OR(REGEXMATCH(D80,""(?i)-Flashing""), REGEXMATCH(D80,""(?i)-EavesGut""), REGEXMATCH(D80,""(?i)Valley"")), ""DR"" & TEXT( ROUNDUP( MIN( VALUE(MID(C80, FIND("&"""("",C80)+1, FIND(""/"",C80)-FIND(""("",C80)-1)), 1200 ) / 50, 0 ) * 50, ""0"" ) & MID(C80, FIND(""/"",C80)+1, FIND("")"",C80)-FIND(""/"",C80)-1) & TEXT(H80*100,""0"") & I80,"&" IF(AND(D80=""Roof Sheet"", REGEXMATCH(C80,""(?i)KS\d{4}[A-Z]{2}"")), REGEXEXTRACT(C80,""(?i)KS\d{4}[A-Z]{2}""), IF(AND(REGEXMATCH(D80,""(?i)-DP""), REGEXMATCH(C80,""(?i)Downpipe"")), ""dp"" & REGEXEXTRACT(C80,""(\d+)"") & ""mm"", "&" IF(AND(REGEXMATCH(D80,""(?i)Bracket""), REGEXMATCH(C80,""(?i)Bracket"")), ""Brkt"" & REGEXEXTRACT(C80,""(\d+)"") & ""mm"", IF(AND(REGEXMATCH(D80,""(?i)-OP""), REGEXMATCH(C80,""(?i)pops"")), ""op"" & REGEXEXTRACT(C80,""(\d+)"") & ""mm"""&", IF(OR(D80=""R-FFTop"", D80=""R-FFBottom"", D80=""R-FFSide""), IF(REGEXMATCH(C80,""(?i)Profiled.*Top|Top.*Profiled""),""pfft"", IF(REGEXMATCH(C80,""(?i)Profiled.*Bottom|Bottom.*Profiled""),""pffb"", IF(REGEXMATCH(C80,""(?i)Squ"&"are""),""sff"",""""))), IF(REGEXMATCH(D80,""(?i)-Rivets""),""Rvt"", IF(REGEXMATCH(D80,""(?i)Silicone""),""300ml"", IF(REGEXMATCH(D80,""(?i)R-Butyl""),""300ml"", IF(REGEXMATCH(D80,""(?i)Fix""),""GenFix"", IF(AND(REGEXMATCH(C80,""(?i)Tim"&"ber""), REGEXMATCH(D80,""(?i)Timber"")),""tp"", IF(AND(REGEXMATCH(C80,""(?i)Vent G1275""), REGEXMATCH(D80,""(?i)Comb FIller"")),""CFV1275"", IF(REGEXMATCH(C80,""(?i)DPC""),""dpc"", IF(REGEXMATCH(C80,""(?i)Concealed Clips""),""ConClips"", I"&"F(REGEXMATCH(D80,""(?i)-Takeoff ea""),""Takeoff ea"", IF(REGEXMATCH(D80,""(?i)-Takeoff LM""),""Takeoff LM"", IF(REGEXMATCH(D80,""(?i)-Takeoff m2""),""Takeoff m2"", IF(D80=""R-TU/TD"",""TU/TD"",""""))))))))))))))))) )))"),"Rvt") -> Rvt | C80: Rivets | D80: R-Rivets | E80: =E78 -> 0.57 | F80: =F79 -> 9° | J80: No Specs | K80: ea | L80: =M78 -> 19.14 | M80: =ROUNDUP(((M78/5.7)+1)*(E80/0.05),0) -> 50 | N80: =IFERROR(__xludf.DUMMYFUNCTION("""COMPUTED_VALUE"""),1.0124651257880029) -> 1.0124651 | O80: 1 | P80: 1 | Q80: =M80*N80*O80*P80 -> 50.623256 | S80: =R80*Q80 -> 0 | W80: =U80*Q80 -> 0 | AB80: =W80+S80 -> 0 | AM80: 50 | AN80: Matched | AO80: 0
B81: =IFERROR(__xludf.DUMMYFUNCTION("IFERROR( IF(C81="""","""", IF(OR(REGEXMATCH(D81,""(?i)-Flashing""), REGEXMATCH(D81,""(?i)-EavesGut""), REGEXMATCH(D81,""(?i)Valley"")), ""DR"" & TEXT( ROUNDUP( MIN( VALUE(MID(C81, FIND("&"""("",C81)+1, FIND(""/"",C81)-FIND(""("",C81)-1)), 1200 ) / 50, 0 ) * 50, ""0"" ) & MID(C81, FIND(""/"",C81)+1, FIND("")"",C81)-FIND(""/"",C81)-1) & TEXT(H81*100,""0"") & I81,"&" IF(AND(D81=""Roof Sheet"", REGEXMATCH(C81,""(?i)KS\d{4}[A-Z]{2}"")), REGEXEXTRACT(C81,""(?i)KS\d{4}[A-Z]{2}""), IF(AND(REGEXMATCH(D81,""(?i)-DP""), REGEXMATCH(C81,""(?i)Downpipe"")), ""dp"" & REGEXEXTRACT(C81,""(\d+)"") & ""mm"", "&" IF(AND(REGEXMATCH(D81,""(?i)Bracket""), REGEXMATCH(C81,""(?i)Bracket"")), ""Brkt"" & REGEXEXTRACT(C81,""(\d+)"") & ""mm"", IF(AND(REGEXMATCH(D81,""(?i)-OP""), REGEXMATCH(C81,""(?i)pops"")), ""op"" & REGEXEXTRACT(C81,""(\d+)"") & ""mm"""&", IF(OR(D81=""R-FFTop"", D81=""R-FFBottom"", D81=""R-FFSide""), IF(REGEXMATCH(C81,""(?i)Profiled.*Top|Top.*Profiled""),""pfft"", IF(REGEXMATCH(C81,""(?i)Profiled.*Bottom|Bottom.*Profiled""),""pffb"", IF(REGEXMATCH(C81,""(?i)Squ"&"are""),""sff"",""""))), IF(REGEXMATCH(D81,""(?i)-Rivets""),""Rvt"", IF(REGEXMATCH(D81,""(?i)Silicone""),""300ml"", IF(REGEXMATCH(D81,""(?i)R-Butyl""),""300ml"", IF(REGEXMATCH(D81,""(?i)Fix""),""GenFix"", IF(AND(REGEXMATCH(C81,""(?i)Tim"&"ber""), REGEXMATCH(D81,""(?i)Timber"")),""tp"", IF(AND(REGEXMATCH(C81,""(?i)Vent G1275""), REGEXMATCH(D81,""(?i)Comb FIller"")),""CFV1275"", IF(REGEXMATCH(C81,""(?i)DPC""),""dpc"", IF(REGEXMATCH(C81,""(?i)Concealed Clips""),""ConClips"", I"&"F(REGEXMATCH(D81,""(?i)-Takeoff ea""),""Takeoff ea"", IF(REGEXMATCH(D81,""(?i)-Takeoff LM""),""Takeoff LM"", IF(REGEXMATCH(D81,""(?i)-Takeoff m2""),""Takeoff m2"", IF(D81=""R-TU/TD"",""TU/TD"",""""))))))))))))))))) )))"),"GenFix") -> GenFix | C81: Fixings | D81: R-GenFix | F81: =F80 -> 9° | J81: No Specs | K81: ea | L81: =M78 -> 19.14 | M81: =ROUNDUP(M78/0.6,0)+1 -> 33 | N81: =IFERROR(__xludf.DUMMYFUNCTION("""COMPUTED_VALUE"""),1.0124651257880029) -> 1.0124651 | O81: 1 | P81: 1 | Q81: =M81*N81*O81*P81 -> 33.411349 | S81: =R81*Q81 -> 0 | W81: =U81*Q81 -> 0 | AB81: =W81+S81 -> 0 | AM81: 33 | AN81: Matched | AO81: 0
B82: =IFERROR(__xludf.DUMMYFUNCTION("IFERROR( IF(C82="""","""", IF(OR(REGEXMATCH(D82,""(?i)-Flashing""), REGEXMATCH(D82,""(?i)-EavesGut""), REGEXMATCH(D82,""(?i)Valley"")), ""DR"" & TEXT( ROUNDUP( MIN( VALUE(MID(C82, FIND("&"""("",C82)+1, FIND(""/"",C82)-FIND(""("",C82)-1)), 1200 ) / 50, 0 ) * 50, ""0"" ) & MID(C82, FIND(""/"",C82)+1, FIND("")"",C82)-FIND(""/"",C82)-1) & TEXT(H82*100,""0"") & I82,"&" IF(AND(D82=""Roof Sheet"", REGEXMATCH(C82,""(?i)KS\d{4}[A-Z]{2}"")), REGEXEXTRACT(C82,""(?i)KS\d{4}[A-Z]{2}""), IF(AND(REGEXMATCH(D82,""(?i)-DP""), REGEXMATCH(C82,""(?i)Downpipe"")), ""dp"" & REGEXEXTRACT(C82,""(\d+)"") & ""mm"", "&" IF(AND(REGEXMATCH(D82,""(?i)Bracket""), REGEXMATCH(C82,""(?i)Bracket"")), ""Brkt"" & REGEXEXTRACT(C82,""(\d+)"") & ""mm"", IF(AND(REGEXMATCH(D82,""(?i)-OP""), REGEXMATCH(C82,""(?i)pops"")), ""op"" & REGEXEXTRACT(C82,""(\d+)"") & ""mm"""&", IF(OR(D82=""R-FFTop"", D82=""R-FFBottom"", D82=""R-FFSide""), IF(REGEXMATCH(C82,""(?i)Profiled.*Top|Top.*Profiled""),""pfft"", IF(REGEXMATCH(C82,""(?i)Profiled.*Bottom|Bottom.*Profiled""),""pffb"", IF(REGEXMATCH(C82,""(?i)Squ"&"are""),""sff"",""""))), IF(REGEXMATCH(D82,""(?i)-Rivets""),""Rvt"", IF(REGEXMATCH(D82,""(?i)Silicone""),""300ml"", IF(REGEXMATCH(D82,""(?i)R-Butyl""),""300ml"", IF(REGEXMATCH(D82,""(?i)Fix""),""GenFix"", IF(AND(REGEXMATCH(C82,""(?i)Tim"&"ber""), REGEXMATCH(D82,""(?i)Timber"")),""tp"", IF(AND(REGEXMATCH(C82,""(?i)Vent G1275""), REGEXMATCH(D82,""(?i)Comb FIller"")),""CFV1275"", IF(REGEXMATCH(C82,""(?i)DPC""),""dpc"", IF(REGEXMATCH(C82,""(?i)Concealed Clips""),""ConClips"", I"&"F(REGEXMATCH(D82,""(?i)-Takeoff ea""),""Takeoff ea"", IF(REGEXMATCH(D82,""(?i)-Takeoff LM""),""Takeoff LM"", IF(REGEXMATCH(D82,""(?i)-Takeoff m2""),""Takeoff m2"", IF(D82=""R-TU/TD"",""TU/TD"",""""))))))))))))))))) )))"),"sff") -> sff | C82: Square Foam Filler Top | D82: R-FFSide | F82: =F81 -> 9° | J82: No Specs | K82: LM | L82: =M78 -> 19.14 | M82: =M78 -> 19.14 | N82: =IFERROR(__xludf.DUMMYFUNCTION("""COMPUTED_VALUE"""),1.0124651257880029) -> 1.0124651 | O82: 1 | P82: 1 | Q82: =M82*N82*O82*P82 -> 19.378583 | S82: =R82*Q82 -> 0 | W82: =U82*Q82 -> 0 | AB82: =W82+S82 -> 0 | AM82: 19.14 | AN82: Matched | AO82: 0
N83: =IFERROR(__xludf.DUMMYFUNCTION("""COMPUTED_VALUE"""),"")
A84: 1 | C84: Supply and install 0.55mm BMT Coloursteel Maxam side barge flashing, as per detail 6 (A502) | L84: =Q84 -> 32.804832 | N84: =IFERROR(__xludf.DUMMYFUNCTION("""COMPUTED_VALUE"""),"") | Q84: =Q85 -> 32.804832 | S84: =T84/Q84 -> 0 | T84: =SUM(S85:S89) -> 0 | V84: =W84/Q84 -> 0 | W84: =SUM(W85:W89) -> 0 | X84: =W84/$AC$176/$W$183/$X$173 -> #REF! | Y84: =(T84+W84)=(SUM(AB85:AB89)) -> TRUE | Z84: =(T84+W84)-(SUM(AB85:AB89)) -> 0 | AD84: =W84+T84 -> 0 | AE84: =AD84 -> 0 | AF84: =AE84/$AE$151 -> #REF! | AG84: =AF84*$AG$158 -> #REF! | AH84: =AF84*$AG$161 -> #REF! | AJ84: =ROUND(AK84/L84,2) -> #REF! | AK84: =ROUND(AH84+AG84+AD84,2) -> #REF!
B85: =IFERROR(__xludf.DUMMYFUNCTION("IFERROR( IF(C85="""","""", IF(OR(REGEXMATCH(D85,""(?i)-Flashing""), REGEXMATCH(D85,""(?i)-EavesGut""), REGEXMATCH(D85,""(?i)Valley"")), ""DR"" & TEXT( ROUNDUP( MIN( VALUE(MID(C85, FIND("&"""("",C85)+1, FIND(""/"",C85)-FIND(""("",C85)-1)), 1200 ) / 50, 0 ) * 50, ""0"" ) & MID(C85, FIND(""/"",C85)+1, FIND("")"",C85)-FIND(""/"",C85)-1) & TEXT(H85*100,""0"") & I85,"&" IF(AND(D85=""Roof Sheet"", REGEXMATCH(C85,""(?i)KS\d{4}[A-Z]{2}"")), REGEXEXTRACT(C85,""(?i)KS\d{4}[A-Z]{2}""), IF(AND(REGEXMATCH(D85,""(?i)-DP""), REGEXMATCH(C85,""(?i)Downpipe"")), ""dp"" & REGEXEXTRACT(C85,""(\d+)"") & ""mm"", "&" IF(AND(REGEXMATCH(D85,""(?i)Bracket""), REGEXMATCH(C85,""(?i)Bracket"")), ""Brkt"" & REGEXEXTRACT(C85,""(\d+)"") & ""mm"", IF(AND(REGEXMATCH(D85,""(?i)-OP""), REGEXMATCH(C85,""(?i)pops"")), ""op"" & REGEXEXTRACT(C85,""(\d+)"") & ""mm"""&", IF(OR(D85=""R-FFTop"", D85=""R-FFBottom"", D85=""R-FFSide""), IF(REGEXMATCH(C85,""(?i)Profiled.*Top|Top.*Profiled""),""pfft"", IF(REGEXMATCH(C85,""(?i)Profiled.*Bottom|Bottom.*Profiled""),""pffb"", IF(REGEXMATCH(C85,""(?i)Squ"&"are""),""sff"",""""))), IF(REGEXMATCH(D85,""(?i)-Rivets""),""Rvt"", IF(REGEXMATCH(D85,""(?i)Silicone""),""300ml"", IF(REGEXMATCH(D85,""(?i)R-Butyl""),""300ml"", IF(REGEXMATCH(D85,""(?i)Fix""),""GenFix"", IF(AND(REGEXMATCH(C85,""(?i)Tim"&"ber""), REGEXMATCH(D85,""(?i)Timber"")),""tp"", IF(AND(REGEXMATCH(C85,""(?i)Vent G1275""), REGEXMATCH(D85,""(?i)Comb FIller"")),""CFV1275"", IF(REGEXMATCH(C85,""(?i)DPC""),""dpc"", IF(REGEXMATCH(C85,""(?i)Concealed Clips""),""ConClips"", I"&"F(REGEXMATCH(D85,""(?i)-Takeoff ea""),""Takeoff ea"", IF(REGEXMATCH(D85,""(?i)-Takeoff LM""),""Takeoff LM"", IF(REGEXMATCH(D85,""(?i)-Takeoff m2""),""Takeoff m2"", IF(D85=""R-TU/TD"",""TU/TD"",""""))))))))))))))))) )))"),"DR6003B55Mag") -> DR6003B55Mag | C85: 0.55mm BMT Coloursteel Maxam side barge flashing (570/3B) @ 5 deg | D85: R-Flashing | E85: =VALUE(MID(C85, FIND("(", C85)+1, FIND("/", C85)-FIND("(", C85)-1)) / 1000 -> 0.57 | F85: =IFERROR(__xludf.DUMMYFUNCTION("IFERROR(REGEXEXTRACT(C85,""@\s*(\d+)\s*deg"")&""°"","""") "),"5°") -> 5° | H85: =IFERROR(__xludf.DUMMYFUNCTION("IFERROR(REGEXEXTRACT(C85, ""(\d*\.\d+)mm""), """")"),"0.55") -> 0.55 | I85: Mag | J85: Specs | K85: LM | L85: 32.68 | M85: =L85 -> 32.68 | N85: =IFERROR(__xludf.DUMMYFUNCTION("""COMPUTED_VALUE"""),1.0038198375433474) -> 1.0038198 | O85: 1 | P85: 1 | Q85: =M85*N85*O85*P85 -> 32.804832 | S85: =R85*Q85 -> 0 | W85: =U85*Q85 -> 0 | AB85: =W85+S85 -> 0 | AM85: 32.68 | AN85: Matched | AO85: 0
B86: =IFERROR(__xludf.DUMMYFUNCTION("IFERROR( IF(C86="""","""", IF(OR(REGEXMATCH(D86,""(?i)-Flashing""), REGEXMATCH(D86,""(?i)-EavesGut""), REGEXMATCH(D86,""(?i)Valley"")), ""DR"" & TEXT( ROUNDUP( MIN( VALUE(MID(C86, FIND("&"""("",C86)+1, FIND(""/"",C86)-FIND(""("",C86)-1)), 1200 ) / 50, 0 ) * 50, ""0"" ) & MID(C86, FIND(""/"",C86)+1, FIND("")"",C86)-FIND(""/"",C86)-1) & TEXT(H86*100,""0"") & I86,"&" IF(AND(D86=""Roof Sheet"", REGEXMATCH(C86,""(?i)KS\d{4}[A-Z]{2}"")), REGEXEXTRACT(C86,""(?i)KS\d{4}[A-Z]{2}""), IF(AND(REGEXMATCH(D86,""(?i)-DP""), REGEXMATCH(C86,""(?i)Downpipe"")), ""dp"" & REGEXEXTRACT(C86,""(\d+)"") & ""mm"", "&" IF(AND(REGEXMATCH(D86,""(?i)Bracket""), REGEXMATCH(C86,""(?i)Bracket"")), ""Brkt"" & REGEXEXTRACT(C86,""(\d+)"") & ""mm"", IF(AND(REGEXMATCH(D86,""(?i)-OP""), REGEXMATCH(C86,""(?i)pops"")), ""op"" & REGEXEXTRACT(C86,""(\d+)"") & ""mm"""&", IF(OR(D86=""R-FFTop"", D86=""R-FFBottom"", D86=""R-FFSide""), IF(REGEXMATCH(C86,""(?i)Profiled.*Top|Top.*Profiled""),""pfft"", IF(REGEXMATCH(C86,""(?i)Profiled.*Bottom|Bottom.*Profiled""),""pffb"", IF(REGEXMATCH(C86,""(?i)Squ"&"are""),""sff"",""""))), IF(REGEXMATCH(D86,""(?i)-Rivets""),""Rvt"", IF(REGEXMATCH(D86,""(?i)Silicone""),""300ml"", IF(REGEXMATCH(D86,""(?i)R-Butyl""),""300ml"", IF(REGEXMATCH(D86,""(?i)Fix""),""GenFix"", IF(AND(REGEXMATCH(C86,""(?i)Tim"&"ber""), REGEXMATCH(D86,""(?i)Timber"")),""tp"", IF(AND(REGEXMATCH(C86,""(?i)Vent G1275""), REGEXMATCH(D86,""(?i)Comb FIller"")),""CFV1275"", IF(REGEXMATCH(C86,""(?i)DPC""),""dpc"", IF(REGEXMATCH(C86,""(?i)Concealed Clips""),""ConClips"", I"&"F(REGEXMATCH(D86,""(?i)-Takeoff ea""),""Takeoff ea"", IF(REGEXMATCH(D86,""(?i)-Takeoff LM""),""Takeoff LM"", IF(REGEXMATCH(D86,""(?i)-Takeoff m2""),""Takeoff m2"", IF(D86=""R-TU/TD"",""TU/TD"",""""))))))))))))))))) )))"),"300ml") -> 300ml | C86: Silicone 300ml | D86: R-Silicone | E86: =E85 -> 0.57 | F86: =F85 -> 5° | J86: No Specs | K86: ea | L86: =M85 -> 32.68 | M86: =(ROUNDDOWN((M85/5.7)+2,0)*E86)/8 -> 0.49875 | N86: =IFERROR(__xludf.DUMMYFUNCTION("""COMPUTED_VALUE"""),1.0038198375433474) -> 1.0038198 | O86: 1 | P86: 1 | Q86: =M86*N86*O86*P86 -> 0.50065514 | S86: =R86*Q86 -> 0 | W86: =U86*Q86 -> 0 | AB86: =W86+S86 -> 0 | AM86: 0.49875 | AN86: Matched | AO86: 0
B87: =IFERROR(__xludf.DUMMYFUNCTION("IFERROR( IF(C87="""","""", IF(OR(REGEXMATCH(D87,""(?i)-Flashing""), REGEXMATCH(D87,""(?i)-EavesGut""), REGEXMATCH(D87,""(?i)Valley"")), ""DR"" & TEXT( ROUNDUP( MIN( VALUE(MID(C87, FIND("&"""("",C87)+1, FIND(""/"",C87)-FIND(""("",C87)-1)), 1200 ) / 50, 0 ) * 50, ""0"" ) & MID(C87, FIND(""/"",C87)+1, FIND("")"",C87)-FIND(""/"",C87)-1) & TEXT(H87*100,""0"") & I87,"&" IF(AND(D87=""Roof Sheet"", REGEXMATCH(C87,""(?i)KS\d{4}[A-Z]{2}"")), REGEXEXTRACT(C87,""(?i)KS\d{4}[A-Z]{2}""), IF(AND(REGEXMATCH(D87,""(?i)-DP""), REGEXMATCH(C87,""(?i)Downpipe"")), ""dp"" & REGEXEXTRACT(C87,""(\d+)"") & ""mm"", "&" IF(AND(REGEXMATCH(D87,""(?i)Bracket""), REGEXMATCH(C87,""(?i)Bracket"")), ""Brkt"" & REGEXEXTRACT(C87,""(\d+)"") & ""mm"", IF(AND(REGEXMATCH(D87,""(?i)-OP""), REGEXMATCH(C87,""(?i)pops"")), ""op"" & REGEXEXTRACT(C87,""(\d+)"") & ""mm"""&", IF(OR(D87=""R-FFTop"", D87=""R-FFBottom"", D87=""R-FFSide""), IF(REGEXMATCH(C87,""(?i)Profiled.*Top|Top.*Profiled""),""pfft"", IF(REGEXMATCH(C87,""(?i)Profiled.*Bottom|Bottom.*Profiled""),""pffb"", IF(REGEXMATCH(C87,""(?i)Squ"&"are""),""sff"",""""))), IF(REGEXMATCH(D87,""(?i)-Rivets""),""Rvt"", IF(REGEXMATCH(D87,""(?i)Silicone""),""300ml"", IF(REGEXMATCH(D87,""(?i)R-Butyl""),""300ml"", IF(REGEXMATCH(D87,""(?i)Fix""),""GenFix"", IF(AND(REGEXMATCH(C87,""(?i)Tim"&"ber""), REGEXMATCH(D87,""(?i)Timber"")),""tp"", IF(AND(REGEXMATCH(C87,""(?i)Vent G1275""), REGEXMATCH(D87,""(?i)Comb FIller"")),""CFV1275"", IF(REGEXMATCH(C87,""(?i)DPC""),""dpc"", IF(REGEXMATCH(C87,""(?i)Concealed Clips""),""ConClips"", I"&"F(REGEXMATCH(D87,""(?i)-Takeoff ea""),""Takeoff ea"", IF(REGEXMATCH(D87,""(?i)-Takeoff LM""),""Takeoff LM"", IF(REGEXMATCH(D87,""(?i)-Takeoff m2""),""Takeoff m2"", IF(D87=""R-TU/TD"",""TU/TD"",""""))))))))))))))))) )))"),"Rvt") -> Rvt | C87: Rivets | D87: R-Rivets | E87: =E85 -> 0.57 | F87: =F86 -> 5° | J87: No Specs | K87: ea | L87: =M85 -> 32.68 | M87: =ROUNDUP(((M85/5.7)+1)*(E87/0.05),0) -> 77 | N87: =IFERROR(__xludf.DUMMYFUNCTION("""COMPUTED_VALUE"""),1.0038198375433474) -> 1.0038198 | O87: 1 | P87: 1 | Q87: =M87*N87*O87*P87 -> 77.294127 | S87: =R87*Q87 -> 0 | W87: =U87*Q87 -> 0 | AB87: =W87+S87 -> 0 | AM87: 77 | AN87: Matched | AO87: 0
B88: =IFERROR(__xludf.DUMMYFUNCTION("IFERROR( IF(C88="""","""", IF(OR(REGEXMATCH(D88,""(?i)-Flashing""), REGEXMATCH(D88,""(?i)-EavesGut""), REGEXMATCH(D88,""(?i)Valley"")), ""DR"" & TEXT( ROUNDUP( MIN( VALUE(MID(C88, FIND("&"""("",C88)+1, FIND(""/"",C88)-FIND(""("",C88)-1)), 1200 ) / 50, 0 ) * 50, ""0"" ) & MID(C88, FIND(""/"",C88)+1, FIND("")"",C88)-FIND(""/"",C88)-1) & TEXT(H88*100,""0"") & I88,"&" IF(AND(D88=""Roof Sheet"", REGEXMATCH(C88,""(?i)KS\d{4}[A-Z]{2}"")), REGEXEXTRACT(C88,""(?i)KS\d{4}[A-Z]{2}""), IF(AND(REGEXMATCH(D88,""(?i)-DP""), REGEXMATCH(C88,""(?i)Downpipe"")), ""dp"" & REGEXEXTRACT(C88,""(\d+)"") & ""mm"", "&" IF(AND(REGEXMATCH(D88,""(?i)Bracket""), REGEXMATCH(C88,""(?i)Bracket"")), ""Brkt"" & REGEXEXTRACT(C88,""(\d+)"") & ""mm"", IF(AND(REGEXMATCH(D88,""(?i)-OP""), REGEXMATCH(C88,""(?i)pops"")), ""op"" & REGEXEXTRACT(C88,""(\d+)"") & ""mm"""&", IF(OR(D88=""R-FFTop"", D88=""R-FFBottom"", D88=""R-FFSide""), IF(REGEXMATCH(C88,""(?i)Profiled.*Top|Top.*Profiled""),""pfft"", IF(REGEXMATCH(C88,""(?i)Profiled.*Bottom|Bottom.*Profiled""),""pffb"", IF(REGEXMATCH(C88,""(?i)Squ"&"are""),""sff"",""""))), IF(REGEXMATCH(D88,""(?i)-Rivets""),""Rvt"", IF(REGEXMATCH(D88,""(?i)Silicone""),""300ml"", IF(REGEXMATCH(D88,""(?i)R-Butyl""),""300ml"", IF(REGEXMATCH(D88,""(?i)Fix""),""GenFix"", IF(AND(REGEXMATCH(C88,""(?i)Tim"&"ber""), REGEXMATCH(D88,""(?i)Timber"")),""tp"", IF(AND(REGEXMATCH(C88,""(?i)Vent G1275""), REGEXMATCH(D88,""(?i)Comb FIller"")),""CFV1275"", IF(REGEXMATCH(C88,""(?i)DPC""),""dpc"", IF(REGEXMATCH(C88,""(?i)Concealed Clips""),""ConClips"", I"&"F(REGEXMATCH(D88,""(?i)-Takeoff ea""),""Takeoff ea"", IF(REGEXMATCH(D88,""(?i)-Takeoff LM""),""Takeoff LM"", IF(REGEXMATCH(D88,""(?i)-Takeoff m2""),""Takeoff m2"", IF(D88=""R-TU/TD"",""TU/TD"",""""))))))))))))))))) )))"),"GenFix") -> GenFix | C88: Fixings | D88: R-GenFix | F88: =F87 -> 5° | J88: No Specs | K88: ea | L88: =M85 -> 32.68 | M88: =ROUNDUP(M85/0.6,0)+1 -> 56 | N88: =IFERROR(__xludf.DUMMYFUNCTION("""COMPUTED_VALUE"""),1.0038198375433474) -> 1.0038198 | O88: 1 | P88: 1 | Q88: =M88*N88*O88*P88 -> 56.213911 | S88: =R88*Q88 -> 0 | W88: =U88*Q88 -> 0 | AB88: =W88+S88 -> 0 | AM88: 56 | AN88: Matched | AO88: 0
B89: =IFERROR(__xludf.DUMMYFUNCTION("IFERROR( IF(C89="""","""", IF(OR(REGEXMATCH(D89,""(?i)-Flashing""), REGEXMATCH(D89,""(?i)-EavesGut""), REGEXMATCH(D89,""(?i)Valley"")), ""DR"" & TEXT( ROUNDUP( MIN( VALUE(MID(C89, FIND("&"""("",C89)+1, FIND(""/"",C89)-FIND(""("",C89)-1)), 1200 ) / 50, 0 ) * 50, ""0"" ) & MID(C89, FIND(""/"",C89)+1, FIND("")"",C89)-FIND(""/"",C89)-1) & TEXT(H89*100,""0"") & I89,"&" IF(AND(D89=""Roof Sheet"", REGEXMATCH(C89,""(?i)KS\d{4}[A-Z]{2}"")), REGEXEXTRACT(C89,""(?i)KS\d{4}[A-Z]{2}""), IF(AND(REGEXMATCH(D89,""(?i)-DP""), REGEXMATCH(C89,""(?i)Downpipe"")), ""dp"" & REGEXEXTRACT(C89,""(\d+)"") & ""mm"", "&" IF(AND(REGEXMATCH(D89,""(?i)Bracket""), REGEXMATCH(C89,""(?i)Bracket"")), ""Brkt"" & REGEXEXTRACT(C89,""(\d+)"") & ""mm"", IF(AND(REGEXMATCH(D89,""(?i)-OP""), REGEXMATCH(C89,""(?i)pops"")), ""op"" & REGEXEXTRACT(C89,""(\d+)"") & ""mm"""&", IF(OR(D89=""R-FFTop"", D89=""R-FFBottom"", D89=""R-FFSide""), IF(REGEXMATCH(C89,""(?i)Profiled.*Top|Top.*Profiled""),""pfft"", IF(REGEXMATCH(C89,""(?i)Profiled.*Bottom|Bottom.*Profiled""),""pffb"", IF(REGEXMATCH(C89,""(?i)Squ"&"are""),""sff"",""""))), IF(REGEXMATCH(D89,""(?i)-Rivets""),""Rvt"", IF(REGEXMATCH(D89,""(?i)Silicone""),""300ml"", IF(REGEXMATCH(D89,""(?i)R-Butyl""),""300ml"", IF(REGEXMATCH(D89,""(?i)Fix""),""GenFix"", IF(AND(REGEXMATCH(C89,""(?i)Tim"&"ber""), REGEXMATCH(D89,""(?i)Timber"")),""tp"", IF(AND(REGEXMATCH(C89,""(?i)Vent G1275""), REGEXMATCH(D89,""(?i)Comb FIller"")),""CFV1275"", IF(REGEXMATCH(C89,""(?i)DPC""),""dpc"", IF(REGEXMATCH(C89,""(?i)Concealed Clips""),""ConClips"", I"&"F(REGEXMATCH(D89,""(?i)-Takeoff ea""),""Takeoff ea"", IF(REGEXMATCH(D89,""(?i)-Takeoff LM""),""Takeoff LM"", IF(REGEXMATCH(D89,""(?i)-Takeoff m2""),""Takeoff m2"", IF(D89=""R-TU/TD"",""TU/TD"",""""))))))))))))))))) )))"),"sff") -> sff | C89: Square Foam Filler Top | D89: R-FFSide | F89: =F88 -> 5° | J89: No Specs | K89: LM | L89: =M85 -> 32.68 | M89: =M85 -> 32.68 | N89: =IFERROR(__xludf.DUMMYFUNCTION("""COMPUTED_VALUE"""),1.0038198375433474) -> 1.0038198 | O89: 1 | P89: 1 | Q89: =M89*N89*O89*P89 -> 32.804832 | S89: =R89*Q89 -> 0 | W89: =U89*Q89 -> 0 | AB89: =W89+S89 -> 0 | AM89: 32.68 | AN89: Matched | AO89: 0
N90: =IFERROR(__xludf.DUMMYFUNCTION("""COMPUTED_VALUE"""),"")
A91: 1 | C91: Supply and install 0.55mm BMT cover flashing, as per detail 4 (A502) | L91: =Q91 -> 112.78 | N91: =IFERROR(__xludf.DUMMYFUNCTION("""COMPUTED_VALUE"""),"") | Q91: =Q92 -> 112.78 | S91: =T91/Q91 -> 0 | T91: =SUM(S92:S95) -> 0 | V91: =W91/Q91 -> 0 | W91: =SUM(W92:W95) -> 0 | X91: =W91/$AC$176/$W$183/$X$173 -> #REF! | Y91: =(T91+W91)=(SUM(AB92:AB95)) -> TRUE | Z91: =(T91+W91)-(SUM(AB92:AB95)) -> 0 | AD91: =W91+T91 -> 0 | AE91: =AD91 -> 0 | AF91: =AE91/$AE$151 -> #REF! | AG91: =AF91*$AG$158 -> #REF! | AH91: =AF91*$AG$161 -> #REF! | AJ91: =ROUND(AK91/L91,2) -> #REF! | AK91: =ROUND(AH91+AG91+AD91,2) -> #REF!
B92: =IFERROR(__xludf.DUMMYFUNCTION("IFERROR( IF(C92="""","""", IF(OR(REGEXMATCH(D92,""(?i)-Flashing""), REGEXMATCH(D92,""(?i)-EavesGut""), REGEXMATCH(D92,""(?i)Valley"")), ""DR"" & TEXT( ROUNDUP( MIN( VALUE(MID(C92, FIND("&"""("",C92)+1, FIND(""/"",C92)-FIND(""("",C92)-1)), 1200 ) / 50, 0 ) * 50, ""0"" ) & MID(C92, FIND(""/"",C92)+1, FIND("")"",C92)-FIND(""/"",C92)-1) & TEXT(H92*100,""0"") & I92,"&" IF(AND(D92=""Roof Sheet"", REGEXMATCH(C92,""(?i)KS\d{4}[A-Z]{2}"")), REGEXEXTRACT(C92,""(?i)KS\d{4}[A-Z]{2}""), IF(AND(REGEXMATCH(D92,""(?i)-DP""), REGEXMATCH(C92,""(?i)Downpipe"")), ""dp"" & REGEXEXTRACT(C92,""(\d+)"") & ""mm"", "&" IF(AND(REGEXMATCH(D92,""(?i)Bracket""), REGEXMATCH(C92,""(?i)Bracket"")), ""Brkt"" & REGEXEXTRACT(C92,""(\d+)"") & ""mm"", IF(AND(REGEXMATCH(D92,""(?i)-OP""), REGEXMATCH(C92,""(?i)pops"")), ""op"" & REGEXEXTRACT(C92,""(\d+)"") & ""mm"""&", IF(OR(D92=""R-FFTop"", D92=""R-FFBottom"", D92=""R-FFSide""), IF(REGEXMATCH(C92,""(?i)Profiled.*Top|Top.*Profiled""),""pfft"", IF(REGEXMATCH(C92,""(?i)Profiled.*Bottom|Bottom.*Profiled""),""pffb"", IF(REGEXMATCH(C92,""(?i)Squ"&"are""),""sff"",""""))), IF(REGEXMATCH(D92,""(?i)-Rivets""),""Rvt"", IF(REGEXMATCH(D92,""(?i)Silicone""),""300ml"", IF(REGEXMATCH(D92,""(?i)R-Butyl""),""300ml"", IF(REGEXMATCH(D92,""(?i)Fix""),""GenFix"", IF(AND(REGEXMATCH(C92,""(?i)Tim"&"ber""), REGEXMATCH(D92,""(?i)Timber"")),""tp"", IF(AND(REGEXMATCH(C92,""(?i)Vent G1275""), REGEXMATCH(D92,""(?i)Comb FIller"")),""CFV1275"", IF(REGEXMATCH(C92,""(?i)DPC""),""dpc"", IF(REGEXMATCH(C92,""(?i)Concealed Clips""),""ConClips"", I"&"F(REGEXMATCH(D92,""(?i)-Takeoff ea""),""Takeoff ea"", IF(REGEXMATCH(D92,""(?i)-Takeoff LM""),""Takeoff LM"", IF(REGEXMATCH(D92,""(?i)-Takeoff m2""),""Takeoff m2"", IF(D92=""R-TU/TD"",""TU/TD"",""""))))))))))))))))) )))"),"DR7508B55Mag") -> DR7508B55Mag | C92: 0.55mm BMT cover flashing (710/8B) | D92: R-Flashing | E92: =VALUE(MID(C92, FIND("(", C92)+1, FIND("/", C92)-FIND("(", C92)-1)) / 1000 -> 0.71 | F92: =IFERROR(__xludf.DUMMYFUNCTION("IFERROR(REGEXEXTRACT(C92,""@\s*(\d+)\s*deg"")&""°"","""") "),"") | H92: =IFERROR(__xludf.DUMMYFUNCTION("IFERROR(REGEXEXTRACT(C92, ""(\d*\.\d+)mm""), """")"),"0.55") -> 0.55 | I92: Mag | J92: Specs | K92: LM | L92: =L105 -> 112.78 | M92: =L92 -> 112.78 | N92: =IFERROR(__xludf.DUMMYFUNCTION("""COMPUTED_VALUE"""),1.0) -> 1 | O92: 1 | P92: 1 | Q92: =M92*N92*O92*P92 -> 112.78 | S92: =R92*Q92 -> 0 | W92: =U92*Q92 -> 0 | X92: =W92/$AC$176/$W$183/Y92 -> #REF! | Y92: 2 | Z92: =Q92/X92 -> #REF! | AB92: =W92+S92 -> 0 | AM92: 112.78 | AN92: Matched | AO92: 0
B93: =IFERROR(__xludf.DUMMYFUNCTION("IFERROR( IF(C93="""","""", IF(OR(REGEXMATCH(D93,""(?i)-Flashing""), REGEXMATCH(D93,""(?i)-EavesGut""), REGEXMATCH(D93,""(?i)Valley"")), ""DR"" & TEXT( ROUNDUP( MIN( VALUE(MID(C93, FIND("&"""("",C93)+1, FIND(""/"",C93)-FIND(""("",C93)-1)), 1200 ) / 50, 0 ) * 50, ""0"" ) & MID(C93, FIND(""/"",C93)+1, FIND("")"",C93)-FIND(""/"",C93)-1) & TEXT(H93*100,""0"") & I93,"&" IF(AND(D93=""Roof Sheet"", REGEXMATCH(C93,""(?i)KS\d{4}[A-Z]{2}"")), REGEXEXTRACT(C93,""(?i)KS\d{4}[A-Z]{2}""), IF(AND(REGEXMATCH(D93,""(?i)-DP""), REGEXMATCH(C93,""(?i)Downpipe"")), ""dp"" & REGEXEXTRACT(C93,""(\d+)"") & ""mm"", "&" IF(AND(REGEXMATCH(D93,""(?i)Bracket""), REGEXMATCH(C93,""(?i)Bracket"")), ""Brkt"" & REGEXEXTRACT(C93,""(\d+)"") & ""mm"", IF(AND(REGEXMATCH(D93,""(?i)-OP""), REGEXMATCH(C93,""(?i)pops"")), ""op"" & REGEXEXTRACT(C93,""(\d+)"") & ""mm"""&", IF(OR(D93=""R-FFTop"", D93=""R-FFBottom"", D93=""R-FFSide""), IF(REGEXMATCH(C93,""(?i)Profiled.*Top|Top.*Profiled""),""pfft"", IF(REGEXMATCH(C93,""(?i)Profiled.*Bottom|Bottom.*Profiled""),""pffb"", IF(REGEXMATCH(C93,""(?i)Squ"&"are""),""sff"",""""))), IF(REGEXMATCH(D93,""(?i)-Rivets""),""Rvt"", IF(REGEXMATCH(D93,""(?i)Silicone""),""300ml"", IF(REGEXMATCH(D93,""(?i)R-Butyl""),""300ml"", IF(REGEXMATCH(D93,""(?i)Fix""),""GenFix"", IF(AND(REGEXMATCH(C93,""(?i)Tim"&"ber""), REGEXMATCH(D93,""(?i)Timber"")),""tp"", IF(AND(REGEXMATCH(C93,""(?i)Vent G1275""), REGEXMATCH(D93,""(?i)Comb FIller"")),""CFV1275"", IF(REGEXMATCH(C93,""(?i)DPC""),""dpc"", IF(REGEXMATCH(C93,""(?i)Concealed Clips""),""ConClips"", I"&"F(REGEXMATCH(D93,""(?i)-Takeoff ea""),""Takeoff ea"", IF(REGEXMATCH(D93,""(?i)-Takeoff LM""),""Takeoff LM"", IF(REGEXMATCH(D93,""(?i)-Takeoff m2""),""Takeoff m2"", IF(D93=""R-TU/TD"",""TU/TD"",""""))))))))))))))))) )))"),"300ml") -> 300ml | C93: Silicone 300ml | D93: R-Silicone | E93: =E92 -> 0.71 | F93: =F92 | J93: No Specs | K93: ea | L93: =M92 -> 112.78 | M93: =(ROUNDDOWN((M92/5.7)+2,0)*E93)/8 -> 1.86375 | N93: =IFERROR(__xludf.DUMMYFUNCTION("""COMPUTED_VALUE"""),1.0) -> 1 | O93: 1 | P93: 1 | Q93: =M93*N93*O93*P93 -> 1.86375 | S93: =R93*Q93 -> 0 | W93: =U93*Q93 -> 0 | AB93: =W93+S93 -> 0 | AM93: 1.86375 | AN93: Matched | AO93: 0
B94: =IFERROR(__xludf.DUMMYFUNCTION("IFERROR( IF(C94="""","""", IF(OR(REGEXMATCH(D94,""(?i)-Flashing""), REGEXMATCH(D94,""(?i)-EavesGut""), REGEXMATCH(D94,""(?i)Valley"")), ""DR"" & TEXT( ROUNDUP( MIN( VALUE(MID(C94, FIND("&"""("",C94)+1, FIND(""/"",C94)-FIND(""("",C94)-1)), 1200 ) / 50, 0 ) * 50, ""0"" ) & MID(C94, FIND(""/"",C94)+1, FIND("")"",C94)-FIND(""/"",C94)-1) & TEXT(H94*100,""0"") & I94,"&" IF(AND(D94=""Roof Sheet"", REGEXMATCH(C94,""(?i)KS\d{4}[A-Z]{2}"")), REGEXEXTRACT(C94,""(?i)KS\d{4}[A-Z]{2}""), IF(AND(REGEXMATCH(D94,""(?i)-DP""), REGEXMATCH(C94,""(?i)Downpipe"")), ""dp"" & REGEXEXTRACT(C94,""(\d+)"") & ""mm"", "&" IF(AND(REGEXMATCH(D94,""(?i)Bracket""), REGEXMATCH(C94,""(?i)Bracket"")), ""Brkt"" & REGEXEXTRACT(C94,""(\d+)"") & ""mm"", IF(AND(REGEXMATCH(D94,""(?i)-OP""), REGEXMATCH(C94,""(?i)pops"")), ""op"" & REGEXEXTRACT(C94,""(\d+)"") & ""mm"""&", IF(OR(D94=""R-FFTop"", D94=""R-FFBottom"", D94=""R-FFSide""), IF(REGEXMATCH(C94,""(?i)Profiled.*Top|Top.*Profiled""),""pfft"", IF(REGEXMATCH(C94,""(?i)Profiled.*Bottom|Bottom.*Profiled""),""pffb"", IF(REGEXMATCH(C94,""(?i)Squ"&"are""),""sff"",""""))), IF(REGEXMATCH(D94,""(?i)-Rivets""),""Rvt"", IF(REGEXMATCH(D94,""(?i)Silicone""),""300ml"", IF(REGEXMATCH(D94,""(?i)R-Butyl""),""300ml"", IF(REGEXMATCH(D94,""(?i)Fix""),""GenFix"", IF(AND(REGEXMATCH(C94,""(?i)Tim"&"ber""), REGEXMATCH(D94,""(?i)Timber"")),""tp"", IF(AND(REGEXMATCH(C94,""(?i)Vent G1275""), REGEXMATCH(D94,""(?i)Comb FIller"")),""CFV1275"", IF(REGEXMATCH(C94,""(?i)DPC""),""dpc"", IF(REGEXMATCH(C94,""(?i)Concealed Clips""),""ConClips"", I"&"F(REGEXMATCH(D94,""(?i)-Takeoff ea""),""Takeoff ea"", IF(REGEXMATCH(D94,""(?i)-Takeoff LM""),""Takeoff LM"", IF(REGEXMATCH(D94,""(?i)-Takeoff m2""),""Takeoff m2"", IF(D94=""R-TU/TD"",""TU/TD"",""""))))))))))))))))) )))"),"Rvt") -> Rvt | C94: Rivets | D94: R-Rivets | E94: =E92 -> 0.71 | F94: =F93 | J94: No Specs | K94: ea | L94: =M92 -> 112.78 | M94: =ROUNDUP(((M92/5.7)+1)*(E94/0.05),0) -> 296 | N94: =IFERROR(__xludf.DUMMYFUNCTION("""COMPUTED_VALUE"""),1.0) -> 1 | O94: 1 | P94: 1 | Q94: =M94*N94*O94*P94 -> 296 | S94: =R94*Q94 -> 0 | W94: =U94*Q94 -> 0 | AB94: =W94+S94 -> 0 | AM94: 296 | AN94: Matched | AO94: 0
B95: =IFERROR(__xludf.DUMMYFUNCTION("IFERROR( IF(C95="""","""", IF(OR(REGEXMATCH(D95,""(?i)-Flashing""), REGEXMATCH(D95,""(?i)-EavesGut""), REGEXMATCH(D95,""(?i)Valley"")), ""DR"" & TEXT( ROUNDUP( MIN( VALUE(MID(C95, FIND("&"""("",C95)+1, FIND(""/"",C95)-FIND(""("",C95)-1)), 1200 ) / 50, 0 ) * 50, ""0"" ) & MID(C95, FIND(""/"",C95)+1, FIND("")"",C95)-FIND(""/"",C95)-1) & TEXT(H95*100,""0"") & I95,"&" IF(AND(D95=""Roof Sheet"", REGEXMATCH(C95,""(?i)KS\d{4}[A-Z]{2}"")), REGEXEXTRACT(C95,""(?i)KS\d{4}[A-Z]{2}""), IF(AND(REGEXMATCH(D95,""(?i)-DP""), REGEXMATCH(C95,""(?i)Downpipe"")), ""dp"" & REGEXEXTRACT(C95,""(\d+)"") & ""mm"", "&" IF(AND(REGEXMATCH(D95,""(?i)Bracket""), REGEXMATCH(C95,""(?i)Bracket"")), ""Brkt"" & REGEXEXTRACT(C95,""(\d+)"") & ""mm"", IF(AND(REGEXMATCH(D95,""(?i)-OP""), REGEXMATCH(C95,""(?i)pops"")), ""op"" & REGEXEXTRACT(C95,""(\d+)"") & ""mm"""&", IF(OR(D95=""R-FFTop"", D95=""R-FFBottom"", D95=""R-FFSide""), IF(REGEXMATCH(C95,""(?i)Profiled.*Top|Top.*Profiled""),""pfft"", IF(REGEXMATCH(C95,""(?i)Profiled.*Bottom|Bottom.*Profiled""),""pffb"", IF(REGEXMATCH(C95,""(?i)Squ"&"are""),""sff"",""""))), IF(REGEXMATCH(D95,""(?i)-Rivets""),""Rvt"", IF(REGEXMATCH(D95,""(?i)Silicone""),""300ml"", IF(REGEXMATCH(D95,""(?i)R-Butyl""),""300ml"", IF(REGEXMATCH(D95,""(?i)Fix""),""GenFix"", IF(AND(REGEXMATCH(C95,""(?i)Tim"&"ber""), REGEXMATCH(D95,""(?i)Timber"")),""tp"", IF(AND(REGEXMATCH(C95,""(?i)Vent G1275""), REGEXMATCH(D95,""(?i)Comb FIller"")),""CFV1275"", IF(REGEXMATCH(C95,""(?i)DPC""),""dpc"", IF(REGEXMATCH(C95,""(?i)Concealed Clips""),""ConClips"", I"&"F(REGEXMATCH(D95,""(?i)-Takeoff ea""),""Takeoff ea"", IF(REGEXMATCH(D95,""(?i)-Takeoff LM""),""Takeoff LM"", IF(REGEXMATCH(D95,""(?i)-Takeoff m2""),""Takeoff m2"", IF(D95=""R-TU/TD"",""TU/TD"",""""))))))))))))))))) )))"),"GenFix") -> GenFix | C95: Fixings | D95: R-GenFix | F95: =F94 | J95: No Specs | K95: ea | L95: =M92 -> 112.78 | M95: =ROUNDUP(M92/0.6,0)+1 -> 189 | N95: =IFERROR(__xludf.DUMMYFUNCTION("""COMPUTED_VALUE"""),1.0) -> 1 | O95: 1 | P95: 1 | Q95: =M95*N95*O95*P95 -> 189 | S95: =R95*Q95 -> 0 | W95: =U95*Q95 -> 0 | AB95: =W95+S95 -> 0 | AM95: 189 | AN95: Matched | AO95: 0
N96: =IFERROR(__xludf.DUMMYFUNCTION("""COMPUTED_VALUE"""),"")
A97: 1 | C97: Supply and install 0.55mm BMT Coloursteel Maxam eaves flashing, as per detail 4 (A502) | L97: =Q97 -> 112.78 | N97: =IFERROR(__xludf.DUMMYFUNCTION("""COMPUTED_VALUE"""),"") | Q97: =Q98 -> 112.78 | S97: =T97/Q97 -> 0 | T97: =SUM(S98:S102) -> 0 | V97: =W97/Q97 -> 0 | W97: =SUM(W98:W102) -> 0 | X97: =W97/$AC$176/$W$183/Y97 -> #REF! | Y97: =(T97+W97)=(SUM(AB98:AB102)) -> TRUE | Z97: =(T97+W97)-(SUM(AB98:AB102)) -> 0 | AD97: =W97+T97 -> 0 | AE97: =AD97 -> 0 | AF97: =AE97/$AE$151 -> #REF! | AG97: =AF97*$AG$158 -> #REF! | AH97: =AF97*$AG$161 -> #REF! | AJ97: =ROUND(AK97/L97,2) -> #REF! | AK97: =ROUND(AH97+AG97+AD97,2) -> #REF!
B98: =IFERROR(__xludf.DUMMYFUNCTION("IFERROR( IF(C98="""","""", IF(OR(REGEXMATCH(D98,""(?i)-Flashing""), REGEXMATCH(D98,""(?i)-EavesGut""), REGEXMATCH(D98,""(?i)Valley"")), ""DR"" & TEXT( ROUNDUP( MIN( VALUE(MID(C98, FIND("&"""("",C98)+1, FIND(""/"",C98)-FIND(""("",C98)-1)), 1200 ) / 50, 0 ) * 50, ""0"" ) & MID(C98, FIND(""/"",C98)+1, FIND("")"",C98)-FIND(""/"",C98)-1) & TEXT(H98*100,""0"") & I98,"&" IF(AND(D98=""Roof Sheet"", REGEXMATCH(C98,""(?i)KS\d{4}[A-Z]{2}"")), REGEXEXTRACT(C98,""(?i)KS\d{4}[A-Z]{2}""), IF(AND(REGEXMATCH(D98,""(?i)-DP""), REGEXMATCH(C98,""(?i)Downpipe"")), ""dp"" & REGEXEXTRACT(C98,""(\d+)"") & ""mm"", "&" IF(AND(REGEXMATCH(D98,""(?i)Bracket""), REGEXMATCH(C98,""(?i)Bracket"")), ""Brkt"" & REGEXEXTRACT(C98,""(\d+)"") & ""mm"", IF(AND(REGEXMATCH(D98,""(?i)-OP""), REGEXMATCH(C98,""(?i)pops"")), ""op"" & REGEXEXTRACT(C98,""(\d+)"") & ""mm"""&", IF(OR(D98=""R-FFTop"", D98=""R-FFBottom"", D98=""R-FFSide""), IF(REGEXMATCH(C98,""(?i)Profiled.*Top|Top.*Profiled""),""pfft"", IF(REGEXMATCH(C98,""(?i)Profiled.*Bottom|Bottom.*Profiled""),""pffb"", IF(REGEXMATCH(C98,""(?i)Squ"&"are""),""sff"",""""))), IF(REGEXMATCH(D98,""(?i)-Rivets""),""Rvt"", IF(REGEXMATCH(D98,""(?i)Silicone""),""300ml"", IF(REGEXMATCH(D98,""(?i)R-Butyl""),""300ml"", IF(REGEXMATCH(D98,""(?i)Fix""),""GenFix"", IF(AND(REGEXMATCH(C98,""(?i)Tim"&"ber""), REGEXMATCH(D98,""(?i)Timber"")),""tp"", IF(AND(REGEXMATCH(C98,""(?i)Vent G1275""), REGEXMATCH(D98,""(?i)Comb FIller"")),""CFV1275"", IF(REGEXMATCH(C98,""(?i)DPC""),""dpc"", IF(REGEXMATCH(C98,""(?i)Concealed Clips""),""ConClips"", I"&"F(REGEXMATCH(D98,""(?i)-Takeoff ea""),""Takeoff ea"", IF(REGEXMATCH(D98,""(?i)-Takeoff LM""),""Takeoff LM"", IF(REGEXMATCH(D98,""(?i)-Takeoff m2""),""Takeoff m2"", IF(D98=""R-TU/TD"",""TU/TD"",""""))))))))))))))))) )))"),"DR3503B55Mag") -> DR3503B55Mag | C98: 0.55mm BMT Coloursteel Maxam eaves flashing (320/3B) | D98: R-Flashing | E98: =VALUE(MID(C98, FIND("(", C98)+1, FIND("/", C98)-FIND("(", C98)-1)) / 1000 -> 0.32 | F98: =IFERROR(__xludf.DUMMYFUNCTION("IFERROR(REGEXEXTRACT(C98,""@\s*(\d+)\s*deg"")&""°"","""") "),"") | H98: =IFERROR(__xludf.DUMMYFUNCTION("IFERROR(REGEXEXTRACT(C98, ""(\d*\.\d+)mm""), """")"),"0.55") -> 0.55 | I98: Mag | J98: Specs | K98: LM | L98: =L105 -> 112.78 | M98: =L98 -> 112.78 | N98: =IFERROR(__xludf.DUMMYFUNCTION("""COMPUTED_VALUE"""),1.0) -> 1 | O98: 1 | P98: 1 | Q98: =M98*N98*O98*P98 -> 112.78 | S98: =R98*Q98 -> 0 | W98: =U98*Q98 -> 0 | X98: =W98/$AC$176/$W$183/Y98 -> #REF! | Y98: 2 | Z98: =Q98/X98 -> #REF! | AB98: =W98+S98 -> 0 | AM98: 112.78 | AN98: Matched | AO98: 0
B99: =IFERROR(__xludf.DUMMYFUNCTION("IFERROR( IF(C99="""","""", IF(OR(REGEXMATCH(D99,""(?i)-Flashing""), REGEXMATCH(D99,""(?i)-EavesGut""), REGEXMATCH(D99,""(?i)Valley"")), ""DR"" & TEXT( ROUNDUP( MIN( VALUE(MID(C99, FIND("&"""("",C99)+1, FIND(""/"",C99)-FIND(""("",C99)-1)), 1200 ) / 50, 0 ) * 50, ""0"" ) & MID(C99, FIND(""/"",C99)+1, FIND("")"",C99)-FIND(""/"",C99)-1) & TEXT(H99*100,""0"") & I99,"&" IF(AND(D99=""Roof Sheet"", REGEXMATCH(C99,""(?i)KS\d{4}[A-Z]{2}"")), REGEXEXTRACT(C99,""(?i)KS\d{4}[A-Z]{2}""), IF(AND(REGEXMATCH(D99,""(?i)-DP""), REGEXMATCH(C99,""(?i)Downpipe"")), ""dp"" & REGEXEXTRACT(C99,""(\d+)"") & ""mm"", "&" IF(AND(REGEXMATCH(D99,""(?i)Bracket""), REGEXMATCH(C99,""(?i)Bracket"")), ""Brkt"" & REGEXEXTRACT(C99,""(\d+)"") & ""mm"", IF(AND(REGEXMATCH(D99,""(?i)-OP""), REGEXMATCH(C99,""(?i)pops"")), ""op"" & REGEXEXTRACT(C99,""(\d+)"") & ""mm"""&", IF(OR(D99=""R-FFTop"", D99=""R-FFBottom"", D99=""R-FFSide""), IF(REGEXMATCH(C99,""(?i)Profiled.*Top|Top.*Profiled""),""pfft"", IF(REGEXMATCH(C99,""(?i)Profiled.*Bottom|Bottom.*Profiled""),""pffb"", IF(REGEXMATCH(C99,""(?i)Squ"&"are""),""sff"",""""))), IF(REGEXMATCH(D99,""(?i)-Rivets""),""Rvt"", IF(REGEXMATCH(D99,""(?i)Silicone""),""300ml"", IF(REGEXMATCH(D99,""(?i)R-Butyl""),""300ml"", IF(REGEXMATCH(D99,""(?i)Fix""),""GenFix"", IF(AND(REGEXMATCH(C99,""(?i)Tim"&"ber""), REGEXMATCH(D99,""(?i)Timber"")),""tp"", IF(AND(REGEXMATCH(C99,""(?i)Vent G1275""), REGEXMATCH(D99,""(?i)Comb FIller"")),""CFV1275"", IF(REGEXMATCH(C99,""(?i)DPC""),""dpc"", IF(REGEXMATCH(C99,""(?i)Concealed Clips""),""ConClips"", I"&"F(REGEXMATCH(D99,""(?i)-Takeoff ea""),""Takeoff ea"", IF(REGEXMATCH(D99,""(?i)-Takeoff LM""),""Takeoff LM"", IF(REGEXMATCH(D99,""(?i)-Takeoff m2""),""Takeoff m2"", IF(D99=""R-TU/TD"",""TU/TD"",""""))))))))))))))))) )))"),"300ml") -> 300ml | C99: Silicone 300ml | D99: R-Silicone | E99: =E98 -> 0.32 | F99: =F98 | J99: No Specs | K99: ea | L99: =M98 -> 112.78 | M99: =(ROUNDDOWN((M98/5.7)+2,0)*E99)/8 -> 0.84 | N99: =IFERROR(__xludf.DUMMYFUNCTION("""COMPUTED_VALUE"""),1.0) -> 1 | O99: 1 | P99: 1 | Q99: =M99*N99*O99*P99 -> 0.84 | S99: =R99*Q99 -> 0 | W99: =U99*Q99 -> 0 | AB99: =W99+S99 -> 0 | AM99: 0.84 | AN99: Matched | AO99: 0
B100: =IFERROR(__xludf.DUMMYFUNCTION("IFERROR( IF(C100="""","""", IF(OR(REGEXMATCH(D100,""(?i)-Flashing""), REGEXMATCH(D100,""(?i)-EavesGut""), REGEXMATCH(D100,""(?i)Valley"")), ""DR"" & TEXT( ROUNDUP( MIN( VALUE(MID(C100, "&"FIND(""("",C100)+1, FIND(""/"",C100)-FIND(""("",C100)-1)), 1200 ) / 50, 0 ) * 50, ""0"" ) & MID(C100, FIND(""/"",C100)+1, FIND("")"",C100)-FIND(""/"",C100)-1) & TEXT(H100*100,""0"") &"&" I100, IF(AND(D100=""Roof Sheet"", REGEXMATCH(C100,""(?i)KS\d{4}[A-Z]{2}"")), REGEXEXTRACT(C100,""(?i)KS\d{4}[A-Z]{2}""), IF(AND(REGEXMATCH(D100,""(?i)-DP""), REGEXMATCH(C100,""(?i)Downpipe"")), ""dp"" & REGEXEXTRACT(C100,""("&"\d+)"") & ""mm"", IF(AND(REGEXMATCH(D100,""(?i)Bracket""), REGEXMATCH(C100,""(?i)Bracket"")), ""Brkt"" & REGEXEXTRACT(C100,""(\d+)"") & ""mm"", IF(AND(REGEXMATCH(D100,""(?i)-OP""), REGEXMATCH(C100,""(?i)pops"")), ""op"" & REGEXEXTRAC"&"T(C100,""(\d+)"") & ""mm"", IF(OR(D100=""R-FFTop"", D100=""R-FFBottom"", D100=""R-FFSide""), IF(REGEXMATCH(C100,""(?i)Profiled.*Top|Top.*Profiled""),""pfft"", IF(REGEXMATCH(C100,""(?i)Profiled.*Bottom|Bottom.*Profiled""),""pffb"", "&" IF(REGEXMATCH(C100,""(?i)Square""),""sff"",""""))), IF(REGEXMATCH(D100,""(?i)-Rivets""),""Rvt"", IF(REGEXMATCH(D100,""(?i)Silicone""),""300ml"", IF(REGEXMATCH(D100,""(?i)R-Butyl""),""300ml"", IF(REGEXMATCH(D100,""(?i)Fix""),""GenFix"","&" IF(AND(REGEXMATCH(C100,""(?i)Timber""), REGEXMATCH(D100,""(?i)Timber"")),""tp"", IF(AND(REGEXMATCH(C100,""(?i)Vent G1275""), REGEXMATCH(D100,""(?i)Comb FIller"")),""CFV1275"", IF(REGEXMATCH(C100,""(?i)DPC""),""dpc"", IF(REGEXMATCH(C100,"""&"(?i)Concealed Clips""),""ConClips"", IF(REGEXMATCH(D100,""(?i)-Takeoff ea""),""Takeoff ea"", IF(REGEXMATCH(D100,""(?i)-Takeoff LM""),""Takeoff LM"", IF(REGEXMATCH(D100,""(?i)-Takeoff m2""),""Takeoff m2"", IF(D100=""R-TU/TD"",""TU/TD"","""""&"))))))))))))))))) )))"),"Rvt") -> Rvt | C100: Rivets | D100: R-Rivets | E100: =E98 -> 0.32 | F100: =F99 | J100: No Specs | K100: ea | L100: =M98 -> 112.78 | M100: =ROUNDUP(((M98/5.7)+1)*(E100/0.05),0) -> 134 | N100: =IFERROR(__xludf.DUMMYFUNCTION("""COMPUTED_VALUE"""),1.0) -> 1 | O100: 1 | P100: 1 | Q100: =M100*N100*O100*P100 -> 134 | S100: =R100*Q100 -> 0 | W100: =U100*Q100 -> 0 | AB100: =W100+S100 -> 0 | AM100: 134 | AN100: Matched | AO100: 0
B101: =IFERROR(__xludf.DUMMYFUNCTION("IFERROR( IF(C101="""","""", IF(OR(REGEXMATCH(D101,""(?i)-Flashing""), REGEXMATCH(D101,""(?i)-EavesGut""), REGEXMATCH(D101,""(?i)Valley"")), ""DR"" & TEXT( ROUNDUP( MIN( VALUE(MID(C101, "&"FIND(""("",C101)+1, FIND(""/"",C101)-FIND(""("",C101)-1)), 1200 ) / 50, 0 ) * 50, ""0"" ) & MID(C101, FIND(""/"",C101)+1, FIND("")"",C101)-FIND(""/"",C101)-1) & TEXT(H101*100,""0"") &"&" I101, IF(AND(D101=""Roof Sheet"", REGEXMATCH(C101,""(?i)KS\d{4}[A-Z]{2}"")), REGEXEXTRACT(C101,""(?i)KS\d{4}[A-Z]{2}""), IF(AND(REGEXMATCH(D101,""(?i)-DP""), REGEXMATCH(C101,""(?i)Downpipe"")), ""dp"" & REGEXEXTRACT(C101,""("&"\d+)"") & ""mm"", IF(AND(REGEXMATCH(D101,""(?i)Bracket""), REGEXMATCH(C101,""(?i)Bracket"")), ""Brkt"" & REGEXEXTRACT(C101,""(\d+)"") & ""mm"", IF(AND(REGEXMATCH(D101,""(?i)-OP""), REGEXMATCH(C101,""(?i)pops"")), ""op"" & REGEXEXTRAC"&"T(C101,""(\d+)"") & ""mm"", IF(OR(D101=""R-FFTop"", D101=""R-FFBottom"", D101=""R-FFSide""), IF(REGEXMATCH(C101,""(?i)Profiled.*Top|Top.*Profiled""),""pfft"", IF(REGEXMATCH(C101,""(?i)Profiled.*Bottom|Bottom.*Profiled""),""pffb"", "&" IF(REGEXMATCH(C101,""(?i)Square""),""sff"",""""))), IF(REGEXMATCH(D101,""(?i)-Rivets""),""Rvt"", IF(REGEXMATCH(D101,""(?i)Silicone""),""300ml"", IF(REGEXMATCH(D101,""(?i)R-Butyl""),""300ml"", IF(REGEXMATCH(D101,""(?i)Fix""),""GenFix"","&" IF(AND(REGEXMATCH(C101,""(?i)Timber""), REGEXMATCH(D101,""(?i)Timber"")),""tp"", IF(AND(REGEXMATCH(C101,""(?i)Vent G1275""), REGEXMATCH(D101,""(?i)Comb FIller"")),""CFV1275"", IF(REGEXMATCH(C101,""(?i)DPC""),""dpc"", IF(REGEXMATCH(C101,"""&"(?i)Concealed Clips""),""ConClips"", IF(REGEXMATCH(D101,""(?i)-Takeoff ea""),""Takeoff ea"", IF(REGEXMATCH(D101,""(?i)-Takeoff LM""),""Takeoff LM"", IF(REGEXMATCH(D101,""(?i)-Takeoff m2""),""Takeoff m2"", IF(D101=""R-TU/TD"",""TU/TD"","""""&"))))))))))))))))) )))"),"GenFix") -> GenFix | C101: Fixings | D101: R-GenFix | F101: =F100 | J101: No Specs | K101: ea | L101: =M98 -> 112.78 | M101: =ROUNDUP(M98/0.6,0)+1 -> 189 | N101: =IFERROR(__xludf.DUMMYFUNCTION("""COMPUTED_VALUE"""),1.0) -> 1 | O101: 1 | P101: 1 | Q101: =M101*N101*O101*P101 -> 189 | S101: =R101*Q101 -> 0 | W101: =U101*Q101 -> 0 | AB101: =W101+S101 -> 0 | AM101: 189 | AN101: Matched | AO101: 0
...

Sheet New Spotswood College
A2: 1
A3: 1
A4: 1
A5: 1
A6: 1
A7: 1
A8: 1 | B8: Project: | C8: Spotswood College | K8: DK Roofing BOQ
A9: 1 | B9: Location:
C10: Building | D10: Timber | I10: 1
A11: 1 | B11: SN | C11: Description | D11: Type | E11: Girth | F11: Degree | G11: Location | H11: BMT | I11: Coating | J11: Specs | K11: Unit | L11: BOQ | M11: TAKEOFF | Q11: Qty | R11: MATERIAL | V11: LABOUR | AD11: TOTAL COST | AE11: For Markup | AF11: factor | AG11: Prelims | AH11: Margin | AJ11: Rate | AK11: Amount | AM11: Qty | AN11: Quantity Formula | AO11: Discrepancy | AP11: Remarks
A12: 1 | L12: QTY | M12: Qty | N12: Pitch F | O12: 0 | P12: Unit | R12: Rate | S12: Amount | T12: Total Material Cost | U12: Rate | V12: Amount | W12: Total Labour | AF12: =SUM(AF13) -> 0
A13: 1
A14: 1 | C14: ROOFING WORKS
A15: 1 | C15: Roof Sheeting
A16: 1 | C16: Supply and install 4311: DW Dimond advanced roofing system - 0.55mm BMT AM150 Zincalume Dimond BB900 TBC with Thermakraft 407 Covertek Roof Underlay, Dimond Ashgrid AG40 rail and AB40 post located above all purlins complete with EPDM thermal breaks., Dimond R1.8 75mm thermal BIB insulation over R2.4 95mm BIB insulation, Lap seal tape, and 0.55mm BMT Dimond BB900 TBC Zincalume Base Sheet, as per general notes (A002) | L16: =Q16 -> #REF! | Q16: =Q17 -> #REF! | S16: =T16/Q16 -> #REF! | T16: =SUM(S17:S35) -> #REF! | U16: =iferror(if(B16="",,VLOOKUP(B16,Data!$B$2:$F905,5,0)),"") | V16: =W16/Q16 -> #REF! | W16: =SUM(W17:W35) -> #REF! | X16: =W16/$AC$176/$W$183/$X$173 -> #REF! | Y16: =(T16+W16)=(SUM(AB17:AB34)) -> #REF! | Z16: =(T16+W16)-(SUM(AB17:AB34)) -> #REF! | AD16: =W16+T16 -> #REF! | AE16: =AD16 -> #REF! | AF16: =AE16/$AE$151 -> #REF! | AG16: =AF16*$AG$158 -> #REF! | AH16: =AF16*$AG$161 -> #REF! | AJ16: =ROUND(AK16/L16,2) -> #REF! | AK16: =ROUND(AH16+AG16+AD16,2) -> #REF!
B17: DRBB900Zinc055 | C17: 4311:01 - 0.55mm BMT AM150 Zincalume Dimond BB900 TBC @ 9 deg | D17: R-Sheeting | E17: =IFERROR(__xludf.DUMMYFUNCTION("IF($B$17:$B386="""","""", VLOOKUP( $B$17:$B386, QUERY( IMPORTRANGE(""1Ag27m9YF5mMfJh2E6NipJDFvPLlDI1p-s_1XEnzMHcc"",""Merge!F2:R""), ""select Col1, Col11"", 0 ), 2, FALSE ) ) "),"#REF!") -> #REF! | F17: =IFERROR(__xludf.DUMMYFUNCTION("IFERROR(REGEXEXTRACT(C17,""@\s*(\d+)\s*deg"")&""°"","""") "),"9°") -> 9° | H17: =IFERROR(__xludf.DUMMYFUNCTION("IFERROR(REGEXEXTRACT(C17, ""(\d*\.\d+)mm""), """")"),"0.55") -> 0.55 | J17: Specs | K17: m2 | L17: 602.91 | M17: =L17*E17 -> #REF! | N17: =IFERROR(__xludf.DUMMYFUNCTION("ARRAYFORMULA(IF( (B17:B148<>"""") * (F17:F148=""""), 1, IF( F17:F148="""", """", IFERROR(1/COS(RADIANS(REGEXEXTRACT(F17:F148,""(\d+)"")))) ) ))"),1.0124651257880029) -> 1.0124651 | O17: 1 | P17: 1 | Q17: =M17*N17*O17*P17 -> #REF! | R17: {=iferror(if(B17:B148="",,VLOOKUP(B17:B148,Data!$B$2:$K905,9,0)),"")} | S17: =R17*Q17 -> #REF! | U17: {=iferror(if(B17:B148="",,VLOOKUP(B17:B148,Data!$B$2:$K905,10,0)),"")} | W17: =U17*Q17 -> #REF! | X17: =W17/$AC$176/$W$183/Y17 -> #REF! | Y17: 10 | Z17: =Q17/X17 -> #REF! | AA17: =27*15/60/8 -> 0.84375 | AB17: =W17+S17 -> #REF! | AM17: {=IFERROR( IF(B17:B148="","", IF(D17:D148="Rain Head",L17:L148, IF(D17:D148="R-Accessories",L17:L148, IF(D17:D148="R-AdvFixing",L17:L148, IF(D17:D148="R-Angle Bar",L17:L148, IF(D17:D148="R-Butyl",L17:L148/12, IF(D17:D148="R-Comb Filler",L17:L148, IF(D17:D148="R-Dektite",L17:L148, IF(D17:D148="R-Dektite Fix",L17:L148*(ROUNDUP(E17:E148/0.05,0)+1), IF(D17:D148="R-Dektite Seal",L17:L148*(E17:E148/8), IF(D17:D148="R-DP",L17:L148, IF(D17:D148="R-DPC",L17:L148, IF(D17:D148="R-DPBracket",L17:L148, IF(D17:D148="R-EavesGut",L17:L148, IF(D17:D148="R-EGBracket",ROUNDUP(L17:L148/E17:E148,0)+1, IF(D17:D148="R-EGBracketFixing",ROUNDUP(L17:L148*E17:E148,0)+1, IF(D17:D148="R-ExpFoam",L17:L148, IF(D17:D148="R-Fascia",L17:L148, IF(D17:D148="R-FasciaBracket",ROUNDUP(L17:L148/E17:E148,0)+1, IF(D17:D148="R-FasciaBracketFixing",ROUNDUP(L17:L148/0.6,0)+1, IF(D17:D148="R-FFBottom",L17:L148, IF(D17:D148="R-FFSide",L17:L148, IF(D17:D148="R-FFTop",L17:L148, IF(D17:D148="R-Fixings",ROUNDUP(L17:L148*6,0)+1, IF(D17:D148="R-Flashing",L17:L148, IF(D17:D148="R-GenFix",ROUNDUP(L17:L148/0.6,0)+1, IF(D17:D148="R-Insulation",L17:L148, IF(D17:D148="R-KS",VLOOKUP(B17:B148,Data!B2:H905,6,0)*L17:L148, IF(D17:D148="R-KSFixing",ROUNDUP(L17:L148*6,0)+1, IF(D17:D148="R-LM",L17:L148, IF(D17:D148="R-m2",L17:L148*E17:E148, IF(D17:D148="R-OF",L17:L148, IF(D17:D148="R-OP",L17:L148, IF(D17:D148="R-OPFixing",L17:L148*10, IF(D17:D148="R-OPSeal",(L17:L148*3.14*E17:E148)/8, IF(D17:D148="R-PanFlashing",L17:L148, IF(D17:D148="R-PanFlash Fix",ROUNDUP((L17:L148*E17:E148)*8,0)+1, IF(D17:D148="R-Post",L17:L148/E17:E148, IF(D17:D148="R-PostFix",L17:L148, IF(D17:D148="R-Perforated ",ROUNDUP(L17:L148/E17:E148,0), IF(D17:D148="R-PerforatedFix",ROUNDUP(L17:L148*8,0)+1, IF(D17:D148="R-Rail",L17:L148, IF(D17:D148="R-Rainhead",L17:L148, IF(D17:D148="R-Ridge Vent",(L17:L148/(VLOOKUP(B17:B148,Data!B2:H905,6,0))), IF(D17:D148="R-Rivets",ROUNDUP(((L17:L148/5.7)+1)*(E17:E148/0.05),0), IF(D17:D148="R-RivetsEa",L17:L148, IF(D17:D148="R-RoofClips",ROUNDUP(L17:L148/E17:E148,0)+1, IF(D17:D148="R-Safety Mesh",L17:L148, IF(D17:D148="R-Scupper",L17:L148, IF(D17:D148="R-Sheeting",VLOOKUP(B17:B148,Data!B2:H905,6,0)*L17:L148, IF(D17:D148="R-Silicone",(ROUNDDOWN((L17:L148/5.7)+2,0)*E17:E148)/8, IF(D17:D148="R-Silicone LM",L17:L148/8, IF(D17:D148="R-SumpFixing",ROUNDUP((L17:L148*E17:E148)/0.05,0)+1, IF(D17:D148="R-SumpSeal",(L17:L148*E17:E148)/8, IF(D17:D148="R-Sump",L17:L148, IF(D17:D148="R-Takeoff ea",L17:L148, IF(D17:D148="R-Takeoff LM",L17:L148, IF(D17:D148="R-Takeoff m2",L17:L148*E17:E148, IF(D17:D148="R-Takeoff m3",L17:L148*E17:E148*H17:H148, IF(D17:D148="R-Timber ea",ROUNDUP(L17:L148/E17:E148,0)+1, IF(D17:D148="R-Timber LM",L17:L148, IF(D17:D148="R-Timber m2",L17:L148*E17:E148, IF(D17:D148="R-Timber eaFix",L17:L148*E17:E148, IF(D17:D148="R-TimberLMFix",ROUNDUP(L17:L148/1,0)+1, IF(D17:D148="R-Timberm2Fix",ROUNDUP(L17:L148*5,0)+1, IF(D17:D148="R-TopHatFixings",ROUNDUP(L17:L148/0.6,0)*2, IF(D17:D148="R-Trimmer/Packer",L17:L148, IF(D17:D148="R-TS",VLOOKUP(B17:B148,Data!B2:H905,6,0)*L17:L148, IF(D17:D148="R-TSFixing",(ROUNDUP(L17:L148/0.6,0)+1)*2, IF(D17:D148="R-TSLapSeal",L17:L148, IF(D17:D148="R-TSPurlinStrip",L17:L148/E17:E148, IF(D17:D148="R-TSStitching",L17:L148*2, IF(D17:D148="R-TPO",L17:L148, IF(D17:D148="R-TPO Gutter",L17:L148, IF(D17:D148="R-TU/TD",L17:L148, IF(D17:D148="R-UBracket",ROUNDUP(L17:L148/E17:E148,0)+1, IF(D17:D148="R-UBracketFix",ROUNDUP(L17:L148*E17:E148,0)+1, IF(D17:D148="R-Underlay",(L17:L148/(VLOOKUP(B17:B148,Data!B2:H905,6,0)-0.15))*0.15+L17:L148, IF(D17:D148="R-UTape",L17:L148/E17:E148/H17:H148, IF(D17:D148="R-Vent",(L17:L148/(VLOOKUP(B17:B148,Data!B2:H905,6,0))), IF(D17:D148="R-Valley Gutter",L17:L148, IF(D17:D148="R-VapBarrier",(L17:L148/(E17:E148-0.15))*0.15+L17:L148, IF(D17:D148="R-Washer",L17:L148, IF(D17:D148="R-ZFlashingFix",(L17:L148/E17:E148)*2, IF(D17:D148="W-Comb Filler",L17:L148, IF(D17:D148="W-DPC",L17:L148, IF(D17:D148="W-Fixings",ROUNDUP(L17:L148*6,0)+1, IF(D17:D148="W-Flashing",L17:L148, IF(D17:D148="W-GenFix",ROUNDUP(L17:L148/0.6,0)+1, IF(D17:D148="W-KS",VLOOKUP(B17:B148,Data!B2:H905,6,0)*L17:L148, IF(D17:D148="W-KSFixing",ROUNDUP(L17:L148*6,0)+1, IF(D17:D148="W-RAB",L17:L148, IF(D17:D148="W-RABFix",ROUNDUP(L17:L148*E17:E148,0)+1, IF(D17:D148="W-Rivets",ROUNDUP(((L17:L148/5.7)+1)*(E17:E148/0.05),0), IF(D17:D148="W-Silicone",(ROUNDDOWN((L17:L148/5.7)+2,0)*E17:E148)/8, IF(D17:D148="W-Silicone LM",L17:L148/8, IF(D17:D148="W-Sheeting",VLOOKUP(B17:B148,Data!B2:H905,6,0)*L17:L148, IF(D17:D148="W-Silicone",(ROUNDDOWN((L17:L148/5.7)+2,0)*E17:E148)/8, IF(D17:D148="W-Silicone LM",L17:L148/8, IF(D17:D148="W-Takeoff ea",L17:L148, IF(D17:D148="W-Takeoff LM",L17:L148, IF(D17:D148="W-Takeoff m2",L17:L148*E17:E148, IF(D17:D148="W-Timber LM",L17:L148, IF(D17:D148="W-Timber m2",L17:L148*E17:E148, IF(D17:D148="W-TimberLMFix",ROUNDUP(L17:L148/1,0)+1, IF(D17:D148="W-Timberm2Fix",ROUNDUP(L17:L148*5,0)+1, IF(D17:D148="W-TopHatFixings",ROUNDUP(L17:L148/0.6,0)*2, IF(D17:D148="W-Trimmer/Packer",L17:L148, IF(D17:D148="W-TimberLMFix",ROUNDUP(L17:L148/0.6,0)+1, IF(D17:D148="W-Timberm2Fix",ROUNDUP(L17:L148*8,0)+1, IF(D17:D148="W-Underlay",(L17:L148/(VLOOKUP(B17:B148,Data!B2:H905,6,0)-0.15))*0.15+L17:L148, IF(D17:D148="W-UTape",L17:L148/E17:E148/H17:H148, IF(D17:D148="W-Vent",(L17:L148/(VLOOKUP(B17:B148,Data!B2:H905,6,0))), 0 ))))))))))))))))))))))))))))))))))))))))))))))))))))))))))))))))))))))))))))))))))))))))))))))))))))))))))))))))), "" )} | AN17: {=if(B17:B148="",,if(M17:M148=AM17:AM148,"Matched","Mismatched"))} -> #REF! | AO17: {=if(AM17:AM148="","",AM17:AM148-M17:M148)}
N18: =IFERROR(__xludf.DUMMYFUNCTION("""COMPUTED_VALUE"""),"") | AB18: =W18+S18 -> 0
B19: DR75mmInsul | C19: Dimond R1.8 75mm thermal BIB insulation | D19: R-Insulation | F19: =F59 -> 9° | I19: =Q19+Q39 -> 1471.4055 | J19: Specs | K19: m2 | L19: 539.5 | M19: =L19 -> 539.5 | N19: =IFERROR(__xludf.DUMMYFUNCTION("""COMPUTED_VALUE"""),1.0124651257880029) -> 1.0124651 | O19: 1 | P19: 1 | Q19: =M19*N19*O19*P19 -> 546.22494 | S19: =R19*Q19 -> 0 | W19: =U19*Q19 -> 0 | AB19: =W19+S19 -> 0 | AM19: 539.5 | AN19: Matched | AO19: 0
B20: DR95mmInsul | C20: Dimond R2.4 95mm BIB insulation | D20: R-Insulation | F20: =F19 -> 9° | I20: =Q20+Q40 -> 1471.4055 | J20: Specs | K20: m2 | L20: =M19 -> 539.5 | M20: =L20 -> 539.5 | N20: =IFERROR(__xludf.DUMMYFUNCTION("""COMPUTED_VALUE"""),1.0124651257880029) -> 1.0124651 | O20: 1 | P20: 1 | Q20: =M20*N20*O20*P20 -> 546.22494 | S20: =R20*Q20 -> 0 | W20: =U20*Q20 -> 0 | AB20: =W20+S20 -> 0 | AM20: 539.5 | AN20: Matched | AO20: 0
N21: =IFERROR(__xludf.DUMMYFUNCTION("""COMPUTED_VALUE"""),"") | AB21: =W21+S21 -> 0
B22: DARSFixSt12x75 | C22: Top Sheet Fixing - STEEL 12X75 COLOUR X100 | D22: R-AdvFixing | F22: =F17 -> 9° | H22: =IFERROR(__xludf.DUMMYFUNCTION("IFERROR(REGEXEXTRACT(C22, ""(\d*\.\d+)mm""), """")"),"") | J22: Specs | K22: ea | L22: =M28 -> 676.68 | M22: 676.68 | N22: =IFERROR(__xludf.DUMMYFUNCTION("""COMPUTED_VALUE"""),1.0124651257880029) -> 1.0124651 | O22: 1 | P22: 1 | Q22: =M22*N22*O22*P22 -> 685.1149 | S22: =R22*Q22 -> 0 | W22: =U22*Q22 -> 0 | AB22: =W22+S22 -> 0 | AM22: 676.68 | AN22: Matched | AO22: 0
B23: DARSepdmWsh | C23: Top Sheet EPDM - EPDM SEALING WASH X100 | D23: R-AdvFixing | F23: =F22 -> 9° | J23: Specs | K23: LM | L23: =M28 -> 676.68 | M23: 676.68 | N23: =IFERROR(__xludf.DUMMYFUNCTION("""COMPUTED_VALUE"""),1.0124651257880029) -> 1.0124651 | AB23: =W23+S23 -> 0 | AM23: 676.68 | AN23: Matched | AO23: 0
B24: DARSPrWshrBB900 | C24: Top Sheet Profile Washer - ROOF WASHER BB900 x100 | D24: R-AdvFixing | F24: =F23 -> 9° | J24: Specs | K24: ea | L24: =M28 -> 676.68 | M24: 676.68 | N24: =IFERROR(__xludf.DUMMYFUNCTION("""COMPUTED_VALUE"""),1.0124651257880029) -> 1.0124651 | AB24: =W24+S24 -> 0 | AM24: 676.68 | AN24: Matched | AO24: 0
N25: =IFERROR(__xludf.DUMMYFUNCTION("""COMPUTED_VALUE"""),"") | AB25: =W25+S25 -> 0
B26: AG40rail | C26: 4311:03 - Ashgrid AG40 rail | D26: R-Rail | J26: Specs | K26: LM | L26: 676.68 | M26: 676.68 | N26: =IFERROR(__xludf.DUMMYFUNCTION("""COMPUTED_VALUE"""),1.0) -> 1 | O26: 1 | P26: 1 | Q26: =M26*N26*O26*P26 -> 676.68 | S26: =R26*Q26 -> 0 | W26: =U26*Q26 -> 0 | AB26: =W26+S26 -> 0 | AM26: 676.68 | AN26: Matched | AO26: 0
N27: =IFERROR(__xludf.DUMMYFUNCTION("""COMPUTED_VALUE"""),"") | AB27: =W27+S27 -> 0
B28: AB40post | C28: 4311:03 - AB40 post | D28: R-Post | E28: 1 | I28: =L28+L48 -> 1748.09 | J28: Specs | K28: ea | L28: =M26 -> 676.68 | M28: =L28/E28 -> 676.68 | N28: =IFERROR(__xludf.DUMMYFUNCTION("""COMPUTED_VALUE"""),1.0) -> 1 | O28: 1 | P28: 1 | Q28: =M28*N28*O28*P28 -> 676.68 | S28: =R28*Q28 -> 0 | W28: =U28*Q28 -> 0 | AB28: =W28+S28 -> 0 | AM28: 676.68 | AN28: Matched | AO28: 0
B29: PostFixSt12x30 | C29: 4311:11 - Fixings 12g x 20mm tek (for steel purlins) to secure the post to purlins. STEEL 12X30 NO NEO X100 | D29: R-PostFix | J29: Specs | K29: ea | L29: =M28 -> 676.68 | M29: 676.68 | N29: =IFERROR(__xludf.DUMMYFUNCTION("""COMPUTED_VALUE"""),1.0) -> 1 | O29: 1 | P29: 2 | Q29: =M29*N29*O29*P29 -> 1353.36 | S29: =R29*Q29 -> 0 | W29: =U29*Q29 -> 0 | AB29: =W29+S29 -> 0 | AM29: 676.68 | AN29: Matched | AO29: 0
N30: =IFERROR(__xludf.DUMMYFUNCTION("""COMPUTED_VALUE"""),"") | AB30: =W30+S30 -> 0
B31: EPDMThrmBrks | C31: 4311:03 - EPDM thermal breaks | D31: R-Takeoff LM | J31: Specs | K31: LM | L31: =M26 -> 676.68 | M31: =L31 -> 676.68 | N31: =IFERROR(__xludf.DUMMYFUNCTION("""COMPUTED_VALUE"""),1.0) -> 1 | O31: 1 | P31: 1 | Q31: =M31*N31*O31*P31 -> 676.68 | S31: =R31*Q31 -> 0 | W31: =U31*Q31 -> 0 | AB31: =W31+S31 -> 0 | AM31: 676.68 | AN31: Matched | AO31: 0
N32: =IFERROR(__xludf.DUMMYFUNCTION("""COMPUTED_VALUE"""),"") | AB32: =W32+S32 -> 0
B33: DRBB900Maxam055 | C33: 4311:01 - 0.55bmt BB900 Maxam | D33: R-Sheeting | E33: =IFERROR(__xludf.DUMMYFUNCTION("IF($B$17:$B386="""","""", VLOOKUP( $B$17:$B386, QUERY( IMPORTRANGE(""1Ag27m9YF5mMfJh2E6NipJDFvPLlDI1p-s_1XEnzMHcc"",""Merge!F2:R""), ""select Col1, Col11"", 0 ), 2, FALSE ) ) "),"#REF!") -> #REF! | F33: 9° | H33: 0.55 | J33: Specs | K33: m2 | L33: =L17 -> 602.91 | M33: =L33*E33 -> #REF! | N33: =IFERROR(__xludf.DUMMYFUNCTION("""COMPUTED_VALUE"""),1.0124651257880029) -> 1.0124651 | O33: 1 | P33: 1 | Q33: =M33*N33*O33*P33 -> #REF! | S33: =R33*Q33 -> #REF! | W33: =U33*Q33 -> #REF! | AB33: =W33+S33 -> #REF! | AN33: #REF!
B34: LinerFixSt12x20 | C34: Liner Fixing - STEEL 12X20 PER X100 | D34: R-AdvFixing | J34: Specs | K34: ea | L34: 676.68 | M34: 676.68 | N34: =IFERROR(__xludf.DUMMYFUNCTION("""COMPUTED_VALUE"""),1.0) -> 1 | O34: 1 | P34: 1 | Q34: =M34*N34*O34*P34 -> 676.68 | S34: =R34*Q34 -> 0 | W34: =U34*Q34 -> 0 | AB34: =W34+S34 -> 0 | AM34: 676.68 | AN34: Matched | AO34: 0
N35: =IFERROR(__xludf.DUMMYFUNCTION("""COMPUTED_VALUE"""),"")
A36: 1 | C36: Supply and install 4311: DW Dimond advanced roofing system - 0.55mm BMT AM150 Zincalume Dimond BB900 TBC with Thermakraft 407 Covertek Roof Underlay, Dimond Ashgrid AG40 rail and AB40 post located above all purlins complete with EPDM thermal breaks., Dimond R1.8 75mm thermal BIB insulation over R2.4 95mm BIB insulation, Lap seal tape, and 0.55mm BMT Dimond BB900 TBC Zincalume Base Sheet, as per general notes (A002) | L36: =Q36 -> #REF! | N36: =IFERROR(__xludf.DUMMYFUNCTION("""COMPUTED_VALUE"""),"") | P36: =Q16+Q36 -> #REF! | Q36: =Q37 -> #REF! | S36: =T36/Q36 -> #REF! | T36: =SUM(S37:S55) -> #REF! | V36: =W36/Q36 -> #REF! | W36: =SUM(W37:W55) -> #REF! | X36: =W36/$AC$176/$W$183/$X$173 -> #REF! | Y36: =(T36+W36)=(SUM(AB37:AB55)) -> #REF! | Z36: =(T36+W36)-(SUM(AB37:AB55)) -> #REF! | AD36: =W36+T36 -> #REF! | AE36: =AD36 -> #REF! | AF36: =AE36/$AE$151 -> #REF! | AG36: =AF36*$AG$158 -> #REF! | AH36: =AF36*$AG$161 -> #REF! | AJ36: =ROUND(AK36/L36,2) -> #REF! | AK36: =ROUND(AH36+AG36+AD36,2) -> #REF!
B37: DRBB900Zinc055 | C37: 4311:01 - 0.55mm BMT AM150 Zincalume Dimond BB900 TBC @ 5 deg | D37: R-Sheeting | E37: =IFERROR(__xludf.DUMMYFUNCTION("IF($B$17:$B386="""","""", VLOOKUP( $B$17:$B386, QUERY( IMPORTRANGE(""1Ag27m9YF5mMfJh2E6NipJDFvPLlDI1p-s_1XEnzMHcc"",""Merge!F2:R""), ""select Col1, Col11"", 0 ), 2, FALSE ) ) "),"#REF!") -> #REF! | F37: =IFERROR(__xludf.DUMMYFUNCTION("IFERROR(REGEXEXTRACT(C37,""@\s*(\d+)\s*deg"")&""°"","""") "),"5°") -> 5° | H37: =IFERROR(__xludf.DUMMYFUNCTION("IFERROR(REGEXEXTRACT(C37, ""(\d*\.\d+)mm""), """")"),"0.55") -> 0.55 | J37: Specs | K37: m2 | L37: 1029.42 | M37: =L37*E37 -> #REF! | N37: =IFERROR(__xludf.DUMMYFUNCTION("""COMPUTED_VALUE"""),1.0038198375433474) -> 1.0038198 | O37: 1 | P37: 1 | Q37: =M37*N37*O37*P37 -> #REF! | S37: =R37*Q37 -> #REF! | W37: =U37*Q37 -> #REF! | X37: =W37/$AC$176/$W$183/Y37 -> #REF! | Y37: 10 | Z37: =Q37/X37 -> #REF! | AA37: =27*15/60/8 -> 0.84375 | AB37: =W37+S37 -> #REF! | AN37: #REF!
N38: =IFERROR(__xludf.DUMMYFUNCTION("""COMPUTED_VALUE"""),"") | AB38: =W38+S38 -> 0
B39: DR75mmInsul | C39: Dimond R1.8 75mm thermal BIB insulation | D39: R-Insulation | F39: =F61 -> 5° | J39: Specs | K39: m2 | L39: 921.66 | M39: 921.66 | N39: =IFERROR(__xludf.DUMMYFUNCTION("""COMPUTED_VALUE"""),1.0038198375433474) -> 1.0038198 | O39: 1 | P39: 1 | Q39: =M39*N39*O39*P39 -> 925.18059 | S39: =R39*Q39 -> 0 | W39: =U39*Q39 -> 0 | AB39: =W39+S39 -> 0 | AM39: 921.66 | AN39: Matched | AO39: 0
B40: DR95mmInsul | C40: Dimond R2.4 95mm BIB insulation | D40: R-Insulation | F40: =F39 -> 5° | J40: Specs | K40: m2 | L40: =M39 -> 921.66 | M40: 921.66 | N40: =IFERROR(__xludf.DUMMYFUNCTION("""COMPUTED_VALUE"""),1.0038198375433474) -> 1.0038198 | O40: 1 | P40: 1 | Q40: =M40*N40*O40*P40 -> 925.18059 | S40: =R40*Q40 -> 0 | W40: =U40*Q40 -> 0 | AB40: =W40+S40 -> 0 | AM40: 921.66 | AN40: Matched | AO40: 0
N41: =IFERROR(__xludf.DUMMYFUNCTION("""COMPUTED_VALUE"""),"") | AB41: =W41+S41 -> 0
B42: DARSFixSt12x75 | C42: Top Sheet Fixing - STEEL 12X75 COLOUR X100 | D42: R-AdvFixing | F42: =F40 -> 5° | J42: Specs | K42: ea | L42: 1071.41 | M42: 1071.41 | N42: =IFERROR(__xludf.DUMMYFUNCTION("""COMPUTED_VALUE"""),1.0038198375433474) -> 1.0038198 | AB42: =W42+S42 -> 0 | AM42: 1071.41 | AN42: Matched | AO42: 0
B43: DARSepdmWsh | C43: Top Sheet EPDM - EPDM SEALING WASH X100 | D43: R-AdvFixing | F43: =F42 -> 5° | H43: =IFERROR(__xludf.DUMMYFUNCTION("IFERROR(REGEXEXTRACT(C43, ""(\d*\.\d+)mm""), """")"),"") | J43: Specs | K43: LM | L43: =M48 -> 1071.41 | M43: =M48 -> 1071.41 | N43: =IFERROR(__xludf.DUMMYFUNCTION("""COMPUTED_VALUE"""),1.0038198375433474) -> 1.0038198 | O43: 1 | P43: 1 | Q43: =M43*N43*O43*P43 -> 1075.5026 | S43: =R43*Q43 -> 0 | W43: =U43*Q43 -> 0 | AB43: =W43+S43 -> 0 | AM43: 1071.41 | AN43: Matched | AO43: 0
B44: DARSPrWshrBB900 | C44: Top Sheet Profile Washer - ROOF WASHER BB900 x100 | D44: R-AdvFixing | F44: =F43 -> 5° | J44: Specs | K44: ea | L44: 1071.41 | M44: 1071.41 | N44: =IFERROR(__xludf.DUMMYFUNCTION("""COMPUTED_VALUE"""),1.0038198375433474) -> 1.0038198 | AB44: =W44+S44 -> 0 | AM44: 1071.41 | AN44: Matched | AO44: 0
N45: =IFERROR(__xludf.DUMMYFUNCTION("""COMPUTED_VALUE"""),"") | AB45: =W45+S45 -> 0
B46: AG40rail | C46: 4311:03 - Ashgrid AG40 rail | D46: R-Rail | J46: Specs | K46: LM | L46: 1071.41 | M46: 1071.41 | N46: =IFERROR(__xludf.DUMMYFUNCTION("""COMPUTED_VALUE"""),1.0) -> 1 | O46: 1 | P46: 1 | Q46: =M46*N46*O46*P46 -> 1071.41 | S46: =R46*Q46 -> 0 | W46: =U46*Q46 -> 0 | AB46: =W46+S46 -> 0 | AM46: 1071.41 | AN46: Matched | AO46: 0
N47: =IFERROR(__xludf.DUMMYFUNCTION("""COMPUTED_VALUE"""),"") | AB47: =W47+S47 -> 0
B48: AB40post | C48: 4311:03 - AB40 post | D48: R-Post | E48: 1 | J48: Specs | K48: ea | L48: =M46 -> 1071.41 | M48: =L48/E48 -> 1071.41 | N48: =IFERROR(__xludf.DUMMYFUNCTION("""COMPUTED_VALUE"""),1.0) -> 1 | O48: 1 | P48: 1 | Q48: =M48*N48*O48*P48 -> 1071.41 | S48: =R48*Q48 -> 0 | W48: =U48*Q48 -> 0 | AB48: =W48+S48 -> 0 | AM48: 1071.41 | AN48: Matched | AO48: 0
B49: =IFERROR(__xludf.DUMMYFUNCTION("IFERROR( IF(C49="""","""", IF(OR(REGEXMATCH(D49,""(?i)-Flashing""), REGEXMATCH(D49,""(?i)-EavesGut""), REGEXMATCH(D49,""(?i)Valley"")), ""DR"" & TEXT( ROUNDUP( MIN( VALUE(MID(C49, FIND("&"""("",C49)+1, FIND(""/"",C49)-FIND(""("",C49)-1)), 1200 ) / 50, 0 ) * 50, ""0"" ) & MID(C49, FIND(""/"",C49)+1, FIND("")"",C49)-FIND(""/"",C49)-1) & TEXT(H49*100,""0"") & I49,"&" IF(AND(D49=""Roof Sheet"", REGEXMATCH(C49,""(?i)KS\d{4}[A-Z]{2}"")), REGEXEXTRACT(C49,""(?i)KS\d{4}[A-Z]{2}""), IF(AND(REGEXMATCH(D49,""(?i)-DP""), REGEXMATCH(C49,""(?i)Downpipe"")), ""dp"" & REGEXEXTRACT(C49,""(\d+)"") & ""mm"", "&" IF(AND(REGEXMATCH(D49,""(?i)Bracket""), REGEXMATCH(C49,""(?i)Bracket"")), ""Brkt"" & REGEXEXTRACT(C49,""(\d+)"") & ""mm"", IF(AND(REGEXMATCH(D49,""(?i)-OP""), REGEXMATCH(C49,""(?i)pops"")), ""op"" & REGEXEXTRACT(C49,""(\d+)"") & ""mm"""&", IF(OR(D49=""R-FFTop"", D49=""R-FFBottom"", D49=""R-FFSide""), IF(REGEXMATCH(C49,""(?i)Profiled.*Top|Top.*Profiled""),""pfft"", IF(REGEXMATCH(C49,""(?i)Profiled.*Bottom|Bottom.*Profiled""),""pffb"", IF(REGEXMATCH(C49,""(?i)Squ"&"are""),""sff"",""""))), IF(REGEXMATCH(D49,""(?i)-Rivets""),""Rvt"", IF(REGEXMATCH(D49,""(?i)Silicone""),""300ml"", IF(REGEXMATCH(D49,""(?i)R-Butyl""),""300ml"", IF(REGEXMATCH(D49,""(?i)Fix""),""GenFix"", IF(AND(REGEXMATCH(C49,""(?i)Tim"&"ber""), REGEXMATCH(D49,""(?i)Timber"")),""tp"", IF(AND(REGEXMATCH(C49,""(?i)Vent G1275""), REGEXMATCH(D49,""(?i)Comb FIller"")),""CFV1275"", IF(REGEXMATCH(C49,""(?i)DPC""),""dpc"", IF(REGEXMATCH(C49,""(?i)Concealed Clips""),""ConClips"", I"&"F(REGEXMATCH(D49,""(?i)-Takeoff ea""),""Takeoff ea"", IF(REGEXMATCH(D49,""(?i)-Takeoff LM""),""Takeoff LM"", IF(REGEXMATCH(D49,""(?i)-Takeoff m2""),""Takeoff m2"", IF(D49=""R-TU/TD"",""TU/TD"",""""))))))))))))))))) )))"),"GenFix") -> GenFix | C49: 4311:11 - Fixings 12g x 20mm tek (for steel purlins) to secure the post to purlins | D49: R-PostFix | J49: Specs | K49: ea | L49: =M48 -> 1071.41 | M49: =M48 -> 1071.41 | N49: =IFERROR(__xludf.DUMMYFUNCTION("""COMPUTED_VALUE"""),1.0) -> 1 | O49: 1 | P49: 2 | Q49: =M49*N49*O49*P49 -> 2142.82 | S49: =R49*Q49 -> 0 | W49: =U49*Q49 -> 0 | AB49: =W49+S49 -> 0 | AM49: 1071.41 | AN49: Matched | AO49: 0
N50: =IFERROR(__xludf.DUMMYFUNCTION("""COMPUTED_VALUE"""),"") | AB50: =W50+S50 -> 0
B51: EPDMThrmBrks | C51: 4311:03 - EPDM thermal breaks | D51: R-Takeoff LM | J51: Specs | K51: LM | L51: =M46 -> 1071.41 | M51: =M46 -> 1071.41 | N51: =IFERROR(__xludf.DUMMYFUNCTION("""COMPUTED_VALUE"""),1.0) -> 1 | O51: 1 | P51: 1 | Q51: =M51*N51*O51*P51 -> 1071.41 | S51: =R51*Q51 -> 0 | W51: =U51*Q51 -> 0 | AB51: =W51+S51 -> 0 | AM51: 1071.41 | AN51: Matched | AO51: 0
N52: =IFERROR(__xludf.DUMMYFUNCTION("""COMPUTED_VALUE"""),"") | AB52: =W52+S52 -> 0
B53: DRBB900Maxam055 | C53: 4311:01 - 0.55bmt BB900 Maxam | D53: R-Sheeting | E53: =IFERROR(__xludf.DUMMYFUNCTION("IF($B$17:$B386="""","""", VLOOKUP( $B$17:$B386, QUERY( IMPORTRANGE(""1Ag27m9YF5mMfJh2E6NipJDFvPLlDI1p-s_1XEnzMHcc"",""Merge!F2:R""), ""select Col1, Col11"", 0 ), 2, FALSE ) ) "),"#REF!") -> #REF! | F53: =F37 -> 5° | H53: 0.55 | J53: Specs | K53: m2 | L53: =L37 -> 1029.42 | M53: =L53*E53 -> #REF! | N53: =IFERROR(__xludf.DUMMYFUNCTION("""COMPUTED_VALUE"""),1.0038198375433474) -> 1.0038198 | O53: 1 | P53: 1 | Q53: =M53*N53*O53*P53 -> #REF! | S53: =R53*Q53 -> #REF! | W53: =U53*Q53 -> #REF! | AB53: =W53+S53 -> #REF! | AN53: #REF!
B54: LinerFixSt12x20 | C54: Liner Fixing - STEEL 12X20 PER X100 | D54: R-AdvFixing | J54: Specs | K54: ea | L54: 1071.41 | M54: 1071.41 | N54: =IFERROR(__xludf.DUMMYFUNCTION("""COMPUTED_VALUE"""),1.0) -> 1 | O54: 1 | P54: 1 | Q54: =M54*N54*O54*P54 -> 1071.41 | S54: =R54*Q54 -> 0 | W54: =U54*Q54 -> 0 | AB54: =W54+S54 -> 0 | AM54: 1071.41 | AN54: Matched | AO54: 0
N55: =IFERROR(__xludf.DUMMYFUNCTION("""COMPUTED_VALUE"""),"")
A56: 1 | C56: Underlay | N56: =IFERROR(__xludf.DUMMYFUNCTION("""COMPUTED_VALUE"""),"")
A57: 1 | C57: Supply and install underlay | L57: =Q57 -> #REF! | N57: =IFERROR(__xludf.DUMMYFUNCTION("""COMPUTED_VALUE"""),"") | Q57: =Q58 -> #REF! | S57: =T57/Q57 -> #REF! | T57: =SUM(S58:S62) -> #REF! | V57: =W57/Q57 -> #REF! | W57: =SUM(W58:W62) -> #REF! | X57: =W57/$AC$176/$W$183/$X$173 -> #REF! | Y57: =(T57+W57)=(SUM(AB58:AB62)) -> #REF! | Z57: =(T57+W57)-(SUM(AB58:AB62)) -> #REF! | AD57: =W57+T57 -> #REF! | AE57: =AD57 -> #REF! | AF57: =AE57/$AE$151 -> #REF! | AG57: =AF57*$AG$158 -> #REF! | AH57: =AF57*$AG$161 -> #REF! | AJ57: =ROUND(AK57/L57,2) -> #REF! | AK57: =ROUND(AH57+AG57+AD57,2) -> #REF!
B58: TKUF407 | C58: 4311:02 - Thermakraft 407 Covertek Roof Underlay | D58: R-Underlay | E58: =IFERROR(__xludf.DUMMYFUNCTION("IF($B$17:$B386="""","""", VLOOKUP( $B$17:$B386, QUERY( IMPORTRANGE(""1Ag27m9YF5mMfJh2E6NipJDFvPLlDI1p-s_1XEnzMHcc"",""Merge!F2:R""), ""select Col1, Col11"", 0 ), 2, FALSE ) ) "),"#REF!") -> #REF! | F58: =F17 -> 9° | H58: =IFERROR(__xludf.DUMMYFUNCTION("IFERROR(REGEXEXTRACT(C58, ""(\d*\.\d+)mm""), """")"),"") | J58: Specs | K58: m2 | L58: =M17 -> #REF! | M58: =(M17/(E58-0.15))*0.15+M17 -> #REF! | N58: =IFERROR(__xludf.DUMMYFUNCTION("""COMPUTED_VALUE"""),1.0124651257880029) -> 1.0124651 | O58: 1 | P58: 1 | Q58: =M58*N58*O58*P58 -> #REF! | S58: =R58*Q58 -> #REF! | W58: =U58*Q58 -> #REF! | AB58: =W58+S58 -> #REF! | AN58: #REF!
B59: TKGenTape | C59: Thermakraft White General Purpose Tape (60 mm × 66 m) | D59: R-UTape | E59: =E58 -> #REF! | F59: =F58 -> 9° | H59: =IFERROR(__xludf.DUMMYFUNCTION("IF($B$17:$B386="""","""", VLOOKUP( $B$17:$B386, QUERY( IMPORTRANGE(""1Ag27m9YF5mMfJh2E6NipJDFvPLlDI1p-s_1XEnzMHcc"",""Merge!F2:R""), ""select Col1, Col11"", 0 ), 2, FALSE ) ) "),"#REF!") -> #REF! | J59: No Specs | K59: ea | L59: =M58 -> #REF! | M59: =M58/E59/H59 -> #REF! | N59: =IFERROR(__xludf.DUMMYFUNCTION("""COMPUTED_VALUE"""),1.0124651257880029) -> 1.0124651 | O59: 1 | P59: 1 | Q59: =M59*N59*O59*P59 -> #REF! | S59: =R59*Q59 -> #REF! | W59: =U59*Q59 -> #REF! | AB59: =W59+S59 -> #REF! | AN59: #REF!
B60: TKUF407 | C60: 4311:02 - Thermakraft 407 Covertek Roof Underlay | D60: R-Underlay | E60: =IFERROR(__xludf.DUMMYFUNCTION("IF($B$17:$B386="""","""", VLOOKUP( $B$17:$B386, QUERY( IMPORTRANGE(""1Ag27m9YF5mMfJh2E6NipJDFvPLlDI1p-s_1XEnzMHcc"",""Merge!F2:R""), ""select Col1, Col11"", 0 ), 2, FALSE ) ) "),"#REF!") -> #REF! | F60: 5° | H60: =IFERROR(__xludf.DUMMYFUNCTION("IFERROR(REGEXEXTRACT(C60, ""(\d*\.\d+)mm""), """")"),"") | J60: Specs | K60: m2 | L60: =M43 -> 1071.41 | M60: 1352.7904 | N60: =IFERROR(__xludf.DUMMYFUNCTION("""COMPUTED_VALUE"""),1.0038198375433474) -> 1.0038198 | O60: 1 | P60: 1 | Q60: =M60*N60*O60*P60 -> 1357.9578 | S60: =R60*Q60 -> 0 | W60: =U60*Q60 -> 0 | AB60: =W60+S60 -> 0 | AN60: Mismatched
B61: TKGenTape | C61: Thermakraft White General Purpose Tape (60 mm × 66 m) | D61: R-UTape | E61: =E60 -> #REF! | F61: =F60 -> 5° | H61: =IFERROR(__xludf.DUMMYFUNCTION("IF($B$17:$B386="""","""", VLOOKUP( $B$17:$B386, QUERY( IMPORTRANGE(""1Ag27m9YF5mMfJh2E6NipJDFvPLlDI1p-s_1XEnzMHcc"",""Merge!F2:R""), ""select Col1, Col11"", 0 ), 2, FALSE ) ) "),"#REF!") -> #REF! | J61: No Specs | K61: ea | L61: =M60 -> 1352.7904 | M61: =M60/E61/H61 -> #REF! | N61: =IFERROR(__xludf.DUMMYFUNCTION("""COMPUTED_VALUE"""),1.0038198375433474) -> 1.0038198 | O61: 1 | P61: 1 | Q61: =M61*N61*O61*P61 -> #REF! | S61: =R61*Q61 -> #REF! | W61: =U61*Q61 -> #REF! | AB61: =W61+S61 -> #REF! | AN61: #REF!
N62: =IFERROR(__xludf.DUMMYFUNCTION("""COMPUTED_VALUE"""),"") | AB62: =W62+S62 -> 0
A63: 1 | C63: Safety mesh | N63: =IFERROR(__xludf.DUMMYFUNCTION("""COMPUTED_VALUE"""),"")
A64: 1 | C64: Supply and install safety mesh | L64: =Q64 -> #REF! | N64: =IFERROR(__xludf.DUMMYFUNCTION("""COMPUTED_VALUE"""),"") | Q64: =Q65 -> #REF! | S64: =T64/Q64 -> #REF! | T64: =SUM(S65:S67) -> #REF! | V64: =W64/Q64 -> #REF! | W64: =SUM(W65:W67) -> #REF! | X64: =W64/$AC$176/$W$183/$X$173 -> #REF! | Y64: =(T64+W64)=(SUM(AB65:AB67)) -> #REF! | Z64: =(T64+W64)-(SUM(AB65:AB67)) -> #REF! | AD64: =W64+T64 -> #REF! | AE64: =AD64 -> #REF! | AF64: =AE64/$AE$151 -> #REF! | AG64: =AF64*$AG$158 -> #REF! | AH64: =AF64*$AG$161 -> #REF! | AJ64: =ROUND(AK64/L64,2) -> #REF! | AK64: =ROUND(AH64+AG64+AD64,2) -> #REF!
B65: Safetymesh | C65: Safety mesh | D65: R-Safety Mesh | F65: =F59 -> 9° | H65: =IFERROR(__xludf.DUMMYFUNCTION("IFERROR(REGEXEXTRACT(C65, ""(\d*\.\d+)mm""), """")"),"") | J65: No Specs | K65: m2 | L65: =M58 -> #REF! | M65: =M58 -> #REF! | N65: =IFERROR(__xludf.DUMMYFUNCTION("""COMPUTED_VALUE"""),1.0124651257880029) -> 1.0124651 | O65: 1 | P65: 1 | Q65: =M65*N65*O65*P65 -> #REF! | S65: =R65*Q65 -> #REF! | W65: =U65*Q65 -> #REF! | X65: =W65/$AC$176/$W$183/Y65 -> #REF! | Y65: 4 | Z65: =Q65/X65 -> #REF! | AB65: =W65+S65 -> #REF! | AN65: #REF!
B66: Safetymesh | C66: Safety mesh | D66: R-Safety Mesh | F66: =F61 -> 5° | H66: =IFERROR(__xludf.DUMMYFUNCTION("IFERROR(REGEXEXTRACT(C66, ""(\d*\.\d+)mm""), """")"),"") | J66: No Specs | K66: m2 | L66: =M60 -> 1352.7904 | M66: 1352.7904 | N66: =IFERROR(__xludf.DUMMYFUNCTION("""COMPUTED_VALUE"""),1.0038198375433474) -> 1.0038198 | O66: 1 | P66: 1 | Q66: =M66*N66*O66*P66 -> 1357.9578 | S66: =R66*Q66 -> 0 | W66: =U66*Q66 -> 0 | X66: =W66/$AC$176/$W$183/Y66 -> #REF! | Y66: 4 | Z66: =Q66/X66 -> #REF! | AB66: =W66+S66 -> 0 | AM66: 1352.7904 | AN66: Matched | AO66: 0
N67: =IFERROR(__xludf.DUMMYFUNCTION("""COMPUTED_VALUE"""),"") | AB67: =W67+S67 -> 0
A68: 1 | C68: Flashing/Capping | N68: =IFERROR(__xludf.DUMMYFUNCTION("""COMPUTED_VALUE"""),"")
A69: 1 | C69: Supply and install 0.55mm BMT Coloursteel Maxam ridge cap flashing, as per detail 5 (A502) | L69: =Q69 -> 56.39 | N69: =IFERROR(__xludf.DUMMYFUNCTION("""COMPUTED_VALUE"""),"") | Q69: =Q70 -> 56.39 | S69: =T69/Q69 -> 0 | T69: =SUM(S70:S76) -> 0 | V69: =W69/Q69 -> 0 | W69: =SUM(W70:W76) -> 0 | X69: =W69/$AC$176/$W$183/$X$173 -> #REF! | Y69: =(T69+W69)=(SUM(AB70:AB76)) -> TRUE | Z69: =(T69+W69)-(SUM(AB70:AB76)) -> 0 | AD69: =W69+T69 -> 0 | AE69: =AD69 -> 0 | AF69: =AE69/$AE$151 -> #REF! | AG69: =AF69*$AG$158 -> #REF! | AH69: =AF69*$AG$161 -> #REF! | AJ69: =ROUND(AK69/L69,2) -> #REF! | AK69: =ROUND(AH69+AG69+AD69,2) -> #REF!
B70: =IFERROR(__xludf.DUMMYFUNCTION("IFERROR( IF(C70="""","""", IF(OR(REGEXMATCH(D70,""(?i)-Flashing""), REGEXMATCH(D70,""(?i)-EavesGut""), REGEXMATCH(D70,""(?i)Valley"")), ""DR"" & TEXT( ROUNDUP( MIN( VALUE(MID(C70, FIND("&"""("",C70)+1, FIND(""/"",C70)-FIND(""("",C70)-1)), 1200 ) / 50, 0 ) * 50, ""0"" ) & MID(C70, FIND(""/"",C70)+1, FIND("")"",C70)-FIND(""/"",C70)-1) & TEXT(H70*100,""0"") & I70,"&" IF(AND(D70=""Roof Sheet"", REGEXMATCH(C70,""(?i)KS\d{4}[A-Z]{2}"")), REGEXEXTRACT(C70,""(?i)KS\d{4}[A-Z]{2}""), IF(AND(REGEXMATCH(D70,""(?i)-DP""), REGEXMATCH(C70,""(?i)Downpipe"")), ""dp"" & REGEXEXTRACT(C70,""(\d+)"") & ""mm"", "&" IF(AND(REGEXMATCH(D70,""(?i)Bracket""), REGEXMATCH(C70,""(?i)Bracket"")), ""Brkt"" & REGEXEXTRACT(C70,""(\d+)"") & ""mm"", IF(AND(REGEXMATCH(D70,""(?i)-OP""), REGEXMATCH(C70,""(?i)pops"")), ""op"" & REGEXEXTRACT(C70,""(\d+)"") & ""mm"""&", IF(OR(D70=""R-FFTop"", D70=""R-FFBottom"", D70=""R-FFSide""), IF(REGEXMATCH(C70,""(?i)Profiled.*Top|Top.*Profiled""),""pfft"", IF(REGEXMATCH(C70,""(?i)Profiled.*Bottom|Bottom.*Profiled""),""pffb"", IF(REGEXMATCH(C70,""(?i)Squ"&"are""),""sff"",""""))), IF(REGEXMATCH(D70,""(?i)-Rivets""),""Rvt"", IF(REGEXMATCH(D70,""(?i)Silicone""),""300ml"", IF(REGEXMATCH(D70,""(?i)R-Butyl""),""300ml"", IF(REGEXMATCH(D70,""(?i)Fix""),""GenFix"", IF(AND(REGEXMATCH(C70,""(?i)Tim"&"ber""), REGEXMATCH(D70,""(?i)Timber"")),""tp"", IF(AND(REGEXMATCH(C70,""(?i)Vent G1275""), REGEXMATCH(D70,""(?i)Comb FIller"")),""CFV1275"", IF(REGEXMATCH(C70,""(?i)DPC""),""dpc"", IF(REGEXMATCH(C70,""(?i)Concealed Clips""),""ConClips"", I"&"F(REGEXMATCH(D70,""(?i)-Takeoff ea""),""Takeoff ea"", IF(REGEXMATCH(D70,""(?i)-Takeoff LM""),""Takeoff LM"", IF(REGEXMATCH(D70,""(?i)-Takeoff m2""),""Takeoff m2"", IF(D70=""R-TU/TD"",""TU/TD"",""""))))))))))))))))) )))"),"DR7006B55Mag") -> DR7006B55Mag | C70: 0.55mm BMT Coloursteel Maxam ridge cap flashing (690/6B) | D70: R-Flashing | E70: =VALUE(MID(C70, FIND("(", C70)+1, FIND("/", C70)-FIND("(", C70)-1)) / 1000 -> 0.69 | F70: =IFERROR(__xludf.DUMMYFUNCTION("IFERROR(REGEXEXTRACT(C70,""@\s*(\d+)\s*deg"")&""°"","""") "),"") | H70: =IFERROR(__xludf.DUMMYFUNCTION("IFERROR(REGEXEXTRACT(C70, ""(\d*\.\d+)mm""), """")"),"0.55") -> 0.55 | I70: Mag | J70: Specs | K70: LM | L70: 56.39 | M70: =L70 -> 56.39 | N70: =IFERROR(__xludf.DUMMYFUNCTION("""COMPUTED_VALUE"""),1.0) -> 1 | O70: 1 | P70: 1 | Q70: =M70*N70*O70*P70 -> 56.39 | S70: =R70*Q70 -> 0 | W70: =U70*Q70 -> 0 | X70: =W70/$AC$176/$W$183/Y70 -> #REF! | Y70: 2 | Z70: =Q70/X70 -> #REF! | AB70: =W70+S70 -> 0 | AM70: 56.39 | AN70: Matched | AO70: 0
B71: =IFERROR(__xludf.DUMMYFUNCTION("IFERROR( IF(C71="""","""", IF(OR(REGEXMATCH(D71,""(?i)-Flashing""), REGEXMATCH(D71,""(?i)-EavesGut""), REGEXMATCH(D71,""(?i)Valley"")), ""DR"" & TEXT( ROUNDUP( MIN( VALUE(MID(C71, FIND("&"""("",C71)+1, FIND(""/"",C71)-FIND(""("",C71)-1)), 1200 ) / 50, 0 ) * 50, ""0"" ) & MID(C71, FIND(""/"",C71)+1, FIND("")"",C71)-FIND(""/"",C71)-1) & TEXT(H71*100,""0"") & I71,"&" IF(AND(D71=""Roof Sheet"", REGEXMATCH(C71,""(?i)KS\d{4}[A-Z]{2}"")), REGEXEXTRACT(C71,""(?i)KS\d{4}[A-Z]{2}""), IF(AND(REGEXMATCH(D71,""(?i)-DP""), REGEXMATCH(C71,""(?i)Downpipe"")), ""dp"" & REGEXEXTRACT(C71,""(\d+)"") & ""mm"", "&" IF(AND(REGEXMATCH(D71,""(?i)Bracket""), REGEXMATCH(C71,""(?i)Bracket"")), ""Brkt"" & REGEXEXTRACT(C71,""(\d+)"") & ""mm"", IF(AND(REGEXMATCH(D71,""(?i)-OP""), REGEXMATCH(C71,""(?i)pops"")), ""op"" & REGEXEXTRACT(C71,""(\d+)"") & ""mm"""&", IF(OR(D71=""R-FFTop"", D71=""R-FFBottom"", D71=""R-FFSide""), IF(REGEXMATCH(C71,""(?i)Profiled.*Top|Top.*Profiled""),""pfft"", IF(REGEXMATCH(C71,""(?i)Profiled.*Bottom|Bottom.*Profiled""),""pffb"", IF(REGEXMATCH(C71,""(?i)Squ"&"are""),""sff"",""""))), IF(REGEXMATCH(D71,""(?i)-Rivets""),""Rvt"", IF(REGEXMATCH(D71,""(?i)Silicone""),""300ml"", IF(REGEXMATCH(D71,""(?i)R-Butyl""),""300ml"", IF(REGEXMATCH(D71,""(?i)Fix""),""GenFix"", IF(AND(REGEXMATCH(C71,""(?i)Tim"&"ber""), REGEXMATCH(D71,""(?i)Timber"")),""tp"", IF(AND(REGEXMATCH(C71,""(?i)Vent G1275""), REGEXMATCH(D71,""(?i)Comb FIller"")),""CFV1275"", IF(REGEXMATCH(C71,""(?i)DPC""),""dpc"", IF(REGEXMATCH(C71,""(?i)Concealed Clips""),""ConClips"", I"&"F(REGEXMATCH(D71,""(?i)-Takeoff ea""),""Takeoff ea"", IF(REGEXMATCH(D71,""(?i)-Takeoff LM""),""Takeoff LM"", IF(REGEXMATCH(D71,""(?i)-Takeoff m2""),""Takeoff m2"", IF(D71=""R-TU/TD"",""TU/TD"",""""))))))))))))))))) )))"),"300ml") -> 300ml | C71: Silicone 300ml | D71: R-Silicone | E71: =E70 -> 0.69 | H71: =IFERROR(__xludf.DUMMYFUNCTION("IFERROR(REGEXEXTRACT(C71, ""(\d*\.\d+)mm""), """")"),"") | J71: No Specs | K71: ea | L71: =M70 -> 56.39 | M71: =(ROUNDDOWN((M70/5.7)+2,0)*E71)/8 -> 0.94875 | N71: =IFERROR(__xludf.DUMMYFUNCTION("""COMPUTED_VALUE"""),1.0) -> 1 | O71: 1 | P71: 1 | Q71: =M71*N71*O71*P71 -> 0.94875 | S71: =R71*Q71 -> 0 | W71: =U71*Q71 -> 0 | AB71: =W71+S71 -> 0 | AM71: 0.94875 | AN71: Matched | AO71: 0
B72: =IFERROR(__xludf.DUMMYFUNCTION("IFERROR( IF(C72="""","""", IF(OR(REGEXMATCH(D72,""(?i)-Flashing""), REGEXMATCH(D72,""(?i)-EavesGut""), REGEXMATCH(D72,""(?i)Valley"")), ""DR"" & TEXT( ROUNDUP( MIN( VALUE(MID(C72, FIND("&"""("",C72)+1, FIND(""/"",C72)-FIND(""("",C72)-1)), 1200 ) / 50, 0 ) * 50, ""0"" ) & MID(C72, FIND(""/"",C72)+1, FIND("")"",C72)-FIND(""/"",C72)-1) & TEXT(H72*100,""0"") & I72,"&" IF(AND(D72=""Roof Sheet"", REGEXMATCH(C72,""(?i)KS\d{4}[A-Z]{2}"")), REGEXEXTRACT(C72,""(?i)KS\d{4}[A-Z]{2}""), IF(AND(REGEXMATCH(D72,""(?i)-DP""), REGEXMATCH(C72,""(?i)Downpipe"")), ""dp"" & REGEXEXTRACT(C72,""(\d+)"") & ""mm"", "&" IF(AND(REGEXMATCH(D72,""(?i)Bracket""), REGEXMATCH(C72,""(?i)Bracket"")), ""Brkt"" & REGEXEXTRACT(C72,""(\d+)"") & ""mm"", IF(AND(REGEXMATCH(D72,""(?i)-OP""), REGEXMATCH(C72,""(?i)pops"")), ""op"" & REGEXEXTRACT(C72,""(\d+)"") & ""mm"""&", IF(OR(D72=""R-FFTop"", D72=""R-FFBottom"", D72=""R-FFSide""), IF(REGEXMATCH(C72,""(?i)Profiled.*Top|Top.*Profiled""),""pfft"", IF(REGEXMATCH(C72,""(?i)Profiled.*Bottom|Bottom.*Profiled""),""pffb"", IF(REGEXMATCH(C72,""(?i)Squ"&"are""),""sff"",""""))), IF(REGEXMATCH(D72,""(?i)-Rivets""),""Rvt"", IF(REGEXMATCH(D72,""(?i)Silicone""),""300ml"", IF(REGEXMATCH(D72,""(?i)R-Butyl""),""300ml"", IF(REGEXMATCH(D72,""(?i)Fix""),""GenFix"", IF(AND(REGEXMATCH(C72,""(?i)Tim"&"ber""), REGEXMATCH(D72,""(?i)Timber"")),""tp"", IF(AND(REGEXMATCH(C72,""(?i)Vent G1275""), REGEXMATCH(D72,""(?i)Comb FIller"")),""CFV1275"", IF(REGEXMATCH(C72,""(?i)DPC""),""dpc"", IF(REGEXMATCH(C72,""(?i)Concealed Clips""),""ConClips"", I"&"F(REGEXMATCH(D72,""(?i)-Takeoff ea""),""Takeoff ea"", IF(REGEXMATCH(D72,""(?i)-Takeoff LM""),""Takeoff LM"", IF(REGEXMATCH(D72,""(?i)-Takeoff m2""),""Takeoff m2"", IF(D72=""R-TU/TD"",""TU/TD"",""""))))))))))))))))) )))"),"Rvt") -> Rvt | C72: Rivets | D72: R-Rivets | E72: =E70 -> 0.69 | H72: =IFERROR(__xludf.DUMMYFUNCTION("IFERROR(REGEXEXTRACT(C72, ""(\d*\.\d+)mm""), """")"),"") | J72: No Specs | K72: ea | L72: =M70 -> 56.39 | M72: =ROUNDUP(((M70/5.7)+1)*(E72/0.05),0) -> 151 | N72: =IFERROR(__xludf.DUMMYFUNCTION("""COMPUTED_VALUE"""),1.0) -> 1 | O72: 1 | P72: 1 | Q72: =M72*N72*O72*P72 -> 151 | S72: =R72*Q72 -> 0 | W72: =U72*Q72 -> 0 | AB72: =W72+S72 -> 0 | AM72: 151 | AN72: Matched | AO72: 0
B73: =IFERROR(__xludf.DUMMYFUNCTION("IFERROR( IF(C73="""","""", IF(OR(REGEXMATCH(D73,""(?i)-Flashing""), REGEXMATCH(D73,""(?i)-EavesGut""), REGEXMATCH(D73,""(?i)Valley"")), ""DR"" & TEXT( ROUNDUP( MIN( VALUE(MID(C73, FIND("&"""("",C73)+1, FIND(""/"",C73)-FIND(""("",C73)-1)), 1200 ) / 50, 0 ) * 50, ""0"" ) & MID(C73, FIND(""/"",C73)+1, FIND("")"",C73)-FIND(""/"",C73)-1) & TEXT(H73*100,""0"") & I73,"&" IF(AND(D73=""Roof Sheet"", REGEXMATCH(C73,""(?i)KS\d{4}[A-Z]{2}"")), REGEXEXTRACT(C73,""(?i)KS\d{4}[A-Z]{2}""), IF(AND(REGEXMATCH(D73,""(?i)-DP""), REGEXMATCH(C73,""(?i)Downpipe"")), ""dp"" & REGEXEXTRACT(C73,""(\d+)"") & ""mm"", "&" IF(AND(REGEXMATCH(D73,""(?i)Bracket""), REGEXMATCH(C73,""(?i)Bracket"")), ""Brkt"" & REGEXEXTRACT(C73,""(\d+)"") & ""mm"", IF(AND(REGEXMATCH(D73,""(?i)-OP""), REGEXMATCH(C73,""(?i)pops"")), ""op"" & REGEXEXTRACT(C73,""(\d+)"") & ""mm"""&", IF(OR(D73=""R-FFTop"", D73=""R-FFBottom"", D73=""R-FFSide""), IF(REGEXMATCH(C73,""(?i)Profiled.*Top|Top.*Profiled""),""pfft"", IF(REGEXMATCH(C73,""(?i)Profiled.*Bottom|Bottom.*Profiled""),""pffb"", IF(REGEXMATCH(C73,""(?i)Squ"&"are""),""sff"",""""))), IF(REGEXMATCH(D73,""(?i)-Rivets""),""Rvt"", IF(REGEXMATCH(D73,""(?i)Silicone""),""300ml"", IF(REGEXMATCH(D73,""(?i)R-Butyl""),""300ml"", IF(REGEXMATCH(D73,""(?i)Fix""),""GenFix"", IF(AND(REGEXMATCH(C73,""(?i)Tim"&"ber""), REGEXMATCH(D73,""(?i)Timber"")),""tp"", IF(AND(REGEXMATCH(C73,""(?i)Vent G1275""), REGEXMATCH(D73,""(?i)Comb FIller"")),""CFV1275"", IF(REGEXMATCH(C73,""(?i)DPC""),""dpc"", IF(REGEXMATCH(C73,""(?i)Concealed Clips""),""ConClips"", I"&"F(REGEXMATCH(D73,""(?i)-Takeoff ea""),""Takeoff ea"", IF(REGEXMATCH(D73,""(?i)-Takeoff LM""),""Takeoff LM"", IF(REGEXMATCH(D73,""(?i)-Takeoff m2""),""Takeoff m2"", IF(D73=""R-TU/TD"",""TU/TD"",""""))))))))))))))))) )))"),"GenFix") -> GenFix | C73: Fixings | D73: R-GenFix | F73: =F72 | J73: No Specs | K73: ea | L73: =M70 -> 56.39 | M73: =ROUNDUP(M70/0.6,0)+1 -> 95 | N73: =IFERROR(__xludf.DUMMYFUNCTION("""COMPUTED_VALUE"""),1.0) -> 1 | O73: 1 | P73: 1 | Q73: =M73*N73*O73*P73 -> 95 | S73: =R73*Q73 -> 0 | W73: =U73*Q73 -> 0 | AB73: =W73+S73 -> 0 | AM73: 95 | AN73: Matched | AO73: 0
B74: =IFERROR(__xludf.DUMMYFUNCTION("IFERROR( IF(C74="""","""", IF(OR(REGEXMATCH(D74,""(?i)-Flashing""), REGEXMATCH(D74,""(?i)-EavesGut""), REGEXMATCH(D74,""(?i)Valley"")), ""DR"" & TEXT( ROUNDUP( MIN( VALUE(MID(C74, FIND("&"""("",C74)+1, FIND(""/"",C74)-FIND(""("",C74)-1)), 1200 ) / 50, 0 ) * 50, ""0"" ) & MID(C74, FIND(""/"",C74)+1, FIND("")"",C74)-FIND(""/"",C74)-1) & TEXT(H74*100,""0"") & I74,"&" IF(AND(D74=""Roof Sheet"", REGEXMATCH(C74,""(?i)KS\d{4}[A-Z]{2}"")), REGEXEXTRACT(C74,""(?i)KS\d{4}[A-Z]{2}""), IF(AND(REGEXMATCH(D74,""(?i)-DP""), REGEXMATCH(C74,""(?i)Downpipe"")), ""dp"" & REGEXEXTRACT(C74,""(\d+)"") & ""mm"", "&" IF(AND(REGEXMATCH(D74,""(?i)Bracket""), REGEXMATCH(C74,""(?i)Bracket"")), ""Brkt"" & REGEXEXTRACT(C74,""(\d+)"") & ""mm"", IF(AND(REGEXMATCH(D74,""(?i)-OP""), REGEXMATCH(C74,""(?i)pops"")), ""op"" & REGEXEXTRACT(C74,""(\d+)"") & ""mm"""&", IF(OR(D74=""R-FFTop"", D74=""R-FFBottom"", D74=""R-FFSide""), IF(REGEXMATCH(C74,""(?i)Profiled.*Top|Top.*Profiled""),""pfft"", IF(REGEXMATCH(C74,""(?i)Profiled.*Bottom|Bottom.*Profiled""),""pffb"", IF(REGEXMATCH(C74,""(?i)Squ"&"are""),""sff"",""""))), IF(REGEXMATCH(D74,""(?i)-Rivets""),""Rvt"", IF(REGEXMATCH(D74,""(?i)Silicone""),""300ml"", IF(REGEXMATCH(D74,""(?i)R-Butyl""),""300ml"", IF(REGEXMATCH(D74,""(?i)Fix""),""GenFix"", IF(AND(REGEXMATCH(C74,""(?i)Tim"&"ber""), REGEXMATCH(D74,""(?i)Timber"")),""tp"", IF(AND(REGEXMATCH(C74,""(?i)Vent G1275""), REGEXMATCH(D74,""(?i)Comb FIller"")),""CFV1275"", IF(REGEXMATCH(C74,""(?i)DPC""),""dpc"", IF(REGEXMATCH(C74,""(?i)Concealed Clips""),""ConClips"", I"&"F(REGEXMATCH(D74,""(?i)-Takeoff ea""),""Takeoff ea"", IF(REGEXMATCH(D74,""(?i)-Takeoff LM""),""Takeoff LM"", IF(REGEXMATCH(D74,""(?i)-Takeoff m2""),""Takeoff m2"", IF(D74=""R-TU/TD"",""TU/TD"",""""))))))))))))))))) )))"),"pfft") -> pfft | C74: Profiled Foam Filler Top | D74: R-FFTop | J74: No Specs | K74: LM | L74: =M70 -> 56.39 | M74: =M70 -> 56.39 | N74: =IFERROR(__xludf.DUMMYFUNCTION("""COMPUTED_VALUE"""),1.0) -> 1 | O74: 1 | P74: 2 | Q74: =M74*N74*O74*P74 -> 112.78 | S74: =R74*Q74 -> 0 | W74: =U74*Q74 -> 0 | AB74: =W74+S74 -> 0 | AM74: 56.39 | AN74: Matched | AO74: 0
B75: =IFERROR(__xludf.DUMMYFUNCTION("IFERROR( IF(C75="""","""", IF(OR(REGEXMATCH(D75,""(?i)-Flashing""), REGEXMATCH(D75,""(?i)-EavesGut""), REGEXMATCH(D75,""(?i)Valley"")), ""DR"" & TEXT( ROUNDUP( MIN( VALUE(MID(C75, FIND("&"""("",C75)+1, FIND(""/"",C75)-FIND(""("",C75)-1)), 1200 ) / 50, 0 ) * 50, ""0"" ) & MID(C75, FIND(""/"",C75)+1, FIND("")"",C75)-FIND(""/"",C75)-1) & TEXT(H75*100,""0"") & I75,"&" IF(AND(D75=""Roof Sheet"", REGEXMATCH(C75,""(?i)KS\d{4}[A-Z]{2}"")), REGEXEXTRACT(C75,""(?i)KS\d{4}[A-Z]{2}""), IF(AND(REGEXMATCH(D75,""(?i)-DP""), REGEXMATCH(C75,""(?i)Downpipe"")), ""dp"" & REGEXEXTRACT(C75,""(\d+)"") & ""mm"", "&" IF(AND(REGEXMATCH(D75,""(?i)Bracket""), REGEXMATCH(C75,""(?i)Bracket"")), ""Brkt"" & REGEXEXTRACT(C75,""(\d+)"") & ""mm"", IF(AND(REGEXMATCH(D75,""(?i)-OP""), REGEXMATCH(C75,""(?i)pops"")), ""op"" & REGEXEXTRACT(C75,""(\d+)"") & ""mm"""&", IF(OR(D75=""R-FFTop"", D75=""R-FFBottom"", D75=""R-FFSide""), IF(REGEXMATCH(C75,""(?i)Profiled.*Top|Top.*Profiled""),""pfft"", IF(REGEXMATCH(C75,""(?i)Profiled.*Bottom|Bottom.*Profiled""),""pffb"", IF(REGEXMATCH(C75,""(?i)Squ"&"are""),""sff"",""""))), IF(REGEXMATCH(D75,""(?i)-Rivets""),""Rvt"", IF(REGEXMATCH(D75,""(?i)Silicone""),""300ml"", IF(REGEXMATCH(D75,""(?i)R-Butyl""),""300ml"", IF(REGEXMATCH(D75,""(?i)Fix""),""GenFix"", IF(AND(REGEXMATCH(C75,""(?i)Tim"&"ber""), REGEXMATCH(D75,""(?i)Timber"")),""tp"", IF(AND(REGEXMATCH(C75,""(?i)Vent G1275""), REGEXMATCH(D75,""(?i)Comb FIller"")),""CFV1275"", IF(REGEXMATCH(C75,""(?i)DPC""),""dpc"", IF(REGEXMATCH(C75,""(?i)Concealed Clips""),""ConClips"", I"&"F(REGEXMATCH(D75,""(?i)-Takeoff ea""),""Takeoff ea"", IF(REGEXMATCH(D75,""(?i)-Takeoff LM""),""Takeoff LM"", IF(REGEXMATCH(D75,""(?i)-Takeoff m2""),""Takeoff m2"", IF(D75=""R-TU/TD"",""TU/TD"",""""))))))))))))))))) )))"),"TU/TD") -> TU/TD | C75: Turn Up Roof End | D75: R-TU/TD | J75: No Specs | K75: LM | L75: =M70 -> 56.39 | M75: =M70 -> 56.39 | N75: =IFERROR(__xludf.DUMMYFUNCTION("""COMPUTED_VALUE"""),1.0) -> 1 | O75: 1 | P75: 2 | Q75: =M75*N75*O75*P75 -> 112.78 | S75: =R75*Q75 -> 0 | W75: =U75*Q75 -> 0 | AB75: =W75+S75 -> 0 | AM75: 56.39 | AN75: Matched | AO75: 0
N76: =IFERROR(__xludf.DUMMYFUNCTION("""COMPUTED_VALUE"""),"")
A77: 1 | C77: Supply and install 0.55mm BMT Coloursteel Maxam side barge flashing, as per detail 6 (A502) | L77: =Q77 -> 19.378583 | N77: =IFERROR(__xludf.DUMMYFUNCTION("""COMPUTED_VALUE"""),"") | Q77: =Q78 -> 19.378583 | S77: =T77/Q77 -> 0 | T77: =SUM(S78:S82) -> 0 | V77: =W77/Q77 -> 0 | W77: =SUM(W78:W82) -> 0 | X77: =W77/$AC$176/$W$183/$X$173 -> #REF! | Y77: =(T77+W77)=(SUM(AB78:AB82)) -> TRUE | Z77: =(T77+W77)-(SUM(AB78:AB82)) -> 0 | AD77: =W77+T77 -> 0 | AE77: =AD77 -> 0 | AF77: =AE77/$AE$151 -> #REF! | AG77: =AF77*$AG$158 -> #REF! | AH77: =AF77*$AG$161 -> #REF! | AJ77: =ROUND(AK77/L77,2) -> #REF! | AK77: =ROUND(AH77+AG77+AD77,2) -> #REF!
B78: =IFERROR(__xludf.DUMMYFUNCTION("IFERROR( IF(C78="""","""", IF(OR(REGEXMATCH(D78,""(?i)-Flashing""), REGEXMATCH(D78,""(?i)-EavesGut""), REGEXMATCH(D78,""(?i)Valley"")), ""DR"" & TEXT( ROUNDUP( MIN( VALUE(MID(C78, FIND("&"""("",C78)+1, FIND(""/"",C78)-FIND(""("",C78)-1)), 1200 ) / 50, 0 ) * 50, ""0"" ) & MID(C78, FIND(""/"",C78)+1, FIND("")"",C78)-FIND(""/"",C78)-1) & TEXT(H78*100,""0"") & I78,"&" IF(AND(D78=""Roof Sheet"", REGEXMATCH(C78,""(?i)KS\d{4}[A-Z]{2}"")), REGEXEXTRACT(C78,""(?i)KS\d{4}[A-Z]{2}""), IF(AND(REGEXMATCH(D78,""(?i)-DP""), REGEXMATCH(C78,""(?i)Downpipe"")), ""dp"" & REGEXEXTRACT(C78,""(\d+)"") & ""mm"", "&" IF(AND(REGEXMATCH(D78,""(?i)Bracket""), REGEXMATCH(C78,""(?i)Bracket"")), ""Brkt"" & REGEXEXTRACT(C78,""(\d+)"") & ""mm"", IF(AND(REGEXMATCH(D78,""(?i)-OP""), REGEXMATCH(C78,""(?i)pops"")), ""op"" & REGEXEXTRACT(C78,""(\d+)"") & ""mm"""&", IF(OR(D78=""R-FFTop"", D78=""R-FFBottom"", D78=""R-FFSide""), IF(REGEXMATCH(C78,""(?i)Profiled.*Top|Top.*Profiled""),""pfft"", IF(REGEXMATCH(C78,""(?i)Profiled.*Bottom|Bottom.*Profiled""),""pffb"", IF(REGEXMATCH(C78,""(?i)Squ"&"are""),""sff"",""""))), IF(REGEXMATCH(D78,""(?i)-Rivets""),""Rvt"", IF(REGEXMATCH(D78,""(?i)Silicone""),""300ml"", IF(REGEXMATCH(D78,""(?i)R-Butyl""),""300ml"", IF(REGEXMATCH(D78,""(?i)Fix""),""GenFix"", IF(AND(REGEXMATCH(C78,""(?i)Tim"&"ber""), REGEXMATCH(D78,""(?i)Timber"")),""tp"", IF(AND(REGEXMATCH(C78,""(?i)Vent G1275""), REGEXMATCH(D78,""(?i)Comb FIller"")),""CFV1275"", IF(REGEXMATCH(C78,""(?i)DPC""),""dpc"", IF(REGEXMATCH(C78,""(?i)Concealed Clips""),""ConClips"", I"&"F(REGEXMATCH(D78,""(?i)-Takeoff ea""),""Takeoff ea"", IF(REGEXMATCH(D78,""(?i)-Takeoff LM""),""Takeoff LM"", IF(REGEXMATCH(D78,""(?i)-Takeoff m2""),""Takeoff m2"", IF(D78=""R-TU/TD"",""TU/TD"",""""))))))))))))))))) )))"),"DR6003B55Mag") -> DR6003B55Mag | C78: 0.55mm BMT Coloursteel Maxam side barge flashing (570/3B) @ 9 deg | D78: R-Flashing | E78: =VALUE(MID(C78, FIND("(", C78)+1, FIND("/", C78)-FIND("(", C78)-1)) / 1000 -> 0.57 | F78: =IFERROR(__xludf.DUMMYFUNCTION("IFERROR(REGEXEXTRACT(C78,""@\s*(\d+)\s*deg"")&""°"","""") "),"9°") -> 9° | H78: =IFERROR(__xludf.DUMMYFUNCTION("IFERROR(REGEXEXTRACT(C78, ""(\d*\.\d+)mm""), """")"),"0.55") -> 0.55 | I78: Mag | J78: Specs | K78: LM | L78: 19.14 | M78: =L78 -> 19.14 | N78: =IFERROR(__xludf.DUMMYFUNCTION("""COMPUTED_VALUE"""),1.0124651257880029) -> 1.0124651 | O78: 1 | P78: 1 | Q78: =M78*N78*O78*P78 -> 19.378583 | S78: =R78*Q78 -> 0 | W78: =U78*Q78 -> 0 | AB78: =W78+S78 -> 0 | AM78: 19.14 | AN78: Matched | AO78: 0
B79: =IFERROR(__xludf.DUMMYFUNCTION("IFERROR( IF(C79="""","""", IF(OR(REGEXMATCH(D79,""(?i)-Flashing""), REGEXMATCH(D79,""(?i)-EavesGut""), REGEXMATCH(D79,""(?i)Valley"")), ""DR"" & TEXT( ROUNDUP( MIN( VALUE(MID(C79, FIND("&"""("",C79)+1, FIND(""/"",C79)-FIND(""("",C79)-1)), 1200 ) / 50, 0 ) * 50, ""0"" ) & MID(C79, FIND(""/"",C79)+1, FIND("")"",C79)-FIND(""/"",C79)-1) & TEXT(H79*100,""0"") & I79,"&" IF(AND(D79=""Roof Sheet"", REGEXMATCH(C79,""(?i)KS\d{4}[A-Z]{2}"")), REGEXEXTRACT(C79,""(?i)KS\d{4}[A-Z]{2}""), IF(AND(REGEXMATCH(D79,""(?i)-DP""), REGEXMATCH(C79,""(?i)Downpipe"")), ""dp"" & REGEXEXTRACT(C79,""(\d+)"") & ""mm"", "&" IF(AND(REGEXMATCH(D79,""(?i)Bracket""), REGEXMATCH(C79,""(?i)Bracket"")), ""Brkt"" & REGEXEXTRACT(C79,""(\d+)"") & ""mm"", IF(AND(REGEXMATCH(D79,""(?i)-OP""), REGEXMATCH(C79,""(?i)pops"")), ""op"" & REGEXEXTRACT(C79,""(\d+)"") & ""mm"""&", IF(OR(D79=""R-FFTop"", D79=""R-FFBottom"", D79=""R-FFSide""), IF(REGEXMATCH(C79,""(?i)Profiled.*Top|Top.*Profiled""),""pfft"", IF(REGEXMATCH(C79,""(?i)Profiled.*Bottom|Bottom.*Profiled""),""pffb"", IF(REGEXMATCH(C79,""(?i)Squ"&"are""),""sff"",""""))), IF(REGEXMATCH(D79,""(?i)-Rivets""),""Rvt"", IF(REGEXMATCH(D79,""(?i)Silicone""),""300ml"", IF(REGEXMATCH(D79,""(?i)R-Butyl""),""300ml"", IF(REGEXMATCH(D79,""(?i)Fix""),""GenFix"", IF(AND(REGEXMATCH(C79,""(?i)Tim"&"ber""), REGEXMATCH(D79,""(?i)Timber"")),""tp"", IF(AND(REGEXMATCH(C79,""(?i)Vent G1275""), REGEXMATCH(D79,""(?i)Comb FIller"")),""CFV1275"", IF(REGEXMATCH(C79,""(?i)DPC""),""dpc"", IF(REGEXMATCH(C79,""(?i)Concealed Clips""),""ConClips"", I"&"F(REGEXMATCH(D79,""(?i)-Takeoff ea""),""Takeoff ea"", IF(REGEXMATCH(D79,""(?i)-Takeoff LM""),""Takeoff LM"", IF(REGEXMATCH(D79,""(?i)-Takeoff m2""),""Takeoff m2"", IF(D79=""R-TU/TD"",""TU/TD"",""""))))))))))))))))) )))"),"300ml") -> 300ml | C79: Silicone 300ml | D79: R-Silicone | E79: =E78 -> 0.57 | F79: =F78 -> 9° | J79: No Specs | K79: ea | L79: =M78 -> 19.14 | M79: =(ROUNDDOWN((M78/5.7)+2,0)*E79)/8 -> 0.35625 | N79: =IFERROR(__xludf.DUMMYFUNCTION("""COMPUTED_VALUE"""),1.0124651257880029) -> 1.0124651 | O79: 1 | P79: 1 | Q79: =M79*N79*O79*P79 -> 0.3606907 | S79: =R79*Q79 -> 0 | W79: =U79*Q79 -> 0 | AB79: =W79+S79 -> 0 | AM79: 0.35625 | AN79: Matched | AO79: 0
B80: =IFERROR(__xludf.DUMMYFUNCTION("IFERROR( IF(C80="""","""", IF(OR(REGEXMATCH(D80,""(?i)-Flashing""), REGEXMATCH(D80,""(?i)-EavesGut""), REGEXMATCH(D80,""(?i)Valley"")), ""DR"" & TEXT( ROUNDUP( MIN( VALUE(MID(C80, FIND("&"""("",C80)+1, FIND(""/"",C80)-FIND(""("",C80)-1)), 1200 ) / 50, 0 ) * 50, ""0"" ) & MID(C80, FIND(""/"",C80)+1, FIND("")"",C80)-FIND(""/"",C80)-1) & TEXT(H80*100,""0"") & I80,"&" IF(AND(D80=""Roof Sheet"", REGEXMATCH(C80,""(?i)KS\d{4}[A-Z]{2}"")), REGEXEXTRACT(C80,""(?i)KS\d{4}[A-Z]{2}""), IF(AND(REGEXMATCH(D80,""(?i)-DP""), REGEXMATCH(C80,""(?i)Downpipe"")), ""dp"" & REGEXEXTRACT(C80,""(\d+)"") & ""mm"", "&" IF(AND(REGEXMATCH(D80,""(?i)Bracket""), REGEXMATCH(C80,""(?i)Bracket"")), ""Brkt"" & REGEXEXTRACT(C80,""(\d+)"") & ""mm"", IF(AND(REGEXMATCH(D80,""(?i)-OP""), REGEXMATCH(C80,""(?i)pops"")), ""op"" & REGEXEXTRACT(C80,""(\d+)"") & ""mm"""&", IF(OR(D80=""R-FFTop"", D80=""R-FFBottom"", D80=""R-FFSide""), IF(REGEXMATCH(C80,""(?i)Profiled.*Top|Top.*Profiled""),""pfft"", IF(REGEXMATCH(C80,""(?i)Profiled.*Bottom|Bottom.*Profiled""),""pffb"", IF(REGEXMATCH(C80,""(?i)Squ"&"are""),""sff"",""""))), IF(REGEXMATCH(D80,""(?i)-Rivets""),""Rvt"", IF(REGEXMATCH(D80,""(?i)Silicone""),""300ml"", IF(REGEXMATCH(D80,""(?i)R-Butyl""),""300ml"", IF(REGEXMATCH(D80,""(?i)Fix""),""GenFix"", IF(AND(REGEXMATCH(C80,""(?i)Tim"&"ber""), REGEXMATCH(D80,""(?i)Timber"")),""tp"", IF(AND(REGEXMATCH(C80,""(?i)Vent G1275""), REGEXMATCH(D80,""(?i)Comb FIller"")),""CFV1275"", IF(REGEXMATCH(C80,""(?i)DPC""),""dpc"", IF(REGEXMATCH(C80,""(?i)Concealed Clips""),""ConClips"", I"&"F(REGEXMATCH(D80,""(?i)-Takeoff ea""),""Takeoff ea"", IF(REGEXMATCH(D80,""(?i)-Takeoff LM""),""Takeoff LM"", IF(REGEXMATCH(D80,""(?i)-Takeoff m2""),""Takeoff m2"", IF(D80=""R-TU/TD"",""TU/TD"",""""))))))))))))))))) )))"),"Rvt") -> Rvt | C80: Rivets | D80: R-Rivets | E80: =E78 -> 0.57 | F80: =F79 -> 9° | J80: No Specs | K80: ea | L80: =M78 -> 19.14 | M80: =ROUNDUP(((M78/5.7)+1)*(E80/0.05),0) -> 50 | N80: =IFERROR(__xludf.DUMMYFUNCTION("""COMPUTED_VALUE"""),1.0124651257880029) -> 1.0124651 | O80: 1 | P80: 1 | Q80: =M80*N80*O80*P80 -> 50.623256 | S80: =R80*Q80 -> 0 | W80: =U80*Q80 -> 0 | AB80: =W80+S80 -> 0 | AM80: 50 | AN80: Matched | AO80: 0
B81: =IFERROR(__xludf.DUMMYFUNCTION("IFERROR( IF(C81="""","""", IF(OR(REGEXMATCH(D81,""(?i)-Flashing""), REGEXMATCH(D81,""(?i)-EavesGut""), REGEXMATCH(D81,""(?i)Valley"")), ""DR"" & TEXT( ROUNDUP( MIN( VALUE(MID(C81, FIND("&"""("",C81)+1, FIND(""/"",C81)-FIND(""("",C81)-1)), 1200 ) / 50, 0 ) * 50, ""0"" ) & MID(C81, FIND(""/"",C81)+1, FIND("")"",C81)-FIND(""/"",C81)-1) & TEXT(H81*100,""0"") & I81,"&" IF(AND(D81=""Roof Sheet"", REGEXMATCH(C81,""(?i)KS\d{4}[A-Z]{2}"")), REGEXEXTRACT(C81,""(?i)KS\d{4}[A-Z]{2}""), IF(AND(REGEXMATCH(D81,""(?i)-DP""), REGEXMATCH(C81,""(?i)Downpipe"")), ""dp"" & REGEXEXTRACT(C81,""(\d+)"") & ""mm"", "&" IF(AND(REGEXMATCH(D81,""(?i)Bracket""), REGEXMATCH(C81,""(?i)Bracket"")), ""Brkt"" & REGEXEXTRACT(C81,""(\d+)"") & ""mm"", IF(AND(REGEXMATCH(D81,""(?i)-OP""), REGEXMATCH(C81,""(?i)pops"")), ""op"" & REGEXEXTRACT(C81,""(\d+)"") & ""mm"""&", IF(OR(D81=""R-FFTop"", D81=""R-FFBottom"", D81=""R-FFSide""), IF(REGEXMATCH(C81,""(?i)Profiled.*Top|Top.*Profiled""),""pfft"", IF(REGEXMATCH(C81,""(?i)Profiled.*Bottom|Bottom.*Profiled""),""pffb"", IF(REGEXMATCH(C81,""(?i)Squ"&"are""),""sff"",""""))), IF(REGEXMATCH(D81,""(?i)-Rivets""),""Rvt"", IF(REGEXMATCH(D81,""(?i)Silicone""),""300ml"", IF(REGEXMATCH(D81,""(?i)R-Butyl""),""300ml"", IF(REGEXMATCH(D81,""(?i)Fix""),""GenFix"", IF(AND(REGEXMATCH(C81,""(?i)Tim"&"ber""), REGEXMATCH(D81,""(?i)Timber"")),""tp"", IF(AND(REGEXMATCH(C81,""(?i)Vent G1275""), REGEXMATCH(D81,""(?i)Comb FIller"")),""CFV1275"", IF(REGEXMATCH(C81,""(?i)DPC""),""dpc"", IF(REGEXMATCH(C81,""(?i)Concealed Clips""),""ConClips"", I"&"F(REGEXMATCH(D81,""(?i)-Takeoff ea""),""Takeoff ea"", IF(REGEXMATCH(D81,""(?i)-Takeoff LM""),""Takeoff LM"", IF(REGEXMATCH(D81,""(?i)-Takeoff m2""),""Takeoff m2"", IF(D81=""R-TU/TD"",""TU/TD"",""""))))))))))))))))) )))"),"GenFix") -> GenFix | C81: Fixings | D81: R-GenFix | F81: =F80 -> 9° | J81: No Specs | K81: ea | L81: =M78 -> 19.14 | M81: =ROUNDUP(M78/0.6,0)+1 -> 33 | N81: =IFERROR(__xludf.DUMMYFUNCTION("""COMPUTED_VALUE"""),1.0124651257880029) -> 1.0124651 | O81: 1 | P81: 1 | Q81: =M81*N81*O81*P81 -> 33.411349 | S81: =R81*Q81 -> 0 | W81: =U81*Q81 -> 0 | AB81: =W81+S81 -> 0 | AM81: 33 | AN81: Matched | AO81: 0
B82: =IFERROR(__xludf.DUMMYFUNCTION("IFERROR( IF(C82="""","""", IF(OR(REGEXMATCH(D82,""(?i)-Flashing""), REGEXMATCH(D82,""(?i)-EavesGut""), REGEXMATCH(D82,""(?i)Valley"")), ""DR"" & TEXT( ROUNDUP( MIN( VALUE(MID(C82, FIND("&"""("",C82)+1, FIND(""/"",C82)-FIND(""("",C82)-1)), 1200 ) / 50, 0 ) * 50, ""0"" ) & MID(C82, FIND(""/"",C82)+1, FIND("")"",C82)-FIND(""/"",C82)-1) & TEXT(H82*100,""0"") & I82,"&" IF(AND(D82=""Roof Sheet"", REGEXMATCH(C82,""(?i)KS\d{4}[A-Z]{2}"")), REGEXEXTRACT(C82,""(?i)KS\d{4}[A-Z]{2}""), IF(AND(REGEXMATCH(D82,""(?i)-DP""), REGEXMATCH(C82,""(?i)Downpipe"")), ""dp"" & REGEXEXTRACT(C82,""(\d+)"") & ""mm"", "&" IF(AND(REGEXMATCH(D82,""(?i)Bracket""), REGEXMATCH(C82,""(?i)Bracket"")), ""Brkt"" & REGEXEXTRACT(C82,""(\d+)"") & ""mm"", IF(AND(REGEXMATCH(D82,""(?i)-OP""), REGEXMATCH(C82,""(?i)pops"")), ""op"" & REGEXEXTRACT(C82,""(\d+)"") & ""mm"""&", IF(OR(D82=""R-FFTop"", D82=""R-FFBottom"", D82=""R-FFSide""), IF(REGEXMATCH(C82,""(?i)Profiled.*Top|Top.*Profiled""),""pfft"", IF(REGEXMATCH(C82,""(?i)Profiled.*Bottom|Bottom.*Profiled""),""pffb"", IF(REGEXMATCH(C82,""(?i)Squ"&"are""),""sff"",""""))), IF(REGEXMATCH(D82,""(?i)-Rivets""),""Rvt"", IF(REGEXMATCH(D82,""(?i)Silicone""),""300ml"", IF(REGEXMATCH(D82,""(?i)R-Butyl""),""300ml"", IF(REGEXMATCH(D82,""(?i)Fix""),""GenFix"", IF(AND(REGEXMATCH(C82,""(?i)Tim"&"ber""), REGEXMATCH(D82,""(?i)Timber"")),""tp"", IF(AND(REGEXMATCH(C82,""(?i)Vent G1275""), REGEXMATCH(D82,""(?i)Comb FIller"")),""CFV1275"", IF(REGEXMATCH(C82,""(?i)DPC""),""dpc"", IF(REGEXMATCH(C82,""(?i)Concealed Clips""),""ConClips"", I"&"F(REGEXMATCH(D82,""(?i)-Takeoff ea""),""Takeoff ea"", IF(REGEXMATCH(D82,""(?i)-Takeoff LM""),""Takeoff LM"", IF(REGEXMATCH(D82,""(?i)-Takeoff m2""),""Takeoff m2"", IF(D82=""R-TU/TD"",""TU/TD"",""""))))))))))))))))) )))"),"sff") -> sff | C82: Square Foam Filler Top | D82: R-FFSide | F82: =F81 -> 9° | J82: No Specs | K82: LM | L82: =M78 -> 19.14 | M82: =M78 -> 19.14 | N82: =IFERROR(__xludf.DUMMYFUNCTION("""COMPUTED_VALUE"""),1.0124651257880029) -> 1.0124651 | O82: 1 | P82: 1 | Q82: =M82*N82*O82*P82 -> 19.378583 | S82: =R82*Q82 -> 0 | W82: =U82*Q82 -> 0 | AB82: =W82+S82 -> 0 | AM82: 19.14 | AN82: Matched | AO82: 0
N83: =IFERROR(__xludf.DUMMYFUNCTION("""COMPUTED_VALUE"""),"")
A84: 1 | C84: Supply and install 0.55mm BMT Coloursteel Maxam side barge flashing, as per detail 6 (A502) | L84: =Q84 -> 32.804832 | N84: =IFERROR(__xludf.DUMMYFUNCTION("""COMPUTED_VALUE"""),"") | Q84: =Q85 -> 32.804832 | S84: =T84/Q84 -> 0 | T84: =SUM(S85:S89) -> 0 | V84: =W84/Q84 -> 0 | W84: =SUM(W85:W89) -> 0 | X84: =W84/$AC$176/$W$183/$X$173 -> #REF! | Y84: =(T84+W84)=(SUM(AB85:AB89)) -> TRUE | Z84: =(T84+W84)-(SUM(AB85:AB89)) -> 0 | AD84: =W84+T84 -> 0 | AE84: =AD84 -> 0 | AF84: =AE84/$AE$151 -> #REF! | AG84: =AF84*$AG$158 -> #REF! | AH84: =AF84*$AG$161 -> #REF! | AJ84: =ROUND(AK84/L84,2) -> #REF! | AK84: =ROUND(AH84+AG84+AD84,2) -> #REF!
B85: =IFERROR(__xludf.DUMMYFUNCTION("IFERROR( IF(C85="""","""", IF(OR(REGEXMATCH(D85,""(?i)-Flashing""), REGEXMATCH(D85,""(?i)-EavesGut""), REGEXMATCH(D85,""(?i)Valley"")), ""DR"" & TEXT( ROUNDUP( MIN( VALUE(MID(C85, FIND("&"""("",C85)+1, FIND(""/"",C85)-FIND(""("",C85)-1)), 1200 ) / 50, 0 ) * 50, ""0"" ) & MID(C85, FIND(""/"",C85)+1, FIND("")"",C85)-FIND(""/"",C85)-1) & TEXT(H85*100,""0"") & I85,"&" IF(AND(D85=""Roof Sheet"", REGEXMATCH(C85,""(?i)KS\d{4}[A-Z]{2}"")), REGEXEXTRACT(C85,""(?i)KS\d{4}[A-Z]{2}""), IF(AND(REGEXMATCH(D85,""(?i)-DP""), REGEXMATCH(C85,""(?i)Downpipe"")), ""dp"" & REGEXEXTRACT(C85,""(\d+)"") & ""mm"", "&" IF(AND(REGEXMATCH(D85,""(?i)Bracket""), REGEXMATCH(C85,""(?i)Bracket"")), ""Brkt"" & REGEXEXTRACT(C85,""(\d+)"") & ""mm"", IF(AND(REGEXMATCH(D85,""(?i)-OP""), REGEXMATCH(C85,""(?i)pops"")), ""op"" & REGEXEXTRACT(C85,""(\d+)"") & ""mm"""&", IF(OR(D85=""R-FFTop"", D85=""R-FFBottom"", D85=""R-FFSide""), IF(REGEXMATCH(C85,""(?i)Profiled.*Top|Top.*Profiled""),""pfft"", IF(REGEXMATCH(C85,""(?i)Profiled.*Bottom|Bottom.*Profiled""),""pffb"", IF(REGEXMATCH(C85,""(?i)Squ"&"are""),""sff"",""""))), IF(REGEXMATCH(D85,""(?i)-Rivets""),""Rvt"", IF(REGEXMATCH(D85,""(?i)Silicone""),""300ml"", IF(REGEXMATCH(D85,""(?i)R-Butyl""),""300ml"", IF(REGEXMATCH(D85,""(?i)Fix""),""GenFix"", IF(AND(REGEXMATCH(C85,""(?i)Tim"&"ber""), REGEXMATCH(D85,""(?i)Timber"")),""tp"", IF(AND(REGEXMATCH(C85,""(?i)Vent G1275""), REGEXMATCH(D85,""(?i)Comb FIller"")),""CFV1275"", IF(REGEXMATCH(C85,""(?i)DPC""),""dpc"", IF(REGEXMATCH(C85,""(?i)Concealed Clips""),""ConClips"", I"&"F(REGEXMATCH(D85,""(?i)-Takeoff ea""),""Takeoff ea"", IF(REGEXMATCH(D85,""(?i)-Takeoff LM""),""Takeoff LM"", IF(REGEXMATCH(D85,""(?i)-Takeoff m2""),""Takeoff m2"", IF(D85=""R-TU/TD"",""TU/TD"",""""))))))))))))))))) )))"),"DR6003B55Mag") -> DR6003B55Mag | C85: 0.55mm BMT Coloursteel Maxam side barge flashing (570/3B) @ 5 deg | D85: R-Flashing | E85: =VALUE(MID(C85, FIND("(", C85)+1, FIND("/", C85)-FIND("(", C85)-1)) / 1000 -> 0.57 | F85: =IFERROR(__xludf.DUMMYFUNCTION("IFERROR(REGEXEXTRACT(C85,""@\s*(\d+)\s*deg"")&""°"","""") "),"5°") -> 5° | H85: =IFERROR(__xludf.DUMMYFUNCTION("IFERROR(REGEXEXTRACT(C85, ""(\d*\.\d+)mm""), """")"),"0.55") -> 0.55 | I85: Mag | J85: Specs | K85: LM | L85: 32.68 | M85: =L85 -> 32.68 | N85: =IFERROR(__xludf.DUMMYFUNCTION("""COMPUTED_VALUE"""),1.0038198375433474) -> 1.0038198 | O85: 1 | P85: 1 | Q85: =M85*N85*O85*P85 -> 32.804832 | S85: =R85*Q85 -> 0 | W85: =U85*Q85 -> 0 | AB85: =W85+S85 -> 0 | AM85: 32.68 | AN85: Matched | AO85: 0
B86: =IFERROR(__xludf.DUMMYFUNCTION("IFERROR( IF(C86="""","""", IF(OR(REGEXMATCH(D86,""(?i)-Flashing""), REGEXMATCH(D86,""(?i)-EavesGut""), REGEXMATCH(D86,""(?i)Valley"")), ""DR"" & TEXT( ROUNDUP( MIN( VALUE(MID(C86, FIND("&"""("",C86)+1, FIND(""/"",C86)-FIND(""("",C86)-1)), 1200 ) / 50, 0 ) * 50, ""0"" ) & MID(C86, FIND(""/"",C86)+1, FIND("")"",C86)-FIND(""/"",C86)-1) & TEXT(H86*100,""0"") & I86,"&" IF(AND(D86=""Roof Sheet"", REGEXMATCH(C86,""(?i)KS\d{4}[A-Z]{2}"")), REGEXEXTRACT(C86,""(?i)KS\d{4}[A-Z]{2}""), IF(AND(REGEXMATCH(D86,""(?i)-DP""), REGEXMATCH(C86,""(?i)Downpipe"")), ""dp"" & REGEXEXTRACT(C86,""(\d+)"") & ""mm"", "&" IF(AND(REGEXMATCH(D86,""(?i)Bracket""), REGEXMATCH(C86,""(?i)Bracket"")), ""Brkt"" & REGEXEXTRACT(C86,""(\d+)"") & ""mm"", IF(AND(REGEXMATCH(D86,""(?i)-OP""), REGEXMATCH(C86,""(?i)pops"")), ""op"" & REGEXEXTRACT(C86,""(\d+)"") & ""mm"""&", IF(OR(D86=""R-FFTop"", D86=""R-FFBottom"", D86=""R-FFSide""), IF(REGEXMATCH(C86,""(?i)Profiled.*Top|Top.*Profiled""),""pfft"", IF(REGEXMATCH(C86,""(?i)Profiled.*Bottom|Bottom.*Profiled""),""pffb"", IF(REGEXMATCH(C86,""(?i)Squ"&"are""),""sff"",""""))), IF(REGEXMATCH(D86,""(?i)-Rivets""),""Rvt"", IF(REGEXMATCH(D86,""(?i)Silicone""),""300ml"", IF(REGEXMATCH(D86,""(?i)R-Butyl""),""300ml"", IF(REGEXMATCH(D86,""(?i)Fix""),""GenFix"", IF(AND(REGEXMATCH(C86,""(?i)Tim"&"ber""), REGEXMATCH(D86,""(?i)Timber"")),""tp"", IF(AND(REGEXMATCH(C86,""(?i)Vent G1275""), REGEXMATCH(D86,""(?i)Comb FIller"")),""CFV1275"", IF(REGEXMATCH(C86,""(?i)DPC""),""dpc"", IF(REGEXMATCH(C86,""(?i)Concealed Clips""),""ConClips"", I"&"F(REGEXMATCH(D86,""(?i)-Takeoff ea""),""Takeoff ea"", IF(REGEXMATCH(D86,""(?i)-Takeoff LM""),""Takeoff LM"", IF(REGEXMATCH(D86,""(?i)-Takeoff m2""),""Takeoff m2"", IF(D86=""R-TU/TD"",""TU/TD"",""""))))))))))))))))) )))"),"300ml") -> 300ml | C86: Silicone 300ml | D86: R-Silicone | E86: =E85 -> 0.57 | F86: =F85 -> 5° | J86: No Specs | K86: ea | L86: =M85 -> 32.68 | M86: =(ROUNDDOWN((M85/5.7)+2,0)*E86)/8 -> 0.49875 | N86: =IFERROR(__xludf.DUMMYFUNCTION("""COMPUTED_VALUE"""),1.0038198375433474) -> 1.0038198 | O86: 1 | P86: 1 | Q86: =M86*N86*O86*P86 -> 0.50065514 | S86: =R86*Q86 -> 0 | W86: =U86*Q86 -> 0 | AB86: =W86+S86 -> 0 | AM86: 0.49875 | AN86: Matched | AO86: 0
B87: =IFERROR(__xludf.DUMMYFUNCTION("IFERROR( IF(C87="""","""", IF(OR(REGEXMATCH(D87,""(?i)-Flashing""), REGEXMATCH(D87,""(?i)-EavesGut""), REGEXMATCH(D87,""(?i)Valley"")), ""DR"" & TEXT( ROUNDUP( MIN( VALUE(MID(C87, FIND("&"""("",C87)+1, FIND(""/"",C87)-FIND(""("",C87)-1)), 1200 ) / 50, 0 ) * 50, ""0"" ) & MID(C87, FIND(""/"",C87)+1, FIND("")"",C87)-FIND(""/"",C87)-1) & TEXT(H87*100,""0"") & I87,"&" IF(AND(D87=""Roof Sheet"", REGEXMATCH(C87,""(?i)KS\d{4}[A-Z]{2}"")), REGEXEXTRACT(C87,""(?i)KS\d{4}[A-Z]{2}""), IF(AND(REGEXMATCH(D87,""(?i)-DP""), REGEXMATCH(C87,""(?i)Downpipe"")), ""dp"" & REGEXEXTRACT(C87,""(\d+)"") & ""mm"", "&" IF(AND(REGEXMATCH(D87,""(?i)Bracket""), REGEXMATCH(C87,""(?i)Bracket"")), ""Brkt"" & REGEXEXTRACT(C87,""(\d+)"") & ""mm"", IF(AND(REGEXMATCH(D87,""(?i)-OP""), REGEXMATCH(C87,""(?i)pops"")), ""op"" & REGEXEXTRACT(C87,""(\d+)"") & ""mm"""&", IF(OR(D87=""R-FFTop"", D87=""R-FFBottom"", D87=""R-FFSide""), IF(REGEXMATCH(C87,""(?i)Profiled.*Top|Top.*Profiled""),""pfft"", IF(REGEXMATCH(C87,""(?i)Profiled.*Bottom|Bottom.*Profiled""),""pffb"", IF(REGEXMATCH(C87,""(?i)Squ"&"are""),""sff"",""""))), IF(REGEXMATCH(D87,""(?i)-Rivets""),""Rvt"", IF(REGEXMATCH(D87,""(?i)Silicone""),""300ml"", IF(REGEXMATCH(D87,""(?i)R-Butyl""),""300ml"", IF(REGEXMATCH(D87,""(?i)Fix""),""GenFix"", IF(AND(REGEXMATCH(C87,""(?i)Tim"&"ber""), REGEXMATCH(D87,""(?i)Timber"")),""tp"", IF(AND(REGEXMATCH(C87,""(?i)Vent G1275""), REGEXMATCH(D87,""(?i)Comb FIller"")),""CFV1275"", IF(REGEXMATCH(C87,""(?i)DPC""),""dpc"", IF(REGEXMATCH(C87,""(?i)Concealed Clips""),""ConClips"", I"&"F(REGEXMATCH(D87,""(?i)-Takeoff ea""),""Takeoff ea"", IF(REGEXMATCH(D87,""(?i)-Takeoff LM""),""Takeoff LM"", IF(REGEXMATCH(D87,""(?i)-Takeoff m2""),""Takeoff m2"", IF(D87=""R-TU/TD"",""TU/TD"",""""))))))))))))))))) )))"),"Rvt") -> Rvt | C87: Rivets | D87: R-Rivets | E87: =E85 -> 0.57 | F87: =F86 -> 5° | J87: No Specs | K87: ea | L87: =M85 -> 32.68 | M87: =ROUNDUP(((M85/5.7)+1)*(E87/0.05),0) -> 77 | N87: =IFERROR(__xludf.DUMMYFUNCTION("""COMPUTED_VALUE"""),1.0038198375433474) -> 1.0038198 | O87: 1 | P87: 1 | Q87: =M87*N87*O87*P87 -> 77.294127 | S87: =R87*Q87 -> 0 | W87: =U87*Q87 -> 0 | AB87: =W87+S87 -> 0 | AM87: 77 | AN87: Matched | AO87: 0
B88: =IFERROR(__xludf.DUMMYFUNCTION("IFERROR( IF(C88="""","""", IF(OR(REGEXMATCH(D88,""(?i)-Flashing""), REGEXMATCH(D88,""(?i)-EavesGut""), REGEXMATCH(D88,""(?i)Valley"")), ""DR"" & TEXT( ROUNDUP( MIN( VALUE(MID(C88, FIND("&"""("",C88)+1, FIND(""/"",C88)-FIND(""("",C88)-1)), 1200 ) / 50, 0 ) * 50, ""0"" ) & MID(C88, FIND(""/"",C88)+1, FIND("")"",C88)-FIND(""/"",C88)-1) & TEXT(H88*100,""0"") & I88,"&" IF(AND(D88=""Roof Sheet"", REGEXMATCH(C88,""(?i)KS\d{4}[A-Z]{2}"")), REGEXEXTRACT(C88,""(?i)KS\d{4}[A-Z]{2}""), IF(AND(REGEXMATCH(D88,""(?i)-DP""), REGEXMATCH(C88,""(?i)Downpipe"")), ""dp"" & REGEXEXTRACT(C88,""(\d+)"") & ""mm"", "&" IF(AND(REGEXMATCH(D88,""(?i)Bracket""), REGEXMATCH(C88,""(?i)Bracket"")), ""Brkt"" & REGEXEXTRACT(C88,""(\d+)"") & ""mm"", IF(AND(REGEXMATCH(D88,""(?i)-OP""), REGEXMATCH(C88,""(?i)pops"")), ""op"" & REGEXEXTRACT(C88,""(\d+)"") & ""mm"""&", IF(OR(D88=""R-FFTop"", D88=""R-FFBottom"", D88=""R-FFSide""), IF(REGEXMATCH(C88,""(?i)Profiled.*Top|Top.*Profiled""),""pfft"", IF(REGEXMATCH(C88,""(?i)Profiled.*Bottom|Bottom.*Profiled""),""pffb"", IF(REGEXMATCH(C88,""(?i)Squ"&"are""),""sff"",""""))), IF(REGEXMATCH(D88,""(?i)-Rivets""),""Rvt"", IF(REGEXMATCH(D88,""(?i)Silicone""),""300ml"", IF(REGEXMATCH(D88,""(?i)R-Butyl""),""300ml"", IF(REGEXMATCH(D88,""(?i)Fix""),""GenFix"", IF(AND(REGEXMATCH(C88,""(?i)Tim"&"ber""), REGEXMATCH(D88,""(?i)Timber"")),""tp"", IF(AND(REGEXMATCH(C88,""(?i)Vent G1275""), REGEXMATCH(D88,""(?i)Comb FIller"")),""CFV1275"", IF(REGEXMATCH(C88,""(?i)DPC""),""dpc"", IF(REGEXMATCH(C88,""(?i)Concealed Clips""),""ConClips"", I"&"F(REGEXMATCH(D88,""(?i)-Takeoff ea""),""Takeoff ea"", IF(REGEXMATCH(D88,""(?i)-Takeoff LM""),""Takeoff LM"", IF(REGEXMATCH(D88,""(?i)-Takeoff m2""),""Takeoff m2"", IF(D88=""R-TU/TD"",""TU/TD"",""""))))))))))))))))) )))"),"GenFix") -> GenFix | C88: Fixings | D88: R-GenFix | F88: =F87 -> 5° | J88: No Specs | K88: ea | L88: =M85 -> 32.68 | M88: =ROUNDUP(M85/0.6,0)+1 -> 56 | N88: =IFERROR(__xludf.DUMMYFUNCTION("""COMPUTED_VALUE"""),1.0038198375433474) -> 1.0038198 | O88: 1 | P88: 1 | Q88: =M88*N88*O88*P88 -> 56.213911 | S88: =R88*Q88 -> 0 | W88: =U88*Q88 -> 0 | AB88: =W88+S88 -> 0 | AM88: 56 | AN88: Matched | AO88: 0
B89: =IFERROR(__xludf.DUMMYFUNCTION("IFERROR( IF(C89="""","""", IF(OR(REGEXMATCH(D89,""(?i)-Flashing""), REGEXMATCH(D89,""(?i)-EavesGut""), REGEXMATCH(D89,""(?i)Valley"")), ""DR"" & TEXT( ROUNDUP( MIN( VALUE(MID(C89, FIND("&"""("",C89)+1, FIND(""/"",C89)-FIND(""("",C89)-1)), 1200 ) / 50, 0 ) * 50, ""0"" ) & MID(C89, FIND(""/"",C89)+1, FIND("")"",C89)-FIND(""/"",C89)-1) & TEXT(H89*100,""0"") & I89,"&" IF(AND(D89=""Roof Sheet"", REGEXMATCH(C89,""(?i)KS\d{4}[A-Z]{2}"")), REGEXEXTRACT(C89,""(?i)KS\d{4}[A-Z]{2}""), IF(AND(REGEXMATCH(D89,""(?i)-DP""), REGEXMATCH(C89,""(?i)Downpipe"")), ""dp"" & REGEXEXTRACT(C89,""(\d+)"") & ""mm"", "&" IF(AND(REGEXMATCH(D89,""(?i)Bracket""), REGEXMATCH(C89,""(?i)Bracket"")), ""Brkt"" & REGEXEXTRACT(C89,""(\d+)"") & ""mm"", IF(AND(REGEXMATCH(D89,""(?i)-OP""), REGEXMATCH(C89,""(?i)pops"")), ""op"" & REGEXEXTRACT(C89,""(\d+)"") & ""mm"""&", IF(OR(D89=""R-FFTop"", D89=""R-FFBottom"", D89=""R-FFSide""), IF(REGEXMATCH(C89,""(?i)Profiled.*Top|Top.*Profiled""),""pfft"", IF(REGEXMATCH(C89,""(?i)Profiled.*Bottom|Bottom.*Profiled""),""pffb"", IF(REGEXMATCH(C89,""(?i)Squ"&"are""),""sff"",""""))), IF(REGEXMATCH(D89,""(?i)-Rivets""),""Rvt"", IF(REGEXMATCH(D89,""(?i)Silicone""),""300ml"", IF(REGEXMATCH(D89,""(?i)R-Butyl""),""300ml"", IF(REGEXMATCH(D89,""(?i)Fix""),""GenFix"", IF(AND(REGEXMATCH(C89,""(?i)Tim"&"ber""), REGEXMATCH(D89,""(?i)Timber"")),""tp"", IF(AND(REGEXMATCH(C89,""(?i)Vent G1275""), REGEXMATCH(D89,""(?i)Comb FIller"")),""CFV1275"", IF(REGEXMATCH(C89,""(?i)DPC""),""dpc"", IF(REGEXMATCH(C89,""(?i)Concealed Clips""),""ConClips"", I"&"F(REGEXMATCH(D89,""(?i)-Takeoff ea""),""Takeoff ea"", IF(REGEXMATCH(D89,""(?i)-Takeoff LM""),""Takeoff LM"", IF(REGEXMATCH(D89,""(?i)-Takeoff m2""),""Takeoff m2"", IF(D89=""R-TU/TD"",""TU/TD"",""""))))))))))))))))) )))"),"sff") -> sff | C89: Square Foam Filler Top | D89: R-FFSide | F89: =F88 -> 5° | J89: No Specs | K89: LM | L89: =M85 -> 32.68 | M89: =M85 -> 32.68 | N89: =IFERROR(__xludf.DUMMYFUNCTION("""COMPUTED_VALUE"""),1.0038198375433474) -> 1.0038198 | O89: 1 | P89: 1 | Q89: =M89*N89*O89*P89 -> 32.804832 | S89: =R89*Q89 -> 0 | W89: =U89*Q89 -> 0 | AB89: =W89+S89 -> 0 | AM89: 32.68 | AN89: Matched | AO89: 0
N90: =IFERROR(__xludf.DUMMYFUNCTION("""COMPUTED_VALUE"""),"")
A91: 1 | C91: Supply and install 0.55mm BMT cover flashing, as per detail 4 (A502) | L91: =Q91 -> 112.78 | N91: =IFERROR(__xludf.DUMMYFUNCTION("""COMPUTED_VALUE"""),"") | Q91: =Q92 -> 112.78 | S91: =T91/Q91 -> 0 | T91: =SUM(S92:S95) -> 0 | V91: =W91/Q91 -> 0 | W91: =SUM(W92:W95) -> 0 | X91: =W91/$AC$176/$W$183/$X$173 -> #REF! | Y91: =(T91+W91)=(SUM(AB92:AB95)) -> TRUE | Z91: =(T91+W91)-(SUM(AB92:AB95)) -> 0 | AD91: =W91+T91 -> 0 | AE91: =AD91 -> 0 | AF91: =AE91/$AE$151 -> #REF! | AG91: =AF91*$AG$158 -> #REF! | AH91: =AF91*$AG$161 -> #REF! | AJ91: =ROUND(AK91/L91,2) -> #REF! | AK91: =ROUND(AH91+AG91+AD91,2) -> #REF!
B92: =IFERROR(__xludf.DUMMYFUNCTION("IFERROR( IF(C92="""","""", IF(OR(REGEXMATCH(D92,""(?i)-Flashing""), REGEXMATCH(D92,""(?i)-EavesGut""), REGEXMATCH(D92,""(?i)Valley"")), ""DR"" & TEXT( ROUNDUP( MIN( VALUE(MID(C92, FIND("&"""("",C92)+1, FIND(""/"",C92)-FIND(""("",C92)-1)), 1200 ) / 50, 0 ) * 50, ""0"" ) & MID(C92, FIND(""/"",C92)+1, FIND("")"",C92)-FIND(""/"",C92)-1) & TEXT(H92*100,""0"") & I92,"&" IF(AND(D92=""Roof Sheet"", REGEXMATCH(C92,""(?i)KS\d{4}[A-Z]{2}"")), REGEXEXTRACT(C92,""(?i)KS\d{4}[A-Z]{2}""), IF(AND(REGEXMATCH(D92,""(?i)-DP""), REGEXMATCH(C92,""(?i)Downpipe"")), ""dp"" & REGEXEXTRACT(C92,""(\d+)"") & ""mm"", "&" IF(AND(REGEXMATCH(D92,""(?i)Bracket""), REGEXMATCH(C92,""(?i)Bracket"")), ""Brkt"" & REGEXEXTRACT(C92,""(\d+)"") & ""mm"", IF(AND(REGEXMATCH(D92,""(?i)-OP""), REGEXMATCH(C92,""(?i)pops"")), ""op"" & REGEXEXTRACT(C92,""(\d+)"") & ""mm"""&", IF(OR(D92=""R-FFTop"", D92=""R-FFBottom"", D92=""R-FFSide""), IF(REGEXMATCH(C92,""(?i)Profiled.*Top|Top.*Profiled""),""pfft"", IF(REGEXMATCH(C92,""(?i)Profiled.*Bottom|Bottom.*Profiled""),""pffb"", IF(REGEXMATCH(C92,""(?i)Squ"&"are""),""sff"",""""))), IF(REGEXMATCH(D92,""(?i)-Rivets""),""Rvt"", IF(REGEXMATCH(D92,""(?i)Silicone""),""300ml"", IF(REGEXMATCH(D92,""(?i)R-Butyl""),""300ml"", IF(REGEXMATCH(D92,""(?i)Fix""),""GenFix"", IF(AND(REGEXMATCH(C92,""(?i)Tim"&"ber""), REGEXMATCH(D92,""(?i)Timber"")),""tp"", IF(AND(REGEXMATCH(C92,""(?i)Vent G1275""), REGEXMATCH(D92,""(?i)Comb FIller"")),""CFV1275"", IF(REGEXMATCH(C92,""(?i)DPC""),""dpc"", IF(REGEXMATCH(C92,""(?i)Concealed Clips""),""ConClips"", I"&"F(REGEXMATCH(D92,""(?i)-Takeoff ea""),""Takeoff ea"", IF(REGEXMATCH(D92,""(?i)-Takeoff LM""),""Takeoff LM"", IF(REGEXMATCH(D92,""(?i)-Takeoff m2""),""Takeoff m2"", IF(D92=""R-TU/TD"",""TU/TD"",""""))))))))))))))))) )))"),"DR7508B55Mag") -> DR7508B55Mag | C92: 0.55mm BMT cover flashing (710/8B) | D92: R-Flashing | E92: =VALUE(MID(C92, FIND("(", C92)+1, FIND("/", C92)-FIND("(", C92)-1)) / 1000 -> 0.71 | F92: =IFERROR(__xludf.DUMMYFUNCTION("IFERROR(REGEXEXTRACT(C92,""@\s*(\d+)\s*deg"")&""°"","""") "),"") | H92: =IFERROR(__xludf.DUMMYFUNCTION("IFERROR(REGEXEXTRACT(C92, ""(\d*\.\d+)mm""), """")"),"0.55") -> 0.55 | I92: Mag | J92: Specs | K92: LM | L92: =L105 -> 112.78 | M92: =L92 -> 112.78 | N92: =IFERROR(__xludf.DUMMYFUNCTION("""COMPUTED_VALUE"""),1.0) -> 1 | O92: 1 | P92: 1 | Q92: =M92*N92*O92*P92 -> 112.78 | S92: =R92*Q92 -> 0 | W92: =U92*Q92 -> 0 | X92: =W92/$AC$176/$W$183/Y92 -> #REF! | Y92: 2 | Z92: =Q92/X92 -> #REF! | AB92: =W92+S92 -> 0 | AM92: 112.78 | AN92: Matched | AO92: 0
B93: =IFERROR(__xludf.DUMMYFUNCTION("IFERROR( IF(C93="""","""", IF(OR(REGEXMATCH(D93,""(?i)-Flashing""), REGEXMATCH(D93,""(?i)-EavesGut""), REGEXMATCH(D93,""(?i)Valley"")), ""DR"" & TEXT( ROUNDUP( MIN( VALUE(MID(C93, FIND("&"""("",C93)+1, FIND(""/"",C93)-FIND(""("",C93)-1)), 1200 ) / 50, 0 ) * 50, ""0"" ) & MID(C93, FIND(""/"",C93)+1, FIND("")"",C93)-FIND(""/"",C93)-1) & TEXT(H93*100,""0"") & I93,"&" IF(AND(D93=""Roof Sheet"", REGEXMATCH(C93,""(?i)KS\d{4}[A-Z]{2}"")), REGEXEXTRACT(C93,""(?i)KS\d{4}[A-Z]{2}""), IF(AND(REGEXMATCH(D93,""(?i)-DP""), REGEXMATCH(C93,""(?i)Downpipe"")), ""dp"" & REGEXEXTRACT(C93,""(\d+)"") & ""mm"", "&" IF(AND(REGEXMATCH(D93,""(?i)Bracket""), REGEXMATCH(C93,""(?i)Bracket"")), ""Brkt"" & REGEXEXTRACT(C93,""(\d+)"") & ""mm"", IF(AND(REGEXMATCH(D93,""(?i)-OP""), REGEXMATCH(C93,""(?i)pops"")), ""op"" & REGEXEXTRACT(C93,""(\d+)"") & ""mm"""&", IF(OR(D93=""R-FFTop"", D93=""R-FFBottom"", D93=""R-FFSide""), IF(REGEXMATCH(C93,""(?i)Profiled.*Top|Top.*Profiled""),""pfft"", IF(REGEXMATCH(C93,""(?i)Profiled.*Bottom|Bottom.*Profiled""),""pffb"", IF(REGEXMATCH(C93,""(?i)Squ"&"are""),""sff"",""""))), IF(REGEXMATCH(D93,""(?i)-Rivets""),""Rvt"", IF(REGEXMATCH(D93,""(?i)Silicone""),""300ml"", IF(REGEXMATCH(D93,""(?i)R-Butyl""),""300ml"", IF(REGEXMATCH(D93,""(?i)Fix""),""GenFix"", IF(AND(REGEXMATCH(C93,""(?i)Tim"&"ber""), REGEXMATCH(D93,""(?i)Timber"")),""tp"", IF(AND(REGEXMATCH(C93,""(?i)Vent G1275""), REGEXMATCH(D93,""(?i)Comb FIller"")),""CFV1275"", IF(REGEXMATCH(C93,""(?i)DPC""),""dpc"", IF(REGEXMATCH(C93,""(?i)Concealed Clips""),""ConClips"", I"&"F(REGEXMATCH(D93,""(?i)-Takeoff ea""),""Takeoff ea"", IF(REGEXMATCH(D93,""(?i)-Takeoff LM""),""Takeoff LM"", IF(REGEXMATCH(D93,""(?i)-Takeoff m2""),""Takeoff m2"", IF(D93=""R-TU/TD"",""TU/TD"",""""))))))))))))))))) )))"),"300ml") -> 300ml | C93: Silicone 300ml | D93: R-Silicone | E93: =E92 -> 0.71 | F93: =F92 | J93: No Specs | K93: ea | L93: =M92 -> 112.78 | M93: =(ROUNDDOWN((M92/5.7)+2,0)*E93)/8 -> 1.86375 | N93: =IFERROR(__xludf.DUMMYFUNCTION("""COMPUTED_VALUE"""),1.0) -> 1 | O93: 1 | P93: 1 | Q93: =M93*N93*O93*P93 -> 1.86375 | S93: =R93*Q93 -> 0 | W93: =U93*Q93 -> 0 | AB93: =W93+S93 -> 0 | AM93: 1.86375 | AN93: Matched | AO93: 0
B94: =IFERROR(__xludf.DUMMYFUNCTION("IFERROR( IF(C94="""","""", IF(OR(REGEXMATCH(D94,""(?i)-Flashing""), REGEXMATCH(D94,""(?i)-EavesGut""), REGEXMATCH(D94,""(?i)Valley"")), ""DR"" & TEXT( ROUNDUP( MIN( VALUE(MID(C94, FIND("&"""("",C94)+1, FIND(""/"",C94)-FIND(""("",C94)-1)), 1200 ) / 50, 0 ) * 50, ""0"" ) & MID(C94, FIND(""/"",C94)+1, FIND("")"",C94)-FIND(""/"",C94)-1) & TEXT(H94*100,""0"") & I94,"&" IF(AND(D94=""Roof Sheet"", REGEXMATCH(C94,""(?i)KS\d{4}[A-Z]{2}"")), REGEXEXTRACT(C94,""(?i)KS\d{4}[A-Z]{2}""), IF(AND(REGEXMATCH(D94,""(?i)-DP""), REGEXMATCH(C94,""(?i)Downpipe"")), ""dp"" & REGEXEXTRACT(C94,""(\d+)"") & ""mm"", "&" IF(AND(REGEXMATCH(D94,""(?i)Bracket""), REGEXMATCH(C94,""(?i)Bracket"")), ""Brkt"" & REGEXEXTRACT(C94,""(\d+)"") & ""mm"", IF(AND(REGEXMATCH(D94,""(?i)-OP""), REGEXMATCH(C94,""(?i)pops"")), ""op"" & REGEXEXTRACT(C94,""(\d+)"") & ""mm"""&", IF(OR(D94=""R-FFTop"", D94=""R-FFBottom"", D94=""R-FFSide""), IF(REGEXMATCH(C94,""(?i)Profiled.*Top|Top.*Profiled""),""pfft"", IF(REGEXMATCH(C94,""(?i)Profiled.*Bottom|Bottom.*Profiled""),""pffb"", IF(REGEXMATCH(C94,""(?i)Squ"&"are""),""sff"",""""))), IF(REGEXMATCH(D94,""(?i)-Rivets""),""Rvt"", IF(REGEXMATCH(D94,""(?i)Silicone""),""300ml"", IF(REGEXMATCH(D94,""(?i)R-Butyl""),""300ml"", IF(REGEXMATCH(D94,""(?i)Fix""),""GenFix"", IF(AND(REGEXMATCH(C94,""(?i)Tim"&"ber""), REGEXMATCH(D94,""(?i)Timber"")),""tp"", IF(AND(REGEXMATCH(C94,""(?i)Vent G1275""), REGEXMATCH(D94,""(?i)Comb FIller"")),""CFV1275"", IF(REGEXMATCH(C94,""(?i)DPC""),""dpc"", IF(REGEXMATCH(C94,""(?i)Concealed Clips""),""ConClips"", I"&"F(REGEXMATCH(D94,""(?i)-Takeoff ea""),""Takeoff ea"", IF(REGEXMATCH(D94,""(?i)-Takeoff LM""),""Takeoff LM"", IF(REGEXMATCH(D94,""(?i)-Takeoff m2""),""Takeoff m2"", IF(D94=""R-TU/TD"",""TU/TD"",""""))))))))))))))))) )))"),"Rvt") -> Rvt | C94: Rivets | D94: R-Rivets | E94: =E92 -> 0.71 | F94: =F93 | J94: No Specs | K94: ea | L94: =M92 -> 112.78 | M94: =ROUNDUP(((M92/5.7)+1)*(E94/0.05),0) -> 296 | N94: =IFERROR(__xludf.DUMMYFUNCTION("""COMPUTED_VALUE"""),1.0) -> 1 | O94: 1 | P94: 1 | Q94: =M94*N94*O94*P94 -> 296 | S94: =R94*Q94 -> 0 | W94: =U94*Q94 -> 0 | AB94: =W94+S94 -> 0 | AM94: 296 | AN94: Matched | AO94: 0
B95: =IFERROR(__xludf.DUMMYFUNCTION("IFERROR( IF(C95="""","""", IF(OR(REGEXMATCH(D95,""(?i)-Flashing""), REGEXMATCH(D95,""(?i)-EavesGut""), REGEXMATCH(D95,""(?i)Valley"")), ""DR"" & TEXT( ROUNDUP( MIN( VALUE(MID(C95, FIND("&"""("",C95)+1, FIND(""/"",C95)-FIND(""("",C95)-1)), 1200 ) / 50, 0 ) * 50, ""0"" ) & MID(C95, FIND(""/"",C95)+1, FIND("")"",C95)-FIND(""/"",C95)-1) & TEXT(H95*100,""0"") & I95,"&" IF(AND(D95=""Roof Sheet"", REGEXMATCH(C95,""(?i)KS\d{4}[A-Z]{2}"")), REGEXEXTRACT(C95,""(?i)KS\d{4}[A-Z]{2}""), IF(AND(REGEXMATCH(D95,""(?i)-DP""), REGEXMATCH(C95,""(?i)Downpipe"")), ""dp"" & REGEXEXTRACT(C95,""(\d+)"") & ""mm"", "&" IF(AND(REGEXMATCH(D95,""(?i)Bracket""), REGEXMATCH(C95,""(?i)Bracket"")), ""Brkt"" & REGEXEXTRACT(C95,""(\d+)"") & ""mm"", IF(AND(REGEXMATCH(D95,""(?i)-OP""), REGEXMATCH(C95,""(?i)pops"")), ""op"" & REGEXEXTRACT(C95,""(\d+)"") & ""mm"""&", IF(OR(D95=""R-FFTop"", D95=""R-FFBottom"", D95=""R-FFSide""), IF(REGEXMATCH(C95,""(?i)Profiled.*Top|Top.*Profiled""),""pfft"", IF(REGEXMATCH(C95,""(?i)Profiled.*Bottom|Bottom.*Profiled""),""pffb"", IF(REGEXMATCH(C95,""(?i)Squ"&"are""),""sff"",""""))), IF(REGEXMATCH(D95,""(?i)-Rivets""),""Rvt"", IF(REGEXMATCH(D95,""(?i)Silicone""),""300ml"", IF(REGEXMATCH(D95,""(?i)R-Butyl""),""300ml"", IF(REGEXMATCH(D95,""(?i)Fix""),""GenFix"", IF(AND(REGEXMATCH(C95,""(?i)Tim"&"ber""), REGEXMATCH(D95,""(?i)Timber"")),""tp"", IF(AND(REGEXMATCH(C95,""(?i)Vent G1275""), REGEXMATCH(D95,""(?i)Comb FIller"")),""CFV1275"", IF(REGEXMATCH(C95,""(?i)DPC""),""dpc"", IF(REGEXMATCH(C95,""(?i)Concealed Clips""),""ConClips"", I"&"F(REGEXMATCH(D95,""(?i)-Takeoff ea""),""Takeoff ea"", IF(REGEXMATCH(D95,""(?i)-Takeoff LM""),""Takeoff LM"", IF(REGEXMATCH(D95,""(?i)-Takeoff m2""),""Takeoff m2"", IF(D95=""R-TU/TD"",""TU/TD"",""""))))))))))))))))) )))"),"GenFix") -> GenFix | C95: Fixings | D95: R-GenFix | F95: =F94 | J95: No Specs | K95: ea | L95: =M92 -> 112.78 | M95: =ROUNDUP(M92/0.6,0)+1 -> 189 | N95: =IFERROR(__xludf.DUMMYFUNCTION("""COMPUTED_VALUE"""),1.0) -> 1 | O95: 1 | P95: 1 | Q95: =M95*N95*O95*P95 -> 189 | S95: =R95*Q95 -> 0 | W95: =U95*Q95 -> 0 | AB95: =W95+S95 -> 0 | AM95: 189 | AN95: Matched | AO95: 0
N96: =IFERROR(__xludf.DUMMYFUNCTION("""COMPUTED_VALUE"""),"")
A97: 1 | C97: Supply and install 0.55mm BMT Coloursteel Maxam eaves flashing, as per detail 4 (A502) | L97: =Q97 -> 112.78 | N97: =IFERROR(__xludf.DUMMYFUNCTION("""COMPUTED_VALUE"""),"") | Q97: =Q98 -> 112.78 | S97: =T97/Q97 -> 0 | T97: =SUM(S98:S102) -> 0 | V97: =W97/Q97 -> 0 | W97: =SUM(W98:W102) -> 0 | X97: =W97/$AC$176/$W$183/Y97 -> #REF! | Y97: =(T97+W97)=(SUM(AB98:AB102)) -> TRUE | Z97: =(T97+W97)-(SUM(AB98:AB102)) -> 0 | AD97: =W97+T97 -> 0 | AE97: =AD97 -> 0 | AF97: =AE97/$AE$151 -> #REF! | AG97: =AF97*$AG$158 -> #REF! | AH97: =AF97*$AG$161 -> #REF! | AJ97: =ROUND(AK97/L97,2) -> #REF! | AK97: =ROUND(AH97+AG97+AD97,2) -> #REF!
B98: =IFERROR(__xludf.DUMMYFUNCTION("IFERROR( IF(C98="""","""", IF(OR(REGEXMATCH(D98,""(?i)-Flashing""), REGEXMATCH(D98,""(?i)-EavesGut""), REGEXMATCH(D98,""(?i)Valley"")), ""DR"" & TEXT( ROUNDUP( MIN( VALUE(MID(C98, FIND("&"""("",C98)+1, FIND(""/"",C98)-FIND(""("",C98)-1)), 1200 ) / 50, 0 ) * 50, ""0"" ) & MID(C98, FIND(""/"",C98)+1, FIND("")"",C98)-FIND(""/"",C98)-1) & TEXT(H98*100,""0"") & I98,"&" IF(AND(D98=""Roof Sheet"", REGEXMATCH(C98,""(?i)KS\d{4}[A-Z]{2}"")), REGEXEXTRACT(C98,""(?i)KS\d{4}[A-Z]{2}""), IF(AND(REGEXMATCH(D98,""(?i)-DP""), REGEXMATCH(C98,""(?i)Downpipe"")), ""dp"" & REGEXEXTRACT(C98,""(\d+)"") & ""mm"", "&" IF(AND(REGEXMATCH(D98,""(?i)Bracket""), REGEXMATCH(C98,""(?i)Bracket"")), ""Brkt"" & REGEXEXTRACT(C98,""(\d+)"") & ""mm"", IF(AND(REGEXMATCH(D98,""(?i)-OP""), REGEXMATCH(C98,""(?i)pops"")), ""op"" & REGEXEXTRACT(C98,""(\d+)"") & ""mm"""&", IF(OR(D98=""R-FFTop"", D98=""R-FFBottom"", D98=""R-FFSide""), IF(REGEXMATCH(C98,""(?i)Profiled.*Top|Top.*Profiled""),""pfft"", IF(REGEXMATCH(C98,""(?i)Profiled.*Bottom|Bottom.*Profiled""),""pffb"", IF(REGEXMATCH(C98,""(?i)Squ"&"are""),""sff"",""""))), IF(REGEXMATCH(D98,""(?i)-Rivets""),""Rvt"", IF(REGEXMATCH(D98,""(?i)Silicone""),""300ml"", IF(REGEXMATCH(D98,""(?i)R-Butyl""),""300ml"", IF(REGEXMATCH(D98,""(?i)Fix""),""GenFix"", IF(AND(REGEXMATCH(C98,""(?i)Tim"&"ber""), REGEXMATCH(D98,""(?i)Timber"")),""tp"", IF(AND(REGEXMATCH(C98,""(?i)Vent G1275""), REGEXMATCH(D98,""(?i)Comb FIller"")),""CFV1275"", IF(REGEXMATCH(C98,""(?i)DPC""),""dpc"", IF(REGEXMATCH(C98,""(?i)Concealed Clips""),""ConClips"", I"&"F(REGEXMATCH(D98,""(?i)-Takeoff ea""),""Takeoff ea"", IF(REGEXMATCH(D98,""(?i)-Takeoff LM""),""Takeoff LM"", IF(REGEXMATCH(D98,""(?i)-Takeoff m2""),""Takeoff m2"", IF(D98=""R-TU/TD"",""TU/TD"",""""))))))))))))))))) )))"),"DR3503B55Mag") -> DR3503B55Mag | C98: 0.55mm BMT Coloursteel Maxam eaves flashing (320/3B) | D98: R-Flashing | E98: =VALUE(MID(C98, FIND("(", C98)+1, FIND("/", C98)-FIND("(", C98)-1)) / 1000 -> 0.32 | F98: =IFERROR(__xludf.DUMMYFUNCTION("IFERROR(REGEXEXTRACT(C98,""@\s*(\d+)\s*deg"")&""°"","""") "),"") | H98: =IFERROR(__xludf.DUMMYFUNCTION("IFERROR(REGEXEXTRACT(C98, ""(\d*\.\d+)mm""), """")"),"0.55") -> 0.55 | I98: Mag | J98: Specs | K98: LM | L98: =L105 -> 112.78 | M98: =L98 -> 112.78 | N98: =IFERROR(__xludf.DUMMYFUNCTION("""COMPUTED_VALUE"""),1.0) -> 1 | O98: 1 | P98: 1 | Q98: =M98*N98*O98*P98 -> 112.78 | S98: =R98*Q98 -> 0 | W98: =U98*Q98 -> 0 | X98: =W98/$AC$176/$W$183/Y98 -> #REF! | Y98: 2 | Z98: =Q98/X98 -> #REF! | AB98: =W98+S98 -> 0 | AM98: 112.78 | AN98: Matched | AO98: 0
B99: =IFERROR(__xludf.DUMMYFUNCTION("IFERROR( IF(C99="""","""", IF(OR(REGEXMATCH(D99,""(?i)-Flashing""), REGEXMATCH(D99,""(?i)-EavesGut""), REGEXMATCH(D99,""(?i)Valley"")), ""DR"" & TEXT( ROUNDUP( MIN( VALUE(MID(C99, FIND("&"""("",C99)+1, FIND(""/"",C99)-FIND(""("",C99)-1)), 1200 ) / 50, 0 ) * 50, ""0"" ) & MID(C99, FIND(""/"",C99)+1, FIND("")"",C99)-FIND(""/"",C99)-1) & TEXT(H99*100,""0"") & I99,"&" IF(AND(D99=""Roof Sheet"", REGEXMATCH(C99,""(?i)KS\d{4}[A-Z]{2}"")), REGEXEXTRACT(C99,""(?i)KS\d{4}[A-Z]{2}""), IF(AND(REGEXMATCH(D99,""(?i)-DP""), REGEXMATCH(C99,""(?i)Downpipe"")), ""dp"" & REGEXEXTRACT(C99,""(\d+)"") & ""mm"", "&" IF(AND(REGEXMATCH(D99,""(?i)Bracket""), REGEXMATCH(C99,""(?i)Bracket"")), ""Brkt"" & REGEXEXTRACT(C99,""(\d+)"") & ""mm"", IF(AND(REGEXMATCH(D99,""(?i)-OP""), REGEXMATCH(C99,""(?i)pops"")), ""op"" & REGEXEXTRACT(C99,""(\d+)"") & ""mm"""&", IF(OR(D99=""R-FFTop"", D99=""R-FFBottom"", D99=""R-FFSide""), IF(REGEXMATCH(C99,""(?i)Profiled.*Top|Top.*Profiled""),""pfft"", IF(REGEXMATCH(C99,""(?i)Profiled.*Bottom|Bottom.*Profiled""),""pffb"", IF(REGEXMATCH(C99,""(?i)Squ"&"are""),""sff"",""""))), IF(REGEXMATCH(D99,""(?i)-Rivets""),""Rvt"", IF(REGEXMATCH(D99,""(?i)Silicone""),""300ml"", IF(REGEXMATCH(D99,""(?i)R-Butyl""),""300ml"", IF(REGEXMATCH(D99,""(?i)Fix""),""GenFix"", IF(AND(REGEXMATCH(C99,""(?i)Tim"&"ber""), REGEXMATCH(D99,""(?i)Timber"")),""tp"", IF(AND(REGEXMATCH(C99,""(?i)Vent G1275""), REGEXMATCH(D99,""(?i)Comb FIller"")),""CFV1275"", IF(REGEXMATCH(C99,""(?i)DPC""),""dpc"", IF(REGEXMATCH(C99,""(?i)Concealed Clips""),""ConClips"", I"&"F(REGEXMATCH(D99,""(?i)-Takeoff ea""),""Takeoff ea"", IF(REGEXMATCH(D99,""(?i)-Takeoff LM""),""Takeoff LM"", IF(REGEXMATCH(D99,""(?i)-Takeoff m2""),""Takeoff m2"", IF(D99=""R-TU/TD"",""TU/TD"",""""))))))))))))))))) )))"),"300ml") -> 300ml | C99: Silicone 300ml | D99: R-Silicone | E99: =E98 -> 0.32 | F99: =F98 | J99: No Specs | K99: ea | L99: =M98 -> 112.78 | M99: =(ROUNDDOWN((M98/5.7)+2,0)*E99)/8 -> 0.84 | N99: =IFERROR(__xludf.DUMMYFUNCTION("""COMPUTED_VALUE"""),1.0) -> 1 | O99: 1 | P99: 1 | Q99: =M99*N99*O99*P99 -> 0.84 | S99: =R99*Q99 -> 0 | W99: =U99*Q99 -> 0 | AB99: =W99+S99 -> 0 | AM99: 0.84 | AN99: Matched | AO99: 0
B100: =IFERROR(__xludf.DUMMYFUNCTION("IFERROR( IF(C100="""","""", IF(OR(REGEXMATCH(D100,""(?i)-Flashing""), REGEXMATCH(D100,""(?i)-EavesGut""), REGEXMATCH(D100,""(?i)Valley"")), ""DR"" & TEXT( ROUNDUP( MIN( VALUE(MID(C100, "&"FIND(""("",C100)+1, FIND(""/"",C100)-FIND(""("",C100)-1)), 1200 ) / 50, 0 ) * 50, ""0"" ) & MID(C100, FIND(""/"",C100)+1, FIND("")"",C100)-FIND(""/"",C100)-1) & TEXT(H100*100,""0"") &"&" I100, IF(AND(D100=""Roof Sheet"", REGEXMATCH(C100,""(?i)KS\d{4}[A-Z]{2}"")), REGEXEXTRACT(C100,""(?i)KS\d{4}[A-Z]{2}""), IF(AND(REGEXMATCH(D100,""(?i)-DP""), REGEXMATCH(C100,""(?i)Downpipe"")), ""dp"" & REGEXEXTRACT(C100,""("&"\d+)"") & ""mm"", IF(AND(REGEXMATCH(D100,""(?i)Bracket""), REGEXMATCH(C100,""(?i)Bracket"")), ""Brkt"" & REGEXEXTRACT(C100,""(\d+)"") & ""mm"", IF(AND(REGEXMATCH(D100,""(?i)-OP""), REGEXMATCH(C100,""(?i)pops"")), ""op"" & REGEXEXTRAC"&"T(C100,""(\d+)"") & ""mm"", IF(OR(D100=""R-FFTop"", D100=""R-FFBottom"", D100=""R-FFSide""), IF(REGEXMATCH(C100,""(?i)Profiled.*Top|Top.*Profiled""),""pfft"", IF(REGEXMATCH(C100,""(?i)Profiled.*Bottom|Bottom.*Profiled""),""pffb"", "&" IF(REGEXMATCH(C100,""(?i)Square""),""sff"",""""))), IF(REGEXMATCH(D100,""(?i)-Rivets""),""Rvt"", IF(REGEXMATCH(D100,""(?i)Silicone""),""300ml"", IF(REGEXMATCH(D100,""(?i)R-Butyl""),""300ml"", IF(REGEXMATCH(D100,""(?i)Fix""),""GenFix"","&" IF(AND(REGEXMATCH(C100,""(?i)Timber""), REGEXMATCH(D100,""(?i)Timber"")),""tp"", IF(AND(REGEXMATCH(C100,""(?i)Vent G1275""), REGEXMATCH(D100,""(?i)Comb FIller"")),""CFV1275"", IF(REGEXMATCH(C100,""(?i)DPC""),""dpc"", IF(REGEXMATCH(C100,"""&"(?i)Concealed Clips""),""ConClips"", IF(REGEXMATCH(D100,""(?i)-Takeoff ea""),""Takeoff ea"", IF(REGEXMATCH(D100,""(?i)-Takeoff LM""),""Takeoff LM"", IF(REGEXMATCH(D100,""(?i)-Takeoff m2""),""Takeoff m2"", IF(D100=""R-TU/TD"",""TU/TD"","""""&"))))))))))))))))) )))"),"Rvt") -> Rvt | C100: Rivets | D100: R-Rivets | E100: =E98 -> 0.32 | F100: =F99 | J100: No Specs | K100: ea | L100: =M98 -> 112.78 | M100: =ROUNDUP(((M98/5.7)+1)*(E100/0.05),0) -> 134 | N100: =IFERROR(__xludf.DUMMYFUNCTION("""COMPUTED_VALUE"""),1.0) -> 1 | O100: 1 | P100: 1 | Q100: =M100*N100*O100*P100 -> 134 | S100: =R100*Q100 -> 0 | W100: =U100*Q100 -> 0 | AB100: =W100+S100 -> 0 | AM100: 134 | AN100: Matched | AO100: 0
B101: =IFERROR(__xludf.DUMMYFUNCTION("IFERROR( IF(C101="""","""", IF(OR(REGEXMATCH(D101,""(?i)-Flashing""), REGEXMATCH(D101,""(?i)-EavesGut""), REGEXMATCH(D101,""(?i)Valley"")), ""DR"" & TEXT( ROUNDUP( MIN( VALUE(MID(C101, "&"FIND(""("",C101)+1, FIND(""/"",C101)-FIND(""("",C101)-1)), 1200 ) / 50, 0 ) * 50, ""0"" ) & MID(C101, FIND(""/"",C101)+1, FIND("")"",C101)-FIND(""/"",C101)-1) & TEXT(H101*100,""0"") &"&" I101, IF(AND(D101=""Roof Sheet"", REGEXMATCH(C101,""(?i)KS\d{4}[A-Z]{2}"")), REGEXEXTRACT(C101,""(?i)KS\d{4}[A-Z]{2}""), IF(AND(REGEXMATCH(D101,""(?i)-DP""), REGEXMATCH(C101,""(?i)Downpipe"")), ""dp"" & REGEXEXTRACT(C101,""("&"\d+)"") & ""mm"", IF(AND(REGEXMATCH(D101,""(?i)Bracket""), REGEXMATCH(C101,""(?i)Bracket"")), ""Brkt"" & REGEXEXTRACT(C101,""(\d+)"") & ""mm"", IF(AND(REGEXMATCH(D101,""(?i)-OP""), REGEXMATCH(C101,""(?i)pops"")), ""op"" & REGEXEXTRAC"&"T(C101,""(\d+)"") & ""mm"", IF(OR(D101=""R-FFTop"", D101=""R-FFBottom"", D101=""R-FFSide""), IF(REGEXMATCH(C101,""(?i)Profiled.*Top|Top.*Profiled""),""pfft"", IF(REGEXMATCH(C101,""(?i)Profiled.*Bottom|Bottom.*Profiled""),""pffb"", "&" IF(REGEXMATCH(C101,""(?i)Square""),""sff"",""""))), IF(REGEXMATCH(D101,""(?i)-Rivets""),""Rvt"", IF(REGEXMATCH(D101,""(?i)Silicone""),""300ml"", IF(REGEXMATCH(D101,""(?i)R-Butyl""),""300ml"", IF(REGEXMATCH(D101,""(?i)Fix""),""GenFix"","&" IF(AND(REGEXMATCH(C101,""(?i)Timber""), REGEXMATCH(D101,""(?i)Timber"")),""tp"", IF(AND(REGEXMATCH(C101,""(?i)Vent G1275""), REGEXMATCH(D101,""(?i)Comb FIller"")),""CFV1275"", IF(REGEXMATCH(C101,""(?i)DPC""),""dpc"", IF(REGEXMATCH(C101,"""&"(?i)Concealed Clips""),""ConClips"", IF(REGEXMATCH(D101,""(?i)-Takeoff ea""),""Takeoff ea"", IF(REGEXMATCH(D101,""(?i)-Takeoff LM""),""Takeoff LM"", IF(REGEXMATCH(D101,""(?i)-Takeoff m2""),""Takeoff m2"", IF(D101=""R-TU/TD"",""TU/TD"","""""&"))))))))))))))))) )))"),"GenFix") -> GenFix | C101: Fixings | D101: R-GenFix | F101: =F100 | J101: No Specs | K101: ea | L101: =M98 -> 112.78 | M101: =ROUNDUP(M98/0.6,0)+1 -> 189 | N101: =IFERROR(__xludf.DUMMYFUNCTION("""COMPUTED_VALUE"""),1.0) -> 1 | O101: 1 | P101: 1 | Q101: =M101*N101*O101*P101 -> 189 | S101: =R101*Q101 -> 0 | W101: =U101*Q101 -> 0 | AB101: =W101+S101 -> 0 | AM101: 189 | AN101: Matched | AO101: 0
...

Sheet Template
R1: =IFERROR( IF(B1="", "", VLOOKUP(B1, Data!$B$2:$K$905, 9, FALSE)), "" ) | U1: =IFERROR( IF(B1="", "", VLOOKUP(B1, Data!$B$2:$K$905, 10, FALSE)), "" )
A2: 1
A3: 1
A4: 1
A5: 1
A6: 1
A7: 1
A8: 1 | B8: Project: | C8: =IFERROR(__xludf.DUMMYFUNCTION("IF( Template!D8="""", """", IFERROR( VLOOKUP( Template!D8, IMPORTRANGE( ""1yRKiSiwTOx_Hj9DHPwpMhw9gK8bTY1IeLWGRh62hnCs"", ""Masterlist!E:L"" ), 2, FALSE ) ) ) "),"") | D8: DKR- | K8: DK Roofing BOQ
A9: 1 | B9: Location: | C9: =IFERROR(__xludf.DUMMYFUNCTION("IF( Template!D8="""", """", IFERROR( VLOOKUP( Template!D8, IMPORTRANGE( ""1yRKiSiwTOx_Hj9DHPwpMhw9gK8bTY1IeLWGRh62hnCs"", ""Masterlist!E:L"" ), 3, FALSE ) ) ) "),"")
C10: Building | D10: Timber | I10: 1
A11: 1 | B11: SN | C11: Description | D11: Type | E11: Girth | F11: Degree | G11: Location | H11: BMT | I11: Coating | J11: Specs | K11: Unit | L11: BOQ | M11: TAKEOFF | Q11: Qty | R11: MATERIAL | V11: LABOUR | AD11: TOTAL COST | AE11: For Markup | AF11: factor | AG11: Prelims | AH11: Margin | AJ11: Rate | AK11: Amount
A12: 1 | L12: QTY | M12: Qty | N12: Pitch F | O12: 0 | P12: Unit | R12: Rate | S12: Amount | T12: Total Material Cost | U12: Rate | V12: Amount | W12: Total Labour | AF12: =SUM(AF13) -> 0
A13: 1
A14: 1 | B14: TB | C14: NORTH BOUND ROOFING WORKS | R14: =IFERROR( IF(B14="", "", VLOOKUP(B14, Data!$B$2:$K$905, 9, FALSE)), "" ) | U14: =IFERROR( IF(B14="", "", VLOOKUP(B14, Data!$B$2:$K$905, 10, FALSE)), "" )
A15: 1 | B15: B | C15: Roof Sheeting | R15: =IFERROR( IF(B15="", "", VLOOKUP(B15, Data!$B$2:$K$905, 9, FALSE)), "" ) | U15: =IFERROR( IF(B15="", "", VLOOKUP(B15, Data!$B$2:$K$905, 10, FALSE)), "" )
A16: 1 | C16: Supply and install 0.55mm BMT Dimondek 630 metal roofing, as per plan (A183) | L16: =Q16 -> #REF! | Q16: =Q17+Q22+Q26 -> #REF! | R16: =IFERROR( IF(B16="", "", VLOOKUP(B16, Data!$B$2:$K$905, 9, FALSE)), "" ) | S16: =IFERROR(T16/Q16, 0) -> 0 | T16: =SUM(S17:S29) -> #REF! | U16: =IFERROR( IF(B16="", "", VLOOKUP(B16, Data!$B$2:$K$905, 10, FALSE)), "" ) | V16: =iferror(W16/Q16,"") | W16: =SUM(W17:W29) -> #REF! | X16: =W16/$AC$758/$W$765/$X$755 -> #REF! | Y16: =(T16+W16)=(SUM(AB17:AB29)) -> #REF! | Z16: =(T16+W16)-(SUM(AB17:AB29)) -> #REF! | AD16: =W16+T16 -> #REF! | AE16: =AD16 -> #REF! | AF16: =AE16/$AE$733 -> #REF! | AG16: =AF16*$AG$740 -> #REF! | AH16: =AF16*$AG$743 -> #REF! | AJ16: =ROUND(AK16/L16,2) -> #REF! | AK16: =ROUND(AH16+AG16+AD16,2) -> #REF!
B17: DRDek630Mag055 | C17: 0.55mm BMT Dimondek 630 metal roofing @ 3 deg - at 1200mm purlin spacing | D17: R-Sheeting | E17: =IFERROR(__xludf.DUMMYFUNCTION("IF($B$15:$B1153="""","""", VLOOKUP( $B$15:$B1153, QUERY( IMPORTRANGE(""1Ag27m9YF5mMfJh2E6NipJDFvPLlDI1p-s_1XEnzMHcc"",""Merge!F2:R""), ""select Col1, Col11"", 0 ), 2, FALSE ) ) "),"#REF!") -> #REF! | G17: North Bound | H17: =IFERROR(__xludf.DUMMYFUNCTION("IFERROR(REGEXEXTRACT(C17, ""(\d*\.\d+)mm""), """")"),"0.55") -> 0.55 | I17: Mag | J17: Specs | K17: =IFERROR( IF(B17="", "", VLOOKUP(B17, Data!$B$2:$K$905, 7, FALSE)), "" ) | L17: 24216.66 | M17: =L17*E17 -> #REF! | N17: =IFERROR(__xludf.DUMMYFUNCTION("IF( AND( IFERROR(REGEXEXTRACT(C17,""@\s*(\d+(?:\.\d+)?)\s*deg""),"""")<>"""", F17<>"""" ), ""Pls Confirm °"", IF( IFERROR(REGEXEXTRACT(C17,""@\s*(\d+(?:\.\d+)?)\s*deg""),"""")<>"""", 1/COS(RADIANS(REGEXEXTRACT(C17,""@\s*(\d+(?:\.\d"&"+)?)\s*deg""))), IF( F17<>"""", IF( ISNUMBER(SEARCH(""|"",F17)), 1/COS( ATAN( TAN(RADIANS(VALUE(INDEX(SPLIT(F17,""|""),1)))) * TAN(RADIANS(VALUE(INDEX(SPLIT(F17,""|""),2)))) / "&" SQRT( TAN(RADIANS(VALUE(INDEX(SPLIT(F17,""|""),1))))^2 + TAN(RADIANS(VALUE(INDEX(SPLIT(F17,""|""),2))))^2 ) ) ), 1/COS(RADIANS(VALUE(F17))) ), 1 ) ) )"),1.001372345997921) -> 1.0013723 | O17: 1 | P17: 1 | Q17: =M17*N17*O17*P17 -> #REF! | R17: =IFERROR( IF(B17="", "", VLOOKUP(B17, Data!$B$2:$K$905, 9, FALSE)), "" ) | S17: =R17*Q17 -> #REF! | U17: =IFERROR( IF(B17="", "", VLOOKUP(B17, Data!$B$2:$K$905, 10, FALSE)), "" ) | W17: =U17*Q17 -> #REF! | AB17: =W17+S17 -> #REF!
B18: DRDek630Clip | C18: Dimondek 630 Clip | D18: R-Clips | E18: 1.2 | H18: =IFERROR(__xludf.DUMMYFUNCTION("IFERROR(REGEXEXTRACT(C18, ""(\d*\.\d+)mm""), """")"),"") | J18: No Specs | K18: =IFERROR( IF(B18="", "", VLOOKUP(B18, Data!$B$2:$K$905, 7, FALSE)), "" ) | M18: =roundup(L17/E18,0)+1 -> 20182 | N18: =N17 -> 1.0013723 | O18: 1 | P18: 1 | Q18: =M18*N18*O18*P18 -> 20209.697 | R18: =IFERROR( IF(B18="", "", VLOOKUP(B18, Data!$B$2:$K$905, 9, FALSE)), "" ) | S18: =R18*Q18 -> 0 | U18: =IFERROR( IF(B18="", "", VLOOKUP(B18, Data!$B$2:$K$905, 10, FALSE)), "" ) | W18: =U18*Q18 -> 0 | AB18: =W18+S18 -> 0
B19: DRDek630T17 | C19: Wafer 10x65 T17 SD No Neo | D19: R-Fixings | J19: No Specs | K19: =IFERROR( IF(B19="", "", VLOOKUP(B19, Data!$B$2:$K$905, 7, FALSE)), "" ) | M19: =M18*2 -> 40364 | N19: =N18 -> 1.0013723 | O19: 1 | P19: 1 | Q19: =M19*N19*O19*P19 -> 40419.393 | R19: =IFERROR( IF(B19="", "", VLOOKUP(B19, Data!$B$2:$K$905, 9, FALSE)), "" ) | S19: =R19*Q19 -> 0 | U19: =IFERROR( IF(B19="", "", VLOOKUP(B19, Data!$B$2:$K$905, 10, FALSE)), "" ) | W19: =U19*Q19 -> 0 | AB19: =W19+S19 -> 0
A20: Ma | B20: 630WindClamp | C20: Windclamp | D20: R-Windclamp | J20: No Specs | K20: =IFERROR( IF(B20="", "", VLOOKUP(B20, Data!$B$2:$K$905, 7, FALSE)), "" ) | M20: =235+235 -> 470 | N20: =N19 -> 1.0013723 | O20: 1 | P20: 1 | Q20: =M20*N20*O20*P20 -> 470.645 | R20: =IFERROR( IF(B20="", "", VLOOKUP(B20, Data!$B$2:$K$905, 9, FALSE)), "" ) | S20: =R20*Q20 -> 0 | U20: =IFERROR( IF(B20="", "", VLOOKUP(B20, Data!$B$2:$K$905, 10, FALSE)), "" ) | W20: =U20*Q20 -> 0
B22: DRDek630Mag055 | C22: 0.55mm BMT Dimondek 630 metal roofing @ 3 deg - at 900mm purlin spacing | D22: R-Sheeting | E22: =IFERROR(__xludf.DUMMYFUNCTION("IF($B$15:$B1152="""","""", VLOOKUP( $B$15:$B1152, QUERY( IMPORTRANGE(""1Ag27m9YF5mMfJh2E6NipJDFvPLlDI1p-s_1XEnzMHcc"",""Merge!F2:R""), ""select Col1, Col11"", 0 ), 2, FALSE ) ) "),"#REF!") -> #REF! | G22: North Bound | H22: =IFERROR(__xludf.DUMMYFUNCTION("IFERROR(REGEXEXTRACT(C22, ""(\d*\.\d+)mm""), """")"),"0.55") -> 0.55 | I22: Mag | J22: Specs | K22: =IFERROR( IF(B22="", "", VLOOKUP(B22, Data!$B$2:$K$905, 7, FALSE)), "" ) | L22: =2101.32+ 1258.92 -> 3360.24 | M22: =L22*E22 -> #REF! | N22: =IFERROR(__xludf.DUMMYFUNCTION("IF( AND( IFERROR(REGEXEXTRACT(C22,""@\s*(\d+(?:\.\d+)?)\s*deg""),"""")<>"""", F22<>"""" ), ""Pls Confirm °"", IF( IFERROR(REGEXEXTRACT(C22,""@\s*(\d+(?:\.\d+)?)\s*deg""),"""")<>"""", 1/COS(RADIANS(REGEXEXTRACT(C22,""@\s*(\d+(?:\.\d"&"+)?)\s*deg""))), IF( F22<>"""", IF( ISNUMBER(SEARCH(""|"",F22)), 1/COS( ATAN( TAN(RADIANS(VALUE(INDEX(SPLIT(F22,""|""),1)))) * TAN(RADIANS(VALUE(INDEX(SPLIT(F22,""|""),2)))) / "&" SQRT( TAN(RADIANS(VALUE(INDEX(SPLIT(F22,""|""),1))))^2 + TAN(RADIANS(VALUE(INDEX(SPLIT(F22,""|""),2))))^2 ) ) ), 1/COS(RADIANS(VALUE(F22))) ), 1 ) ) )"),1.001372345997921) -> 1.0013723 | O22: 1 | P22: 1 | Q22: =M22*N22*O22*P22 -> #REF! | R22: =IFERROR( IF(B22="", "", VLOOKUP(B22, Data!$B$2:$K$905, 9, FALSE)), "" ) | S22: =R22*Q22 -> #REF! | U22: =IFERROR( IF(B22="", "", VLOOKUP(B22, Data!$B$2:$K$905, 10, FALSE)), "" ) | W22: =U22*Q22 -> #REF! | AB22: =W22+S22 -> #REF!
B23: DRDek630Clip | C23: Dimondek 630 Clip | D23: R-Clips | E23: 0.9 | H23: =IFERROR(__xludf.DUMMYFUNCTION("IFERROR(REGEXEXTRACT(C23, ""(\d*\.\d+)mm""), """")"),"") | J23: No Specs | K23: =IFERROR( IF(B23="", "", VLOOKUP(B23, Data!$B$2:$K$905, 7, FALSE)), "" ) | M23: =roundup(L22/E23,0)+1 -> 3735 | N23: =N22 -> 1.0013723 | O23: 1 | P23: 1 | Q23: =M23*N23*O23*P23 -> 3740.1257 | R23: =IFERROR( IF(B23="", "", VLOOKUP(B23, Data!$B$2:$K$905, 9, FALSE)), "" ) | S23: =R23*Q23 -> 0 | U23: =IFERROR( IF(B23="", "", VLOOKUP(B23, Data!$B$2:$K$905, 10, FALSE)), "" ) | W23: =U23*Q23 -> 0 | AB23: =W23+S23 -> 0
B24: DRDek630T17 | C24: Wafer 10x65 T17 SD No Neo | D24: R-Fixings | J24: No Specs | K24: =IFERROR( IF(B24="", "", VLOOKUP(B24, Data!$B$2:$K$905, 7, FALSE)), "" ) | M24: =M23*2 -> 7470 | N24: =N23 -> 1.0013723 | O24: 1 | P24: 1 | Q24: =M24*N24*O24*P24 -> 7480.2514 | R24: =IFERROR( IF(B24="", "", VLOOKUP(B24, Data!$B$2:$K$905, 9, FALSE)), "" ) | S24: =R24*Q24 -> 0 | U24: =IFERROR( IF(B24="", "", VLOOKUP(B24, Data!$B$2:$K$905, 10, FALSE)), "" ) | W24: =U24*Q24 -> 0 | AB24: =W24+S24 -> 0
B26: DRDek630Mag055 | C26: 0.55mm BMT Dimondek 630 metal roofing @ 3 deg - at 700mm purlin spacing | D26: R-Sheeting | E26: =IFERROR(__xludf.DUMMYFUNCTION("IF($B$15:$B1152="""","""", VLOOKUP( $B$15:$B1152, QUERY( IMPORTRANGE(""1Ag27m9YF5mMfJh2E6NipJDFvPLlDI1p-s_1XEnzMHcc"",""Merge!F2:R""), ""select Col1, Col11"", 0 ), 2, FALSE ) ) "),"#REF!") -> #REF! | G26: North Bound | H26: =IFERROR(__xludf.DUMMYFUNCTION("IFERROR(REGEXEXTRACT(C26, ""(\d*\.\d+)mm""), """")"),"0.55") -> 0.55 | I26: Mag | J26: Specs | K26: =IFERROR( IF(B26="", "", VLOOKUP(B26, Data!$B$2:$K$905, 7, FALSE)), "" ) | L26: =1666.08+ 1696.5 -> 3362.58 | M26: =L26*E26 -> #REF! | N26: =IFERROR(__xludf.DUMMYFUNCTION("IF( AND( IFERROR(REGEXEXTRACT(C26,""@\s*(\d+(?:\.\d+)?)\s*deg""),"""")<>"""", F26<>"""" ), ""Pls Confirm °"", IF( IFERROR(REGEXEXTRACT(C26,""@\s*(\d+(?:\.\d+)?)\s*deg""),"""")<>"""", 1/COS(RADIANS(REGEXEXTRACT(C26,""@\s*(\d+(?:\.\d"&"+)?)\s*deg""))), IF( F26<>"""", IF( ISNUMBER(SEARCH(""|"",F26)), 1/COS( ATAN( TAN(RADIANS(VALUE(INDEX(SPLIT(F26,""|""),1)))) * TAN(RADIANS(VALUE(INDEX(SPLIT(F26,""|""),2)))) / "&" SQRT( TAN(RADIANS(VALUE(INDEX(SPLIT(F26,""|""),1))))^2 + TAN(RADIANS(VALUE(INDEX(SPLIT(F26,""|""),2))))^2 ) ) ), 1/COS(RADIANS(VALUE(F26))) ), 1 ) ) )"),1.001372345997921) -> 1.0013723 | O26: 1 | P26: 1 | Q26: =M26*N26*O26*P26 -> #REF! | R26: =IFERROR( IF(B26="", "", VLOOKUP(B26, Data!$B$2:$K$905, 9, FALSE)), "" ) | S26: =R26*Q26 -> #REF! | U26: =IFERROR( IF(B26="", "", VLOOKUP(B26, Data!$B$2:$K$905, 10, FALSE)), "" ) | W26: =U26*Q26 -> #REF! | AB26: =W26+S26 -> #REF!
B27: DRDek630Clip | C27: Dimondek 630 Clip | D27: R-Clips | E27: 0.7 | H27: =IFERROR(__xludf.DUMMYFUNCTION("IFERROR(REGEXEXTRACT(C27, ""(\d*\.\d+)mm""), """")"),"") | J27: No Specs | K27: =IFERROR( IF(B27="", "", VLOOKUP(B27, Data!$B$2:$K$905, 7, FALSE)), "" ) | M27: =roundup(L26/E27,0)+1 -> 4805 | N27: =N26 -> 1.0013723 | O27: 1 | P27: 1 | Q27: =M27*N27*O27*P27 -> 4811.5941 | R27: =IFERROR( IF(B27="", "", VLOOKUP(B27, Data!$B$2:$K$905, 9, FALSE)), "" ) | S27: =R27*Q27 -> 0 | U27: =IFERROR( IF(B27="", "", VLOOKUP(B27, Data!$B$2:$K$905, 10, FALSE)), "" ) | W27: =U27*Q27 -> 0 | AB27: =W27+S27 -> 0
B28: DRDek630T17 | C28: Wafer 10x65 T17 SD No Neo | D28: R-Fixings | J28: No Specs | K28: =IFERROR( IF(B28="", "", VLOOKUP(B28, Data!$B$2:$K$905, 7, FALSE)), "" ) | M28: =M27*2 -> 9610 | N28: =N27 -> 1.0013723 | O28: 1 | P28: 1 | Q28: =M28*N28*O28*P28 -> 9623.1882 | R28: =IFERROR( IF(B28="", "", VLOOKUP(B28, Data!$B$2:$K$905, 9, FALSE)), "" ) | S28: =R28*Q28 -> 0 | U28: =IFERROR( IF(B28="", "", VLOOKUP(B28, Data!$B$2:$K$905, 10, FALSE)), "" ) | W28: =U28*Q28 -> 0 | AB28: =W28+S28 -> 0
R29: =IFERROR( IF(B29="", "", VLOOKUP(B29, Data!$B$2:$K$905, 9, FALSE)), "" ) | U29: =IFERROR( IF(B29="", "", VLOOKUP(B29, Data!$B$2:$K$905, 10, FALSE)), "" ) | AB29: =W29+S29 -> 0
A30: 1 | B30: B | C30: Underlay | R30: =IFERROR( IF(B30="", "", VLOOKUP(B30, Data!$B$2:$K$905, 9, FALSE)), "" ) | U30: =IFERROR( IF(B30="", "", VLOOKUP(B30, Data!$B$2:$K$905, 10, FALSE)), "" )
A31: 1 | C31: Supply and install underlay | L31: =Q31 -> #REF! | Q31: =Q32 -> #REF! | R31: =IFERROR( IF(B31="", "", VLOOKUP(B31, Data!$B$2:$K$905, 9, FALSE)), "" ) | S31: =IFERROR(T31/Q31, 0) -> 0 | T31: =SUM(S32:S34) -> #REF! | U31: =IFERROR( IF(B31="", "", VLOOKUP(B31, Data!$B$2:$K$905, 10, FALSE)), "" ) | V31: =iferror(W31/Q31,"") | W31: =SUM(W32:W34) -> #REF! | X31: =W31/$AC$758/$W$765/$X$755 -> #REF! | Y31: =(T31+W31)=(SUM(AB32:AB34)) -> #REF! | Z31: =(T31+W31)-(SUM(AB32:AB34)) -> #REF! | AD31: =W31+T31 -> #REF! | AE31: =AD31 -> #REF! | AF31: =AE31/$AE$733 -> #REF! | AG31: =AF31*$AG$740 -> #REF! | AH31: =AF31*$AG$743 -> #REF! | AJ31: =ROUND(AK31/L31,2) -> #REF! | AK31: =ROUND(AH31+AG31+AD31,2) -> #REF!
A32: Ma | B32: TKUF405 | C32: Thermakraft Covertek 405 self supporting fire retardant | D32: R-Underlay | E32: =IFERROR(__xludf.DUMMYFUNCTION("IF($B$15:$B927="""","""", VLOOKUP( $B$15:$B927, QUERY( IMPORTRANGE(""1Ag27m9YF5mMfJh2E6NipJDFvPLlDI1p-s_1XEnzMHcc"",""Merge!F2:R""), ""select Col1, Col11"", 0 ), 2, FALSE ) ) "),"#REF!") -> #REF! | G32: North Bound | H32: =IFERROR(__xludf.DUMMYFUNCTION("IFERROR(REGEXEXTRACT(C32, ""(\d*\.\d+)mm""), """")"),"") | J32: Specs | K32: =IFERROR( IF(B32="", "", VLOOKUP(B32, Data!$B$2:$K$905, 7, FALSE)), "" ) | L32: =Q16 -> #REF! | M32: =((L32)/(E32-0.15))*0.15+(L32) -> #REF! | N32: =IFERROR(__xludf.DUMMYFUNCTION("IF(B32="""", """", IFERROR(1 / COS(RADIANS(REGEXEXTRACT(F32,""(\d+)""))), 1))"),1.0) -> 1 | O32: 1 | P32: 1 | Q32: =M32*N32*O32*P32 -> #REF! | R32: =IFERROR( IF(B32="", "", VLOOKUP(B32, Data!$B$2:$K$905, 9, FALSE)), "" ) | S32: =R32*Q32 -> #REF! | U32: =IFERROR( IF(B32="", "", VLOOKUP(B32, Data!$B$2:$K$905, 10, FALSE)), "" ) | W32: =U32*Q32 -> #REF! | AB32: =W32+S32 -> #REF!
A33: Ma | B33: TKGenTape | C33: Thermakraft White General Purpose Tape (60 mm × 66 m) | D33: R-UTape | E33: =E32 -> #REF! | H33: =IFERROR(__xludf.DUMMYFUNCTION("IF($B$15:$B927="""","""", VLOOKUP( $B$15:$B927, QUERY( IMPORTRANGE(""1Ag27m9YF5mMfJh2E6NipJDFvPLlDI1p-s_1XEnzMHcc"",""Merge!F2:R""), ""select Col1, Col11"", 0 ), 2, FALSE ) ) "),"#REF!") -> #REF! | J33: No Specs | K33: =IFERROR( IF(B33="", "", VLOOKUP(B33, Data!$B$2:$K$905, 7, FALSE)), "" ) | M33: =M32/E33/H33 -> #REF! | N33: =N32 -> 1 | O33: 1 | P33: 1 | Q33: =M33*N33*O33*P33 -> #REF! | R33: =IFERROR( IF(B33="", "", VLOOKUP(B33, Data!$B$2:$K$905, 9, FALSE)), "" ) | S33: =R33*Q33 -> #REF! | U33: =IFERROR( IF(B33="", "", VLOOKUP(B33, Data!$B$2:$K$905, 10, FALSE)), "" ) | W33: =U33*Q33 -> #REF! | AB33: =W33+S33 -> #REF!
K34: =IFERROR( IF(B34="", "", VLOOKUP(B34, Data!$B$2:$K$905, 7, FALSE)), "" ) | N34: =IFERROR(__xludf.DUMMYFUNCTION("IF(B34="""", """", IFERROR(1 / COS(RADIANS(REGEXEXTRACT(F34,""(\d+)""))), 1))"),"") | R34: =IFERROR( IF(B34="", "", VLOOKUP(B34, Data!$B$2:$K$905, 9, FALSE)), "" ) | U34: =IFERROR( IF(B34="", "", VLOOKUP(B34, Data!$B$2:$K$905, 10, FALSE)), "" )
A35: 1 | C35: Safety mesh | R35: =IFERROR( IF(B35="", "", VLOOKUP(B35, Data!$B$2:$K$905, 9, FALSE)), "" ) | U35: =IFERROR( IF(B35="", "", VLOOKUP(B35, Data!$B$2:$K$905, 10, FALSE)), "" )
A36: 1 | C36: Supply and install safety mesh | L36: =Q36 -> #REF! | Q36: =Q37 -> #REF! | R36: =IFERROR( IF(B36="", "", VLOOKUP(B36, Data!$B$2:$K$905, 9, FALSE)), "" ) | S36: =iferror(T36/Q36,"") | T36: =SUM(S37:S38) -> #REF! | U36: =IFERROR( IF(B36="", "", VLOOKUP(B36, Data!$B$2:$K$905, 10, FALSE)), "" ) | V36: =iferror(W36/Q36,"") | W36: =SUM(W37:W38) -> #REF! | X36: =W36/$AC$758/$W$765/$X$755 -> #REF! | Y36: =(T36+W36)=(SUM(AB37:AB38)) -> #REF! | Z36: =(T36+W36)-(SUM(AB37:AB38)) -> #REF! | AD36: =W36+T36 -> #REF! | AE36: =AD36 -> #REF! | AF36: =AE36/$AE$733 -> #REF! | AG36: =AF36*$AG$740 -> #REF! | AH36: =AF36*$AG$743 -> #REF! | AJ36: =ROUND(AK36/L36,2) -> #REF! | AK36: =ROUND(AH36+AG36+AD36,2) -> #REF!
A37: Ma | B37: Safetymesh | C37: Safety mesh | D37: R-Safety Mesh | G37: North Bound | H37: =IFERROR(__xludf.DUMMYFUNCTION("IFERROR(REGEXEXTRACT(C37, ""(\d*\.\d+)mm""), """")"),"") | J37: No Specs | K37: m2 | M37: =M32 -> #REF! | N37: =IFERROR(__xludf.DUMMYFUNCTION("IF(B37="""", """", IFERROR(1 / COS(RADIANS(REGEXEXTRACT(F37,""(\d+)""))), 1))"),1.0) -> 1 | O37: 1 | P37: 1 | Q37: =M37*N37*O37*P37 -> #REF! | R37: =IFERROR( IF(B37="", "", VLOOKUP(B37, Data!$B$2:$K$905, 9, FALSE)), "" ) | S37: =R37*Q37 -> #REF! | U37: =IFERROR( IF(B37="", "", VLOOKUP(B37, Data!$B$2:$K$905, 10, FALSE)), "" ) | W37: =U37*Q37 -> #REF! | AB37: =W37+S37 -> #REF!
N38: =IFERROR(__xludf.DUMMYFUNCTION("IF(B38="""", """", IFERROR(1 / COS(RADIANS(REGEXEXTRACT(F38,""(\d+)""))), 1))"),"") | R38: =IFERROR( IF(B38="", "", VLOOKUP(B38, Data!$B$2:$K$905, 9, FALSE)), "" ) | U38: =IFERROR( IF(B38="", "", VLOOKUP(B38, Data!$B$2:$K$905, 10, FALSE)), "" ) | AB38: =W38+S38 -> 0
A39: 1 | B39: B | C39: Flashing/Capping | R39: =IFERROR( IF(B39="", "", VLOOKUP(B39, Data!$B$2:$K$905, 9, FALSE)), "" ) | U39: =IFERROR( IF(B39="", "", VLOOKUP(B39, Data!$B$2:$K$905, 10, FALSE)), "" )
A40: 1 | C40: Supply and install 0.55mm BMT ridge cap flashing (530/3B), as per detail A (A-3000) | L40: =Q40 -> 0 | Q40: =Q41 -> 0 | R40: =IFERROR( IF(B40="", "", VLOOKUP(B40, Data!$B$2:$K$905, 9, FALSE)), "" ) | S40: =IFERROR(T40/Q40, 0) -> 0 | T40: =SUM(S41:S48) -> 0 | U40: =IFERROR( IF(B40="", "", VLOOKUP(B40, Data!$B$2:$K$905, 10, FALSE)), "" ) | V40: =W40/Q40 -> #DIV/0! | W40: =SUM(W41:W48) -> 0 | X40: =W40/$AC$135/$W$142/$X$132 -> #DIV/0! | Y40: =(T40+W40)=(SUM(AB41:AB48)) -> TRUE | Z40: =(T40+W40)-(SUM(AB41:AB48)) -> 0 | AD40: =W40+T40 -> 0 | AE40: =AD40 -> 0 | AF40: =AE40/$AE$110 -> #DIV/0! | AG40: =AF40*$AG$117 -> #DIV/0! | AH40: =AF40*$AG$120 -> #DIV/0! | AJ40: =ROUND(AK40/L40,2) -> #DIV/0! | AK40: =ROUND(AH40+AG40+AD40,2) -> #DIV/0!
A41: Fl | B41: =IFERROR(__xludf.DUMMYFUNCTION("IFERROR( IF(C41="""","""", IF(OR(REGEXMATCH(D41,""(?i)-Flashing""), REGEXMATCH(D41,""(?i)-EavesGut""), REGEXMATCH(D41,""(?i)Valley"")), ""DR"" & TEXT( ROUNDUP( VALUE(MID(C41, FIND(""("",C41)+1, FIND(""/"","&"C41)-FIND(""("",C41)-1)) / 50, 0) * 50, ""0"" ) & MID(C41, FIND(""/"",C41)+1, FIND("")"",C41)-FIND(""/"",C41)-1) & TEXT(H41*100,""0"") & I41, IF(AND(D41=""Roof Sheet"", REGEXMATCH(C41,""(?i)KS\d{4}[A-Z]{2}"""&")), REGEXEXTRACT(C41,""(?i)KS\d{4}[A-Z]{2}""), IF(AND(REGEXMATCH(D41,""(?i)-DP""), REGEXMATCH(C41,""(?i)Downpipe"")), ""dp"" & REGEXEXTRACT(C41,""(\d+)"") & ""mm"", IF(AND(REGEXMATCH(D41,""(?i)Bracket""), REGEXMATCH(C41,""(?i)Bracket"&""")), ""Brkt"" & REGEXEXTRACT(C41,""(\d+)"") & ""mm"", IF(AND(REGEXMATCH(D41,""(?i)-OP""), REGEXMATCH(C41,""(?i)pops"")), ""op"" & REGEXEXTRACT(C41,""(\d+)"") & ""mm"", IF(OR(D41=""R-FFTop"", D41=""R-FFBottom"", D41=""R-FFSide""), "&" IF(REGEXMATCH(C41,""(?i)Profiled.*Top|Top.*Profiled""),""pfft"", IF(REGEXMATCH(C41,""(?i)Profiled.*Bottom|Bottom.*Profiled""),""pffb"", IF(REGEXMATCH(C41,""(?i)Square""),""sff"",""""))), IF(REGEXMATCH(D41,""(?i)-Rivets""),""Rvt"""&", IF(REGEXMATCH(D41,""(?i)Silicone""),""300ml"", IF(REGEXMATCH(D41,""(?i)R-Butyl""),""300ml"", IF(REGEXMATCH(D41,""(?i)Fix""),""GenFix"", IF(AND(REGEXMATCH(C41,""(?i)Timber""), REGEXMATCH(D41,""(?i)Timber"")),""tp"", IF(AND(REGEXMATCH("&"C41,""(?i)Vent G1275""), REGEXMATCH(D41,""(?i)Comb FIller"")),""CFV1275"", IF(REGEXMATCH(C41,""(?i)DPC""),""dpc"", IF(REGEXMATCH(C41,""(?i)Concealed Clips""),""ConClips"", IF(REGEXMATCH(D41,""(?i)-Takeoff ea""),""Takeoff ea"", IF(REGEXMATC"&"H(D41,""(?i)-Takeoff LM""),""Takeoff LM"", IF(REGEXMATCH(D41,""(?i)-Takeoff m2""),""Takeoff m2"", IF(D41=""R-TU/TD"",""TU/TD"",""""))))))))))))))))) )))"),"DR5503B55Mag") -> DR5503B55Mag | C41: 0.55mm BMT ridge cap flashing (530/3B) | D41: R-Flashing | E41: =VALUE(MID(C41, FIND("(", C41)+1, FIND("/", C41)-FIND("(", C41)-1)) / 1000 -> 0.53 | H41: =IFERROR(__xludf.DUMMYFUNCTION("IFERROR(REGEXEXTRACT(C41, ""(\d*\.\d+)mm""), """")"),"0.55") -> 0.55 | I41: Mag | J41: Specs | K41: =IFERROR( IF(B41="", "", VLOOKUP(B41, Data!$B$2:$K$905, 7, FALSE)), "" ) | N41: =IFERROR(__xludf.DUMMYFUNCTION("IF( AND( IFERROR(REGEXEXTRACT(C41,""@\s*(\d+(?:\.\d+)?)\s*deg""),"""")<>"""", F41<>"""" ), ""Pls Confirm °"", IF( IFERROR(REGEXEXTRACT(C41,""@\s*(\d+(?:\.\d+)?)\s*deg""),"""")<>"""", 1/COS(RADIANS(REGEXEXTRACT(C41,""@\s*(\d+(?:\.\d"&"+)?)\s*deg""))), IF( F41<>"""", IF( ISNUMBER(SEARCH(""|"",F41)), 1/COS( ATAN( TAN(RADIANS(VALUE(INDEX(SPLIT(F41,""|""),1)))) * TAN(RADIANS(VALUE(INDEX(SPLIT(F41,""|""),2)))) / "&" SQRT( TAN(RADIANS(VALUE(INDEX(SPLIT(F41,""|""),1))))^2 + TAN(RADIANS(VALUE(INDEX(SPLIT(F41,""|""),2))))^2 ) ) ), 1/COS(RADIANS(VALUE(F41))) ), 1 ) ) )"),1.0) -> 1 | O41: 1 | P41: 1 | Q41: =M41*N41*O41*P41 -> 0 | R41: =IFERROR( IF(B41="", "", VLOOKUP(B41, Data!$B$2:$K$905, 9, FALSE)), "" ) | S41: =R41*Q41 -> 0 | U41: =IFERROR( IF(B41="", "", VLOOKUP(B41, Data!$B$2:$K$905, 10, FALSE)), "" ) | W41: =U41*Q41 -> 0 | AB41: =W41+S41 -> 0
B42: =IFERROR(__xludf.DUMMYFUNCTION("IFERROR( IF(C42="""","""", IF(OR(REGEXMATCH(D42,""(?i)-Flashing""), REGEXMATCH(D42,""(?i)-EavesGut""), REGEXMATCH(D42,""(?i)Valley"")), ""DR"" & TEXT( ROUNDUP( MIN( VALUE(MID(C42, FIND("&"""("",C42)+1, FIND(""/"",C42)-FIND(""("",C42)-1)), 1200 ) / 50, 0 ) * 50, ""0"" ) & MID(C42, FIND(""/"",C42)+1, FIND("")"",C42)-FIND(""/"",C42)-1) & TEXT(H42*100,""0"") & I42,"&" IF(AND(D42=""Roof Sheet"", REGEXMATCH(C42,""(?i)KS\d{4}[A-Z]{2}"")), REGEXEXTRACT(C42,""(?i)KS\d{4}[A-Z]{2}""), IF(AND(REGEXMATCH(D42,""(?i)-DP""), REGEXMATCH(C42,""(?i)Downpipe"")), ""dp"" & REGEXEXTRACT(C42,""(\d+)"") & ""mm"", "&" IF(AND(REGEXMATCH(D42,""(?i)Bracket""), REGEXMATCH(C42,""(?i)Bracket"")), ""Brkt"" & REGEXEXTRACT(C42,""(\d+)"") & ""mm"", IF(AND(REGEXMATCH(D42,""(?i)-OP""), REGEXMATCH(C42,""(?i)pops"")), ""op"" & REGEXEXTRACT(C42,""(\d+)"") & ""mm"""&", IF(OR(D42=""R-FFTop"", D42=""R-FFBottom"", D42=""R-FFSide""), IF(REGEXMATCH(C42,""(?i)Profiled.*Top|Top.*Profiled""),""pfft"", IF(REGEXMATCH(C42,""(?i)Profiled.*Bottom|Bottom.*Profiled""),""pffb"", IF(REGEXMATCH(C42,""(?i)Squ"&"are""),""sff"",""""))), IF(REGEXMATCH(D42,""(?i)-Rivets""),""Rvt"", IF(REGEXMATCH(D42,""(?i)Silicone""),""300ml"", IF(REGEXMATCH(D42,""(?i)R-Butyl""),""300ml"", IF(REGEXMATCH(D42,""(?i)Fix""),""GenFix"", IF(AND(REGEXMATCH(C42,""(?i)Tim"&"ber""), REGEXMATCH(D42,""(?i)Timber"")),""tp"", IF(AND(REGEXMATCH(C42,""(?i)Vent G1275""), REGEXMATCH(D42,""(?i)Comb FIller"")),""CFV1275"", IF(REGEXMATCH(C42,""(?i)DPC""),""dpc"", IF(REGEXMATCH(C42,""(?i)Concealed Clips""),""ConClips"", I"&"F(REGEXMATCH(D42,""(?i)-Takeoff ea""),""Takeoff ea"", IF(REGEXMATCH(D42,""(?i)-Takeoff LM""),""Takeoff LM"", IF(REGEXMATCH(D42,""(?i)-Takeoff m2""),""Takeoff m2"", IF(D42=""R-TU/TD"",""TU/TD"",""""))))))))))))))))) )))"),"300ml") -> 300ml | C42: Silicone 300ml | D42: R-Silicone | E42: =E41 -> 0.53 | F42: =IFERROR(__xludf.DUMMYFUNCTION("iferror(ROUND( DEGREES( ATAN( TAN(RADIANS(VALUE(INDEX(SPLIT(F41,""|""),1)))) * TAN(RADIANS(VALUE(INDEX(SPLIT(F41,""|""),2)))) / SQRT( TAN(RADIANS(VALUE(INDEX(SPLIT(F41,""|""),1))))^2 + TAN(RADIANS(VALUE(INDEX("&"SPLIT(F41,""|""),2))))^2 ) ) ), 2 ))"),"") | H42: =IFERROR(__xludf.DUMMYFUNCTION("IFERROR(REGEXEXTRACT(C42, ""(\d*\.\d+)mm""), """")"),"") | J42: No Specs | K42: =IFERROR( IF(B42="", "", VLOOKUP(B42, Data!$B$2:$K$905, 7, FALSE)), "" ) | M42: =(ROUNDDOWN((M41/5.7)+2,0)*E42)/8 -> 0.1325 | N42: =if(B42="","",(if(N41="",N40,N41))) -> 1 | O42: 1 | P42: 1 | Q42: =M42*N42*O42*P42 -> 0.1325 | R42: =IFERROR( IF(B42="", "", VLOOKUP(B42, Data!$B$2:$K$905, 9, FALSE)), "" ) | S42: =R42*Q42 -> 0 | U42: =IFERROR( IF(B42="", "", VLOOKUP(B42, Data!$B$2:$K$905, 10, FALSE)), "" ) | W42: =U42*Q42 -> 0 | AB42: =W42+S42 -> 0
B43: =IFERROR(__xludf.DUMMYFUNCTION("IFERROR( IF(C43="""","""", IF(OR(REGEXMATCH(D43,""(?i)-Flashing""), REGEXMATCH(D43,""(?i)-EavesGut""), REGEXMATCH(D43,""(?i)Valley"")), ""DR"" & TEXT( ROUNDUP( MIN( VALUE(MID(C43, FIND("&"""("",C43)+1, FIND(""/"",C43)-FIND(""("",C43)-1)), 1200 ) / 50, 0 ) * 50, ""0"" ) & MID(C43, FIND(""/"",C43)+1, FIND("")"",C43)-FIND(""/"",C43)-1) & TEXT(H43*100,""0"") & I43,"&" IF(AND(D43=""Roof Sheet"", REGEXMATCH(C43,""(?i)KS\d{4}[A-Z]{2}"")), REGEXEXTRACT(C43,""(?i)KS\d{4}[A-Z]{2}""), IF(AND(REGEXMATCH(D43,""(?i)-DP""), REGEXMATCH(C43,""(?i)Downpipe"")), ""dp"" & REGEXEXTRACT(C43,""(\d+)"") & ""mm"", "&" IF(AND(REGEXMATCH(D43,""(?i)Bracket""), REGEXMATCH(C43,""(?i)Bracket"")), ""Brkt"" & REGEXEXTRACT(C43,""(\d+)"") & ""mm"", IF(AND(REGEXMATCH(D43,""(?i)-OP""), REGEXMATCH(C43,""(?i)pops"")), ""op"" & REGEXEXTRACT(C43,""(\d+)"") & ""mm"""&", IF(OR(D43=""R-FFTop"", D43=""R-FFBottom"", D43=""R-FFSide""), IF(REGEXMATCH(C43,""(?i)Profiled.*Top|Top.*Profiled""),""pfft"", IF(REGEXMATCH(C43,""(?i)Profiled.*Bottom|Bottom.*Profiled""),""pffb"", IF(REGEXMATCH(C43,""(?i)Squ"&"are""),""sff"",""""))), IF(REGEXMATCH(D43,""(?i)-Rivets""),""Rvt"", IF(REGEXMATCH(D43,""(?i)Silicone""),""300ml"", IF(REGEXMATCH(D43,""(?i)R-Butyl""),""300ml"", IF(REGEXMATCH(D43,""(?i)Fix""),""GenFix"", IF(AND(REGEXMATCH(C43,""(?i)Tim"&"ber""), REGEXMATCH(D43,""(?i)Timber"")),""tp"", IF(AND(REGEXMATCH(C43,""(?i)Vent G1275""), REGEXMATCH(D43,""(?i)Comb FIller"")),""CFV1275"", IF(REGEXMATCH(C43,""(?i)DPC""),""dpc"", IF(REGEXMATCH(C43,""(?i)Concealed Clips""),""ConClips"", I"&"F(REGEXMATCH(D43,""(?i)-Takeoff ea""),""Takeoff ea"", IF(REGEXMATCH(D43,""(?i)-Takeoff LM""),""Takeoff LM"", IF(REGEXMATCH(D43,""(?i)-Takeoff m2""),""Takeoff m2"", IF(D43=""R-TU/TD"",""TU/TD"",""""))))))))))))))))) )))"),"Rvt") -> Rvt | C43: Rivets | D43: R-Rivets | E43: =E41 -> 0.53 | H43: =IFERROR(__xludf.DUMMYFUNCTION("IFERROR(REGEXEXTRACT(C43, ""(\d*\.\d+)mm""), """")"),"") | J43: No Specs | K43: =IFERROR( IF(B43="", "", VLOOKUP(B43, Data!$B$2:$K$905, 7, FALSE)), "" ) | M43: =ROUNDUP(((M41/5.7)+1)*(E43/0.05),0) -> 11 | N43: =if(B43="","",(if(N42="",N41,N42))) -> 1 | O43: 1 | P43: 1 | Q43: =M43*N43*O43*P43 -> 11 | R43: =IFERROR( IF(B43="", "", VLOOKUP(B43, Data!$B$2:$K$905, 9, FALSE)), "" ) | S43: =R43*Q43 -> 0 | U43: =IFERROR( IF(B43="", "", VLOOKUP(B43, Data!$B$2:$K$905, 10, FALSE)), "" ) | W43: =U43*Q43 -> 0 | AB43: =W43+S43 -> 0
